Workbook
Name ActualNumberOfPayments: IFERROR(IF('HOA Savings'!LoanIsGood,IF('HOA Savings'!PaymentsPerYear=1,1,MATCH(0.01,'HOA Savings'!End_Bal,-1)+1)),"")
Name ActualNumberOfPayments: IFERROR(IF(LoanIsGood,IF(PaymentsPerYear=1,1,MATCH(0.01,End_Bal,-1)+1)),"")
Name ColumnTitle1: #REF!
Name ColumnTitle1: #REF!
Name End_Bal: #REF!
Name End_Bal: #REF!
Name ExtraPayments: #REF!
Name ExtraPayments: #REF!
Name InterestRate: #REF!
Name InterestRate: #REF!
Name IQ_CH: 110000
Name IQ_CQ: 5000
Name IQ_CY: 10000
Name IQ_DAILY: 500000
Name IQ_FH: 100000
Name IQ_FQ: 500
Name IQ_FY: 1000
Name IQ_LTM: 2000
Name IQ_MONTH: 15000
Name IQ_NTM: 6000
Name IQ_WEEK: 50000
Name IQ_YTD: 3000
Name LastCol: MATCH(REPT("z",255),#REF!)
Name LastCol: MATCH(REPT("z",255),#REF!)
Name LastRow: MATCH(9.99E+307,#REF!)
Name LastRow: MATCH(9.99E+307,#REF!)
Name LenderName: #REF!
Name LenderName: #REF!
Name LoanAmount: #REF!
Name LoanAmount: #REF!
Name LoanIsGood: (#REF!*#REF!*#REF!*#REF!)>0
Name LoanIsGood: (#REF!*#REF!*#REF!*#REF!)>0
Name LoanPeriod: #REF!
Name LoanPeriod: #REF!
Name LoanStartDate: #REF!
Name LoanStartDate: #REF!
Name PaymentsPerYear: #REF!
Name PaymentsPerYear: #REF!
Name PrintArea_SET: OFFSET(#REF!,,,'HOA Savings'!LastRow,'HOA Savings'!LastCol)
Name PrintArea_SET: OFFSET(#REF!,,,LastRow,LastCol)
Name roundOpt: #REF!
Name roundOpt: #REF!
Name RowTitleRegion1..E9: #REF!
Name RowTitleRegion1..E9: #REF!
Name RowTitleRegion2..I7: #REF!
Name RowTitleRegion2..I7: #REF!
Name RowTitleRegion3..E9: #REF!
Name RowTitleRegion3..E9: #REF!
Name RowTitleRegion4..H9: #REF!
Name RowTitleRegion4..H9: #REF!
Name ScheduledNumberOfPayments: #REF!
Name ScheduledNumberOfPayments: #REF!
Name ScheduledPayment: #REF!
Name ScheduledPayment: #REF!
Name TotalEarlyPayments: SUM(#REF!)
Name TotalEarlyPayments: SUM(#REF!)
Name TotalInterest: SUM(#REF!)
Name TotalInterest: SUM(#REF!)
Name valuevx: 42.314159

Sheet Main Budget
B1: Jon Kemp Personal Budget Plan: Bi-weekly
B5: Monthly Expenses
E6: Monthly | F6: Gym Portion | G6: Gym Portion Per Paycheck (Bi-Weekly) | H6: Jon Portion | I6: Jon Portion Per Pay Check (15th and Last Day of month) | J6: Account | K6: Payment Date | L6: Debit/Credit | M6: Payment Source | N6: Notes
B7: Cell Phone Service | E7: -30 | F7: 0 | G7: 0 | H7: =E7-F7 -> -30 | I7: =H7/2 -> -15 | J7: USAA Bills | K7: 15 | L7: Debit | M7: Wells Fargo Credit | N7: Auto Pay set for 17th of each month.
B8: Gym Membership | E8: -44.99 | F8: =-(11.25*2) -> -22.5 | G8: -11.25 | H8: =E8-F8 -> -22.49 | I8: =H8/2 -> -11.245 | J8: USAA Bills | K8: 17 | L8: Debit | M8: Bank of America VISA | N8: Auto Pay set for 18th of each month.
D9: Extra to Bill checking | E9: -13.84 | F9: 0 | G9: 0 | H9: =E9-F9 -> -13.84 | I9: =E9/2 -> -6.92 | L9: Credit
B10: Insurance (Vehicle) | E10: =(-622*2)/12 -> -103.66667 | F10: 0 | G10: 0 | H10: =E10-F10 -> -103.66667 | I10: =E10/2 -> -51.833333 | J10: USAA Bills | K10: Semi Annual | L10: Debit | N10: $622 Due July 1 and Jan 1
E11: =SUM(E7:E10) -> -192.49667 | F11: =SUM(F7:F10) -> -22.5 | G11: =SUM(G7:G10) -> -11.25 | H11: =SUM(H7:H10) -> -169.99667 | I11: =SUM(I7:I10) -> -84.998333
E13: Monthly | F13: Ronnie Portion | H13: Jon Portion | I13: Per Pay Check | J13: Account | K13: Payment Date | L13: Debit/Credit | M13: Payment Source | O13: Notes
B14: Emory Parc - HOA Dues | E14: =-((2350+3.95)/6) -> -392.325 | F14: =(E14/2) -> -196.1625 | H14: =E14/2 -> -196.1625 | I14: =H14/2 -> -98.08125 | J14: USAA HOA Savings | K14: Jan 8, July 8 | L14: Debit | M14: USAA HOA Savings | O14: Paid Semi Annual
B15: Emory Parc - HOA Extra Payments | E15: -50 | F15: =E15/2 -> -25 | H15: =E15/2 -> -25 | I15: =H15/2 -> -12.5 | J15: USAA HOA Savings | L15: Credit
B16: Mortgage - Extra Payments for Random Expenses | E16: =-3200-SUM(E14:E15)-SUM(E17:E22) -> -312.465 | F16: =E16/2 -> -156.2325 | H16: =E16/2 -> -156.2325 | I16: =H16/2 -> -78.11625 | J16: USAA Mortgage | L16: Credit
B17: Emory Parc - Mortgage | E17: -2036.51 | F17: =E17/2 -> -1018.255 | H17: =E17/2 -> -1018.255 | I17: =H17/2 -> -509.1275 | J17: USAA Mortgage | K17: 7 | L17: Debit | M17: Auto Pay Mortgage Checking
B18: Youtube TV Zack | E18: -36.5 | F18: =E18/2 -> -18.25 | H18: =E18/2 -> -18.25 | I18: =H18/2 -> -9.125 | J18: USAA Mortgage | K18: 9 | L18: Debit | M18: Mortgage Checking | O18: Must Pay via ZELLE to Zack
B19: Water/Sewer | E19: -70 | F19: =E19/2 -> -35 | H19: =E19/2 -> -35 | I19: =H19/2 -> -17.5 | J19: USAA Mortgage | K19: 3 | L19: Debit | M19: Mortgage Checking | O19: Must pay through USAA bill Pay
B20: Georgia Power - Electricity | E20: -175 | F20: =E20/2 -> -87.5 | H20: =E20/2 -> -87.5 | I20: =H20/2 -> -43.75 | J20: USAA Mortgage | K20: 1 | L20: Debit | M20: Mortgage Checking | O20: Auto Pay from USAA Mortgage Checking
B21: Natural Gas | E21: -76 | F21: =E21/2 -> -38 | H21: =E21/2 -> -38 | I21: =H21/2 -> -19 | J21: USAA Mortgage | K21: 26 | L21: Debit | M21: Mortgage Checking | O21: Auto Pay set for 1st of each Month
B22: Comcast Cable | E22: -51.2 | F22: =E22/2 -> -25.6 | H22: =E22/2 -> -25.6 | I22: =H22/2 -> -12.8 | J22: USAA Mortgage | K22: 12 | L22: Debit | M22: Mortgage Checking | O22: Auto Pay set for 11th of each Month
E23: =F23+H23 -> -3200 | F23: =(SUM(F14:F22)) -> -1600 | H23: =SUM(H14:H22) -> -1600 | I23: =SUM(I14:I22) -> -800
B25: Total Expenses | E25: =E23+E11 -> -3392.4967 | I25: =I23+I11 -> -884.99833
D28: Ronnie Portion | E28: Jon Portion (Per Paycheck) | F28: Gym Portion (Bi Weekly)
B29: Amount To USAA Bill Checking - 7071 | D29: 0 | E29: =-I11 -> 84.998333 | F29: 11.25
B30: Amount to USAA Mortgage Checking - 3223 | D30: =-SUM(F16:F22) -> 1378.8375 | E30: =-SUM(I16:I22) -> 689.41875 | F30: 0
B31: Amount To USAA HOA Savings - 9575 | D31: =-F14-F15 -> 221.1625 | E31: =-I14-I15 -> 110.58125 | F31: 0
D32: =SUM(D29:D31) -> 1600 | E32: =SUM(E29:E31) -> 884.99833 | F32: =SUM(F29:F31) -> 11.25

Sheet Mortgage Checking
A1: Date | B1: Total Beg Balance | C1: Regular Beg Balance | D1: Extra Beg Balance | E1: Jon Credit | F1: Ronnie Credit | G1: Jon Extra Credit | H1: Ronnie Extra Credit | I1: Mortgage | J1: Water (GA Utility) (AutoPay Checking) | K1: Electric: Georgia Power (AutoPay Checking) | L1: Natural Gas (AutoPay Checking : Energy Inc Geo) | M1: Comcast (AutoPay Checking) | N1: YouTube TV (Zelle to Zack) | O1: Other $ | P1: Regular Ending Balance | Q1: Extra Ending Balance | R1: Total End Balance | S1: Other Description
A2: 46022 | B2: 2591.06 | C2: 0 | E2: 0 | F2: 0 | I2: 0 | J2: 0 | K2: 0 | L2: 0 | M2: 0 | N2: 0 | P2: 1861.9725 | Q2: 729.085 | R2: 2591.0575
A3: 46023 | B3: =R2 -> 2591.0575 | C3: 0 | E3: 0 | F3: 0 | I3: 0 | J3: 0 | K3: -175 | L3: 0 | M3: 0 | N3: 0 | P3: 1861.9725 | Q3: 729.085 | R3: 2591.0575
A4: 46024 | B4: =R3 -> 2591.0575 | C4: 0 | E4: 0 | F4: 0 | I4: 0 | J4: 0 | K4: 0 | L4: 0 | M4: 0 | N4: 0 | P4: 1861.9725 | Q4: 729.085 | R4: 2591.0575
A5: 46025 | B5: =R4 -> 2591.0575 | C5: 0 | E5: 0 | F5: 0 | I5: 0 | J5: -78.34 | K5: 0 | L5: 0 | M5: 0 | N5: 0 | P5: 1861.9725 | Q5: 729.085 | R5: 2591.0575
A6: 46026 | B6: =R5 -> 2591.0575 | C6: 0 | E6: 0 | F6: 0 | I6: 0 | J6: 0 | K6: 0 | L6: 0 | M6: 0 | N6: 0 | P6: 1861.9725 | Q6: 729.085 | R6: 2591.0575
A7: 46027 | B7: =R6 -> 2591.0575 | C7: 0 | E7: 0 | F7: 0 | I7: 0 | J7: 0 | K7: 0 | L7: 0 | M7: 0 | N7: -36.5 | P7: 1861.9725 | Q7: 729.085 | R7: 2591.0575
A8: 46028 | B8: =R7 -> 2591.0575 | C8: 0 | E8: 0 | F8: 0 | I8: 0 | J8: 0 | K8: 0 | L8: 0 | M8: 0 | N8: 0 | P8: 1861.9725 | Q8: 729.085 | R8: 2591.0575
A9: 46029 | B9: =R8 -> 2591.0575 | C9: 0 | E9: 0 | F9: 0 | I9: -2036.51 | J9: 0 | K9: 0 | L9: 0 | M9: 0 | N9: 0 | P9: 1861.9725 | Q9: 729.085 | R9: 2591.0575
A10: 46030 | B10: =R9 -> 2591.0575 | C10: 0 | E10: 0 | F10: 0 | I10: 0 | J10: 0 | K10: 0 | L10: 0 | M10: 0 | N10: 0 | P10: 1861.9725 | Q10: 729.085 | R10: 2591.0575
A11: 46031 | B11: =R10 -> 2591.0575 | C11: 0 | E11: 0 | F11: 0 | I11: 0 | J11: 0 | K11: 0 | L11: 0 | M11: 0 | N11: 0 | P11: 1861.9725 | Q11: 729.085 | R11: 2591.0575
A12: 46032 | B12: =R11 -> 2591.0575 | C12: 0 | E12: 0 | F12: 0 | I12: 0 | J12: 0 | K12: 0 | L12: 0 | M12: 0 | N12: 0 | P12: 1861.9725 | Q12: 729.085 | R12: 2591.0575
A13: 46033 | B13: =R12 -> 2591.0575 | C13: 0 | E13: 0 | F13: 0 | I13: 0 | J13: 0 | K13: 0 | L13: 0 | M13: 0 | N13: 0 | P13: 1861.9725 | Q13: 729.085 | R13: 2591.0575
A14: 46034 | B14: =R13 -> 2591.0575 | C14: 0 | E14: 0 | F14: 0 | I14: 0 | J14: 0 | K14: 0 | L14: 0 | M14: -51.2 | N14: 0 | P14: 1861.9725 | Q14: 729.085 | R14: 2591.0575
... A20: 46040 | B20: =R19 -> 2591.0575 | C20: 0 | E20: 0 | F20: 0 | I20: 0 | J20: 0 | K20: 0 | L20: 0 | M20: 0 | N20: 0 | P20: 1861.9725 | Q20: 729.085 | R20: 2591.0575
A21: 46041 | B21: =R20 -> 2591.0575 | C21: 0 | E21: 0 | F21: 0 | I21: 0 | J21: 0 | K21: 0 | L21: 0 | M21: 0 | N21: 0 | O21: 0.02 | P21: 1861.9725 | Q21: 729.085 | R21: 2591.0575
A22: 46042 | B22: =R21 -> 2591.0575 | C22: 0 | E22: 0 | F22: 0 | I22: 0 | J22: 0 | K22: 0 | L22: 0 | M22: 0 | N22: 0 | P22: 1861.9725 | Q22: 729.085 | R22: 2591.0575
A23: 46043 | B23: =R22 -> 2591.0575 | C23: 0 | E23: 0 | F23: 0 | I23: 0 | J23: 0 | K23: 0 | L23: 0 | M23: 0 | N23: 0 | P23: 1861.9725 | Q23: 729.085 | R23: 2591.0575
A24: 46044 | B24: =R23 -> 2591.0575 | C24: 0 | E24: 0 | F24: 0 | I24: 0 | J24: 0 | K24: 0 | L24: 0 | M24: 0 | N24: 0 | P24: 1861.9725 | Q24: 729.085 | R24: 2591.0575
A25: 46045 | B25: =R24 -> 2591.0575 | C25: 0 | E25: 0 | F25: 0 | I25: 0 | J25: 0 | K25: 0 | L25: 0 | M25: 0 | N25: 0 | P25: 1861.9725 | Q25: 729.085 | R25: 2591.0575
A26: 46046 | B26: =R25 -> 2591.0575 | C26: 0 | E26: 0 | F26: 0 | I26: 0 | J26: 0 | K26: 0 | L26: 0 | M26: 0 | N26: 0 | P26: 1861.9725 | Q26: 729.085 | R26: 2591.0575
A27: 46047 | B27: =R26 -> 2591.0575 | C27: 0 | E27: 0 | F27: 0 | I27: 0 | J27: 0 | K27: 0 | L27: 0 | M27: 0 | N27: 0 | P27: 1861.9725 | Q27: 729.085 | R27: 2591.0575
A28: 46048 | B28: =R27 -> 2591.0575 | C28: 0 | E28: 0 | F28: 0 | I28: 0 | J28: 0 | K28: 0 | L28: -57.89 | M28: 0 | N28: 0 | P28: 1861.9725 | Q28: 729.085 | R28: 2591.0575
A29: 46049 | B29: =R28 -> 2591.0575 | C29: 0 | E29: 0 | F29: 1378 | I29: 0 | J29: 0 | K29: 0 | L29: 0 | M29: 0 | N29: 0 | P29: 1861.9725 | Q29: 729.085 | R29: 2591.0575
A30: 46050 | B30: =R29 -> 2591.0575 | C30: 0 | E30: 0 | F30: 0 | I30: 0 | J30: 0 | K30: 0 | L30: 0 | M30: 0 | N30: 0 | P30: 1861.9725 | Q30: 729.085 | R30: 2591.0575
A31: 46051 | B31: =R30 -> 2591.0575 | C31: 0 | E31: 0 | F31: 0 | I31: 0 | J31: 0 | K31: 0 | L31: 0 | M31: 0 | N31: 0 | P31: 1861.9725 | Q31: 729.085 | R31: 2591.0575
A32: 46052 | B32: =R31 -> 2591.0575 | C32: 0 | E32: 689 | F32: 0 | I32: 0 | J32: 0 | K32: 0 | L32: 0 | M32: 0 | N32: 0 | P32: 1861.9725 | Q32: 729.085 | R32: 2591.0575
A33: 46053 | B33: =R32 -> 2591.0575 | C33: 0 | E33: 0 | F33: 0 | I33: 0 | J33: 0 | K33: 0 | L33: 0 | M33: 0 | N33: 0 | P33: 1861.9725 | Q33: 729.085 | R33: 2591.0575
A34: 46054 | B34: =R33 -> 2591.0575 | C34: 0 | E34: 0 | F34: 0 | I34: 0 | J34: 0 | K34: -175 | L34: 0 | M34: 0 | N34: 0 | P34: 1861.9725 | Q34: 729.085 | R34: 2591.0575
A35: 46055 | B35: =R34 -> 2591.0575 | C35: 2328.4625 | D35: 1300 | E35: 0 | F35: 0 | I35: 0 | J35: 0 | K35: 0 | L35: 0 | M35: 0 | N35: 0 | P35: 2328.4625 | Q35: 1300 | R35: 3628.4625
A36: 46056 | B36: =R35 -> 3628.4625 | C36: =P35 -> 2328.4625 | D36: =Q35 -> 1300 | E36: 0 | F36: 0 | G36: 0 | H36: 0 | I36: 0 | J36: -81.97 | K36: 0 | L36: 0 | M36: 0 | N36: 0 | P36: =C36+(SUM(I36:N36)+(SUM(E36:F36))) -> 2246.4925 | Q36: =D36+G36+H36+O36 -> 1300 | R36: =P36+Q36 -> 3546.4925
A37: 46057 | B37: =R36 -> 3546.4925 | C37: =P36 -> 2246.4925 | D37: =Q36 -> 1300 | E37: 0 | F37: 0 | G37: 0 | H37: 0 | I37: 0 | J37: 0 | K37: 0 | L37: 0 | M37: 0 | N37: 0 | P37: =C37+(SUM(I37:N37)+(SUM(E37:F37))) -> 2246.4925 | Q37: =D37+G37+H37+O37 -> 1300 | R37: =P37+Q37 -> 3546.4925
A38: 46058 | B38: =R37 -> 3546.4925 | C38: =P37 -> 2246.4925 | D38: =Q37 -> 1300 | E38: 0 | F38: 0 | G38: 0 | H38: 0 | I38: 0 | J38: 0 | K38: 0 | L38: 0 | M38: 0 | N38: 0 | P38: =C38+(SUM(I38:N38)+(SUM(E38:F38))) -> 2246.4925 | Q38: =D38+G38+H38+O38 -> 1300 | R38: =P38+Q38 -> 3546.4925
A39: 46059 | B39: =R38 -> 3546.4925 | C39: =P38 -> 2246.4925 | D39: =Q38 -> 1300 | E39: 0 | F39: 0 | G39: 0 | H39: 0 | I39: 0 | J39: 0 | K39: 0 | L39: 0 | M39: 0 | N39: 0 | P39: =C39+(SUM(I39:N39)+(SUM(E39:F39))) -> 2246.4925 | Q39: =D39+G39+H39+O39 -> 1300 | R39: =P39+Q39 -> 3546.4925
A40: 46060 | B40: =R39 -> 3546.4925 | C40: =P39 -> 2246.4925 | D40: =Q39 -> 1300 | E40: 0 | F40: 0 | G40: 0 | H40: 0 | I40: -2036.51 | J40: 0 | K40: 0 | L40: 0 | M40: 0 | N40: 0 | P40: =C40+(SUM(I40:N40)+(SUM(E40:F40))) -> 209.9825 | Q40: =D40+G40+H40+O40 -> 1300 | R40: =P40+Q40 -> 1509.9825
A41: 46061 | B41: =R40 -> 1509.9825 | C41: =P40 -> 209.9825 | D41: =Q40 -> 1300 | E41: 0 | F41: 0 | G41: 0 | H41: 0 | I41: 0 | J41: 0 | K41: 0 | L41: 0 | M41: 0 | N41: 0 | P41: =C41+(SUM(I41:N41)+(SUM(E41:F41))) -> 209.9825 | Q41: =D41+G41+H41+O41 -> 1300 | R41: =P41+Q41 -> 1509.9825
A42: 46062 | B42: =R41 -> 1509.9825 | C42: =P41 -> 209.9825 | D42: =Q41 -> 1300 | E42: 0 | F42: 0 | G42: 0 | H42: 0 | I42: 0 | J42: 0 | K42: 0 | L42: 0 | M42: 0 | N42: 0 | P42: =C42+(SUM(I42:N42)+(SUM(E42:F42))) -> 209.9825 | Q42: =D42+G42+H42+O42 -> 1300 | R42: =P42+Q42 -> 1509.9825
A43: 46063 | B43: =R42 -> 1509.9825 | C43: =P42 -> 209.9825 | D43: =Q42 -> 1300 | E43: 0 | F43: 0 | G43: 0 | H43: 0 | I43: 0 | J43: 0 | K43: 0 | L43: 0 | M43: 0 | N43: 0 | P43: =C43+(SUM(I43:N43)+(SUM(E43:F43))) -> 209.9825 | Q43: =D43+G43+H43+O43 -> 1300 | R43: =P43+Q43 -> 1509.9825
A44: 46064 | B44: =R43 -> 1509.9825 | C44: =P43 -> 209.9825 | D44: =Q43 -> 1300 | E44: 0 | F44: 0 | G44: 0 | H44: 0 | I44: 0 | J44: 0 | K44: 0 | L44: 0 | M44: 0 | N44: 0 | P44: =C44+(SUM(I44:N44)+(SUM(E44:F44))) -> 209.9825 | Q44: =D44+G44+H44+O44 -> 1300 | R44: =P44+Q44 -> 1509.9825
A45: 46065 | B45: =R44 -> 1509.9825 | C45: =P44 -> 209.9825 | D45: =Q44 -> 1300 | E45: 0 | F45: 0 | G45: 0 | H45: 0 | I45: 0 | J45: 0 | K45: 0 | L45: 0 | M45: -51.2 | N45: 0 | P45: =C45+(SUM(I45:N45)+(SUM(E45:F45))) -> 158.7825 | Q45: =D45+G45+H45+O45 -> 1300 | R45: =P45+Q45 -> 1458.7825
A46: 46066 | B46: =R45 -> 1458.7825 | C46: =P45 -> 158.7825 | D46: =Q45 -> 1300 | E46: 0 | F46: 0 | G46: 0 | H46: 0 | I46: 0 | J46: 0 | K46: 0 | L46: 0 | M46: 0 | N46: 0 | P46: =C46+(SUM(I46:N46)+(SUM(E46:F46))) -> 158.7825 | Q46: =D46+G46+H46+O46 -> 1300 | R46: =P46+Q46 -> 1458.7825
A47: 46067 | B47: =R46 -> 1458.7825 | C47: =P46 -> 158.7825 | D47: =Q46 -> 1300 | E47: 611.315 | F47: 0 | G47: 77.685 | H47: 0 | I47: 0 | J47: 0 | K47: 0 | L47: 0 | M47: 0 | N47: 0 | P47: =C47+(SUM(I47:N47)+(SUM(E47:F47))) -> 770.0975 | Q47: =D47+G47+H47+O47 -> 1377.685 | R47: =P47+Q47 -> 2147.7825
A48: 46068 | B48: =R47 -> 2147.7825 | C48: =P47 -> 770.0975 | D48: =Q47 -> 1377.685 | E48: 0 | F48: 0 | G48: 0 | H48: 0 | I48: 0 | J48: 0 | K48: 0 | L48: 0 | M48: 0 | N48: -36.5 | P48: =C48+(SUM(I48:N48)+(SUM(E48:F48))) -> 733.5975 | Q48: =D48+G48+H48+O48 -> 1377.685 | R48: =P48+Q48 -> 2111.2825
A49: 46069 | B49: =R48 -> 2111.2825 | C49: =P48 -> 733.5975 | D49: =Q48 -> 1377.685 | E49: 0 | F49: 0 | G49: 0 | H49: 0 | I49: 0 | J49: 0 | K49: 0 | L49: 0 | M49: 0 | N49: 0 | O49: -1004.99 | P49: =C49+(SUM(I49:N49)+(SUM(E49:F49))) -> 733.5975 | Q49: =D49+G49+H49+O49 -> 372.695 | R49: =P49+Q49 -> 1106.2925 | S49: Mattress
A50: 46070 | B50: =R49 -> 1106.2925 | C50: =P49 -> 733.5975 | D50: =Q49 -> 372.695 | E50: 0 | F50: 0 | G50: 0 | H50: 0 | I50: 0 | J50: 0 | K50: 0 | L50: 0 | M50: 0 | N50: 0 | O50: 0.02 | P50: =C50+(SUM(I50:N50)+(SUM(E50:F50))) -> 733.5975 | Q50: =D50+G50+H50+O50 -> 372.715 | R50: =P50+Q50 -> 1106.3125
A51: 46071 | B51: =R50 -> 1106.3125 | C51: =P50 -> 733.5975 | D51: =Q50 -> 372.715 | E51: 0 | F51: 0 | G51: 0 | H51: 0 | I51: 0 | J51: 0 | K51: 0 | L51: 0 | M51: 0 | N51: 0 | P51: =C51+(SUM(I51:N51)+(SUM(E51:F51))) -> 733.5975 | Q51: =D51+G51+H51+O51 -> 372.715 | R51: =P51+Q51 -> 1106.3125
A52: 46072 | B52: =R51 -> 1106.3125 | C52: =P51 -> 733.5975 | D52: =Q51 -> 372.715 | E52: 0 | F52: 0 | G52: 0 | H52: 0 | I52: 0 | J52: 0 | K52: 0 | L52: 0 | M52: 0 | N52: 0 | P52: =C52+(SUM(I52:N52)+(SUM(E52:F52))) -> 733.5975 | Q52: =D52+G52+H52+O52 -> 372.715 | R52: =P52+Q52 -> 1106.3125
A53: 46073 | B53: =R52 -> 1106.3125 | C53: =P52 -> 733.5975 | D53: =Q52 -> 372.715 | E53: 0 | F53: 0 | G53: 0 | H53: 0 | I53: 0 | J53: 0 | K53: 0 | L53: 0 | M53: 0 | N53: 0 | P53: =C53+(SUM(I53:N53)+(SUM(E53:F53))) -> 733.5975 | Q53: =D53+G53+H53+O53 -> 372.715 | R53: =P53+Q53 -> 1106.3125
A54: 46074 | B54: =R53 -> 1106.3125 | C54: =P53 -> 733.5975 | D54: =Q53 -> 372.715 | E54: 0 | F54: 0 | G54: 0 | H54: 0 | I54: 0 | J54: 0 | K54: 0 | L54: 0 | M54: 0 | N54: 0 | P54: =C54+(SUM(I54:N54)+(SUM(E54:F54))) -> 733.5975 | Q54: =D54+G54+H54+O54 -> 372.715 | R54: =P54+Q54 -> 1106.3125
A55: 46075 | B55: =R54 -> 1106.3125 | C55: =P54 -> 733.5975 | D55: =Q54 -> 372.715 | E55: 0 | F55: 0 | G55: 0 | H55: 0 | I55: 0 | J55: 0 | K55: 0 | L55: 0 | M55: 0 | N55: 0 | P55: =C55+(SUM(I55:N55)+(SUM(E55:F55))) -> 733.5975 | Q55: =D55+G55+H55+O55 -> 372.715 | R55: =P55+Q55 -> 1106.3125
A56: 46076 | B56: =R55 -> 1106.3125 | C56: =P55 -> 733.5975 | D56: =Q55 -> 372.715 | E56: 0 | F56: 0 | G56: 0 | H56: 0 | I56: 0 | J56: 0 | K56: 0 | L56: 0 | M56: 0 | N56: 0 | P56: =C56+(SUM(I56:N56)+(SUM(E56:F56))) -> 733.5975 | Q56: =D56+G56+H56+O56 -> 372.715 | R56: =P56+Q56 -> 1106.3125
A57: 46077 | B57: =R56 -> 1106.3125 | C57: =P56 -> 733.5975 | D57: =Q56 -> 372.715 | E57: 0 | F57: 0 | G57: 0 | H57: 0 | I57: 0 | J57: 0 | K57: 0 | L57: 0 | M57: 0 | N57: 0 | P57: =C57+(SUM(I57:N57)+(SUM(E57:F57))) -> 733.5975 | Q57: =D57+G57+H57+O57 -> 372.715 | R57: =P57+Q57 -> 1106.3125
A58: 46078 | B58: =R57 -> 1106.3125 | C58: =P57 -> 733.5975 | D58: =Q57 -> 372.715 | E58: 0 | F58: 0 | G58: 0 | H58: 0 | I58: 0 | J58: 0 | K58: 0 | L58: 0 | M58: 0 | N58: 0 | P58: =C58+(SUM(I58:N58)+(SUM(E58:F58))) -> 733.5975 | Q58: =D58+G58+H58+O58 -> 372.715 | R58: =P58+Q58 -> 1106.3125
A59: 46079 | B59: =R58 -> 1106.3125 | C59: =P58 -> 733.5975 | D59: =Q58 -> 372.715 | E59: 0 | F59: 0 | G59: 0 | H59: 0 | I59: 0 | J59: 0 | K59: 0 | L59: -117.13 | M59: 0 | N59: 0 | P59: =C59+(SUM(I59:N59)+(SUM(E59:F59))) -> 616.4675 | Q59: =D59+G59+H59+O59 -> 372.715 | R59: =P59+Q59 -> 989.1825
A60: 46080 | B60: =R59 -> 989.1825 | C60: =P59 -> 616.4675 | D60: =Q59 -> 372.715 | E60: 611.315 | F60: 1222.63 | G60: 77.685 | H60: 155.37 | I60: 0 | J60: 0 | K60: 0 | L60: 0 | M60: 0 | N60: 0 | P60: =C60+(SUM(I60:N60)+(SUM(E60:F60))) -> 2450.4125 | Q60: =D60+G60+H60+O60 -> 605.77 | R60: =P60+Q60 -> 3056.1825
A61: 46081 | B61: =R60 -> 3056.1825 | C61: =P60 -> 2450.4125 | D61: =Q60 -> 605.77 | E61: 0 | F61: 0 | G61: 0 | H61: 0 | I61: 0 | J61: 0 | K61: 0 | L61: 0 | M61: 0 | N61: 0 | P61: =C61+(SUM(I61:N61)+(SUM(E61:F61))) -> 2450.4125 | Q61: =D61+G61+H61+O61 -> 605.77 | R61: =P61+Q61 -> 3056.1825
A62: 46082 | B62: =R61 -> 3056.1825 | C62: =P61 -> 2450.4125 | D62: =Q61 -> 605.77 | E62: 0 | F62: 0 | G62: 0 | H62: 0 | I62: 0 | J62: 0 | K62: -175 | L62: 0 | M62: 0 | N62: 0 | P62: =C62+(SUM(I62:N62)+(SUM(E62:F62))) -> 2275.4125 | Q62: =D62+G62+H62+O62 -> 605.77 | R62: =P62+Q62 -> 2881.1825
... A69: 46089 | B69: =R68 -> 731.5325 | C69: =P68 -> 125.7625 | D69: =Q68 -> 605.77 | E69: 0 | F69: 0 | G69: 0 | H69: 0 | I69: 0 | J69: 0 | K69: 0 | L69: 0 | M69: 0 | N69: 0 | P69: =C69+(SUM(I69:N69)+(SUM(E69:F69))) -> 125.7625 | Q69: =D69+G69+H69+O69 -> 605.77 | R69: =P69+Q69 -> 731.5325
A70: 46090 | B70: =R69 -> 731.5325 | C70: =P69 -> 125.7625 | D70: =Q69 -> 605.77 | E70: 0 | F70: 0 | G70: 0 | H70: 0 | I70: 0 | J70: 0 | K70: 0 | L70: 0 | M70: 0 | N70: 0 | O70: -237.05 | P70: =C70+(SUM(I70:N70)+(SUM(E70:F70))) -> 125.7625 | Q70: =D70+G70+H70+O70 -> 368.72 | R70: =P70+Q70 -> 494.4825 | S70: Temper Mattress
A71: 46091 | B71: =R70 -> 494.4825 | C71: =P70 -> 125.7625 | D71: =Q70 -> 368.72 | E71: 0 | F71: 0 | G71: 0 | H71: 0 | I71: 0 | J71: 0 | K71: 0 | L71: 0 | M71: 0 | N71: 0 | O71: -80 | P71: =C71+(SUM(I71:N71)+(SUM(E71:F71))) -> 125.7625 | Q71: =D71+G71+H71+O71 -> 288.72 | R71: =P71+Q71 -> 414.4825 | S71: Harry Potter @ Fox
A72: 46092 | B72: =R71 -> 414.4825 | C72: =P71 -> 125.7625 | D72: =Q71 -> 288.72 | E72: 0 | F72: 0 | G72: 0 | H72: 0 | I72: 0 | J72: 0 | K72: 0 | L72: 0 | M72: 0 | N72: 0 | P72: =C72+(SUM(I72:N72)+(SUM(E72:F72))) -> 125.7625 | Q72: =D72+G72+H72+O72 -> 288.72 | R72: =P72+Q72 -> 414.4825
A73: 46093 | B73: =R72 -> 414.4825 | C73: =P72 -> 125.7625 | D73: =Q72 -> 288.72 | E73: 0 | F73: 0 | G73: 0 | H73: 0 | I73: 0 | J73: 0 | K73: 0 | L73: 0 | M73: -51.2 | N73: 0 | P73: =C73+(SUM(I73:N73)+(SUM(E73:F73))) -> 74.5625 | Q73: =D73+G73+H73+O73 -> 288.72 | R73: =P73+Q73 -> 363.2825
A74: 46094 | B74: =R73 -> 363.2825 | C74: =P73 -> 74.5625 | D74: =Q73 -> 288.72 | E74: 0 | F74: 0 | G74: 0 | H74: 0 | I74: 0 | J74: 0 | K74: 0 | L74: 0 | M74: 0 | N74: 0 | O74: 0.01 | P74: =C74+(SUM(I74:N74)+(SUM(E74:F74))) -> 74.5625 | Q74: =D74+G74+H74+O74 -> 288.73 | R74: =P74+Q74 -> 363.2925
A75: 46095 | B75: =R74 -> 363.2925 | C75: =P74 -> 74.5625 | D75: =Q74 -> 288.73 | E75: 611.315 | F75: 0 | G75: 77.685 | H75: 0 | I75: 0 | J75: 0 | K75: 0 | L75: 0 | M75: 0 | N75: 0 | P75: =C75+(SUM(I75:N75)+(SUM(E75:F75))) -> 685.8775 | Q75: =D75+G75+H75+O75 -> 366.415 | R75: =P75+Q75 -> 1052.2925
A76: 46096 | B76: =R75 -> 1052.2925 | C76: =P75 -> 685.8775 | D76: =Q75 -> 366.415 | E76: 0 | F76: 0 | G76: 0 | H76: 0 | I76: 0 | J76: 0 | K76: 0 | L76: 0 | M76: 0 | N76: 0 | P76: =C76+(SUM(I76:N76)+(SUM(E76:F76))) -> 685.8775 | Q76: =D76+G76+H76+O76 -> 366.415 | R76: =P76+Q76 -> 1052.2925
A77: 46097 | B77: =R76 -> 1052.2925 | C77: =P76 -> 685.8775 | D77: =Q76 -> 366.415 | E77: 0 | F77: 0 | G77: 0 | H77: 0 | I77: 0 | J77: 0 | K77: 0 | L77: 0 | M77: 0 | N77: 0 | P77: =C77+(SUM(I77:N77)+(SUM(E77:F77))) -> 685.8775 | Q77: =D77+G77+H77+O77 -> 366.415 | R77: =P77+Q77 -> 1052.2925
A78: 46098 | B78: =R77 -> 1052.2925 | C78: =P77 -> 685.8775 | D78: =Q77 -> 366.415 | E78: 0 | F78: 0 | G78: 0 | H78: 0 | I78: 0 | J78: 0 | K78: 0 | L78: 0 | M78: 0 | N78: 0 | P78: =C78+(SUM(I78:N78)+(SUM(E78:F78))) -> 685.8775 | Q78: =D78+G78+H78+O78 -> 366.415 | R78: =P78+Q78 -> 1052.2925
A79: 46099 | B79: =R78 -> 1052.2925 | C79: =P78 -> 685.8775 | D79: =Q78 -> 366.415 | E79: 0 | F79: 0 | G79: 0 | H79: 0 | I79: 0 | J79: 0 | K79: 0 | L79: 0 | M79: 0 | N79: 0 | P79: =C79+(SUM(I79:N79)+(SUM(E79:F79))) -> 685.8775 | Q79: =D79+G79+H79+O79 -> 366.415 | R79: =P79+Q79 -> 1052.2925
A80: 46100 | B80: =R79 -> 1052.2925 | C80: =P79 -> 685.8775 | D80: =Q79 -> 366.415 | E80: 0 | F80: 0 | G80: 0 | H80: 0 | I80: 0 | J80: 0 | K80: 0 | L80: 0 | M80: 0 | N80: 0 | P80: =C80+(SUM(I80:N80)+(SUM(E80:F80))) -> 685.8775 | Q80: =D80+G80+H80+O80 -> 366.415 | R80: =P80+Q80 -> 1052.2925
A81: 46101 | B81: =R80 -> 1052.2925 | C81: =P80 -> 685.8775 | D81: =Q80 -> 366.415 | E81: 0 | F81: 0 | G81: 0 | H81: 0 | I81: 0 | J81: 0 | K81: 0 | L81: 0 | M81: 0 | N81: 0 | P81: =C81+(SUM(I81:N81)+(SUM(E81:F81))) -> 685.8775 | Q81: =D81+G81+H81+O81 -> 366.415 | R81: =P81+Q81 -> 1052.2925
A82: 46102 | B82: =R81 -> 1052.2925 | C82: =P81 -> 685.8775 | D82: =Q81 -> 366.415 | E82: 0 | F82: 0 | G82: 0 | H82: 0 | I82: 0 | J82: 0 | K82: 0 | L82: 0 | M82: 0 | N82: 0 | P82: =C82+(SUM(I82:N82)+(SUM(E82:F82))) -> 685.8775 | Q82: =D82+G82+H82+O82 -> 366.415 | R82: =P82+Q82 -> 1052.2925
A83: 46103 | B83: =R82 -> 1052.2925 | C83: =P82 -> 685.8775 | D83: =Q82 -> 366.415 | E83: 0 | F83: 0 | G83: 0 | H83: 0 | I83: 0 | J83: 0 | K83: 0 | L83: 0 | M83: 0 | N83: 0 | P83: =C83+(SUM(I83:N83)+(SUM(E83:F83))) -> 685.8775 | Q83: =D83+G83+H83+O83 -> 366.415 | R83: =P83+Q83 -> 1052.2925
A84: 46104 | B84: =R83 -> 1052.2925 | C84: =P83 -> 685.8775 | D84: =Q83 -> 366.415 | E84: 0 | F84: 0 | G84: 0 | H84: 0 | I84: 0 | J84: 0 | K84: 0 | L84: 0 | M84: 0 | N84: 0 | P84: =C84+(SUM(I84:N84)+(SUM(E84:F84))) -> 685.8775 | Q84: =D84+G84+H84+O84 -> 366.415 | R84: =P84+Q84 -> 1052.2925
A85: 46105 | B85: =R84 -> 1052.2925 | C85: =P84 -> 685.8775 | D85: =Q84 -> 366.415 | E85: 0 | F85: 0 | G85: 0 | H85: 0 | I85: 0 | J85: 0 | K85: 0 | L85: 0 | M85: 0 | N85: 0 | P85: =C85+(SUM(I85:N85)+(SUM(E85:F85))) -> 685.8775 | Q85: =D85+G85+H85+O85 -> 366.415 | R85: =P85+Q85 -> 1052.2925
A86: 46106 | B86: =R85 -> 1052.2925 | C86: =P85 -> 685.8775 | D86: =Q85 -> 366.415 | E86: 0 | F86: 0 | G86: 0 | H86: 0 | I86: 0 | J86: 0 | K86: 0 | L86: 0 | M86: 0 | N86: 0 | P86: =C86+(SUM(I86:N86)+(SUM(E86:F86))) -> 685.8775 | Q86: =D86+G86+H86+O86 -> 366.415 | R86: =P86+Q86 -> 1052.2925
... A102: 46122 | B102: =R101 -> 657.9425 | C102: =P101 -> 58.4725 | D102: =Q101 -> 599.47 | E102: 0 | F102: 0 | G102: 0 | H102: 0 | I102: 0 | J102: 0 | K102: 0 | L102: 0 | M102: 0 | N102: 0 | P102: =C102+(SUM(I102:N102)+(SUM(E102:F102))) -> 58.4725 | Q102: =D102+G102+H102+O102 -> 599.47 | R102: =P102+Q102 -> 657.9425
A103: 46123 | B103: =R102 -> 657.9425 | C103: =P102 -> 58.4725 | D103: =Q102 -> 599.47 | E103: 0 | F103: 0 | G103: 0 | H103: 0 | I103: 0 | J103: 0 | K103: 0 | L103: 0 | M103: 0 | N103: 0 | O103: -323.99 | P103: =C103+(SUM(I103:N103)+(SUM(E103:F103))) -> 58.4725 | Q103: =D103+G103+H103+O103 -> 275.48 | R103: =P103+Q103 -> 333.9525 | S103: New Gas Range Kitchen
A104: 46124 | B104: =R103 -> 333.9525 | C104: =P103 -> 58.4725 | D104: =Q103 -> 275.48 | E104: 0 | F104: 0 | G104: 0 | H104: 0 | I104: 0 | J104: 0 | K104: 0 | L104: 0 | M104: -51.2 | N104: 0 | P104: =C104+(SUM(I104:N104)+(SUM(E104:F104))) -> 7.2725 | Q104: =D104+G104+H104+O104 -> 275.48 | R104: =P104+Q104 -> 282.7525
A105: 46125 | B105: =R104 -> 282.7525 | C105: =P104 -> 7.2725 | D105: =Q104 -> 275.48 | E105: 0 | F105: 0 | G105: 0 | H105: 0 | I105: 0 | J105: 0 | K105: 0 | L105: 0 | M105: 0 | N105: 0 | P105: =C105+(SUM(I105:N105)+(SUM(E105:F105))) -> 7.2725 | Q105: =D105+G105+H105+O105 -> 275.48 | R105: =P105+Q105 -> 282.7525
A106: 46126 | B106: =R105 -> 282.7525 | C106: =P105 -> 7.2725 | D106: =Q105 -> 275.48 | E106: 611.315 | F106: 0 | G106: 77.685 | H106: 0 | I106: 0 | J106: 0 | K106: 0 | L106: 0 | M106: 0 | N106: 0 | P106: =C106+(SUM(I106:N106)+(SUM(E106:F106))) -> 618.5875 | Q106: =D106+G106+H106+O106 -> 353.165 | R106: =P106+Q106 -> 971.7525
A107: 46127 | B107: =R106 -> 971.7525 | C107: =P106 -> 618.5875 | D107: =Q106 -> 353.165 | E107: 0 | F107: 0 | G107: 0 | H107: 0 | I107: 0 | J107: 0 | K107: 0 | L107: 0 | M107: 0 | N107: 0 | P107: =C107+(SUM(I107:N107)+(SUM(E107:F107))) -> 618.5875 | Q107: =D107+G107+H107+O107 -> 353.165 | R107: =P107+Q107 -> 971.7525
A108: 46128 | B108: =R107 -> 971.7525 | C108: =P107 -> 618.5875 | D108: =Q107 -> 353.165 | E108: 0 | F108: 0 | G108: 0 | H108: 0 | I108: 0 | J108: 0 | K108: 0 | L108: 0 | M108: 0 | N108: 0 | O108: 0.01 | P108: =C108+(SUM(I108:N108)+(SUM(E108:F108))) -> 618.5875 | Q108: =D108+G108+H108+O108 -> 353.175 | R108: =P108+Q108 -> 971.7625
A109: 46129 | B109: =R108 -> 971.7625 | C109: =P108 -> 618.5875 | D109: =Q108 -> 353.175 | E109: 0 | F109: 0 | G109: 0 | H109: 0 | I109: 0 | J109: 0 | K109: 0 | L109: 0 | M109: 0 | N109: 0 | P109: =C109+(SUM(I109:N109)+(SUM(E109:F109))) -> 618.5875 | Q109: =D109+G109+H109+O109 -> 353.175 | R109: =P109+Q109 -> 971.7625
A110: 46130 | B110: =R109 -> 971.7625 | C110: =P109 -> 618.5875 | D110: =Q109 -> 353.175 | E110: 0 | F110: 0 | G110: 0 | H110: 0 | I110: 0 | J110: 0 | K110: 0 | L110: 0 | M110: 0 | N110: 0 | P110: =C110+(SUM(I110:N110)+(SUM(E110:F110))) -> 618.5875 | Q110: =D110+G110+H110+O110 -> 353.175 | R110: =P110+Q110 -> 971.7625
A111: 46131 | B111: =R110 -> 971.7625 | C111: =P110 -> 618.5875 | D111: =Q110 -> 353.175 | E111: 0 | F111: 0 | G111: 0 | H111: 0 | I111: 0 | J111: 0 | K111: 0 | L111: 0 | M111: 0 | N111: 0 | P111: =C111+(SUM(I111:N111)+(SUM(E111:F111))) -> 618.5875 | Q111: =D111+G111+H111+O111 -> 353.175 | R111: =P111+Q111 -> 971.7625
A112: 46132 | B112: =R111 -> 971.7625 | C112: =P111 -> 618.5875 | D112: =Q111 -> 353.175 | E112: 0 | F112: 0 | G112: 0 | H112: 0 | I112: 0 | J112: 0 | K112: 0 | L112: 0 | M112: 0 | N112: 0 | P112: =C112+(SUM(I112:N112)+(SUM(E112:F112))) -> 618.5875 | Q112: =D112+G112+H112+O112 -> 353.175 | R112: =P112+Q112 -> 971.7625
A113: 46133 | B113: =R112 -> 971.7625 | C113: =P112 -> 618.5875 | D113: =Q112 -> 353.175 | E113: 0 | F113: 0 | G113: 0 | H113: 0 | I113: 0 | J113: 0 | K113: 0 | L113: 0 | M113: 0 | N113: 0 | P113: =C113+(SUM(I113:N113)+(SUM(E113:F113))) -> 618.5875 | Q113: =D113+G113+H113+O113 -> 353.175 | R113: =P113+Q113 -> 971.7625
A114: 46134 | B114: =R113 -> 971.7625 | C114: =P113 -> 618.5875 | D114: =Q113 -> 353.175 | E114: 0 | F114: 0 | G114: 0 | H114: 0 | I114: 0 | J114: 0 | K114: 0 | L114: 0 | M114: 0 | N114: 0 | P114: =C114+(SUM(I114:N114)+(SUM(E114:F114))) -> 618.5875 | Q114: =D114+G114+H114+O114 -> 353.175 | R114: =P114+Q114 -> 971.7625
A115: 46135 | B115: =R114 -> 971.7625 | C115: =P114 -> 618.5875 | D115: =Q114 -> 353.175 | E115: 0 | F115: 0 | G115: 0 | H115: 0 | I115: 0 | J115: 0 | K115: 0 | L115: 0 | M115: 0 | N115: 0 | P115: =C115+(SUM(I115:N115)+(SUM(E115:F115))) -> 618.5875 | Q115: =D115+G115+H115+O115 -> 353.175 | R115: =P115+Q115 -> 971.7625
A116: 46136 | B116: =R115 -> 971.7625 | C116: =P115 -> 618.5875 | D116: =Q115 -> 353.175 | E116: 0 | F116: 0 | G116: 0 | H116: 0 | I116: 0 | J116: 0 | K116: 0 | L116: 0 | M116: 0 | N116: 0 | P116: =C116+(SUM(I116:N116)+(SUM(E116:F116))) -> 618.5875 | Q116: =D116+G116+H116+O116 -> 353.175 | R116: =P116+Q116 -> 971.7625
A117: 46137 | B117: =R116 -> 971.7625 | C117: =P116 -> 618.5875 | D117: =Q116 -> 353.175 | E117: 0 | F117: 0 | G117: 0 | H117: 0 | I117: 0 | J117: 0 | K117: 0 | L117: 0 | M117: 0 | N117: 0 | P117: =C117+(SUM(I117:N117)+(SUM(E117:F117))) -> 618.5875 | Q117: =D117+G117+H117+O117 -> 353.175 | R117: =P117+Q117 -> 971.7625
A118: 46138 | B118: =R117 -> 971.7625 | C118: =P117 -> 618.5875 | D118: =Q117 -> 353.175 | E118: 0 | F118: 0 | G118: 0 | H118: 0 | I118: 0 | J118: 0 | K118: 0 | L118: -91.1 | M118: 0 | N118: 0 | P118: =C118+(SUM(I118:N118)+(SUM(E118:F118))) -> 527.4875 | Q118: =D118+G118+H118+O118 -> 353.175 | R118: =P118+Q118 -> 880.6625
A119: 46139 | B119: =R118 -> 880.6625 | C119: =P118 -> 527.4875 | D119: =Q118 -> 353.175 | E119: 0 | F119: 1222.63 | G119: 0 | H119: 155.37 | I119: 0 | J119: 0 | K119: 0 | L119: 0 | M119: 0 | N119: 0 | P119: =C119+(SUM(I119:N119)+(SUM(E119:F119))) -> 1750.1175 | Q119: =D119+G119+H119+O119 -> 508.545 | R119: =P119+Q119 -> 2258.6625
A120: 46140 | B120: =R119 -> 2258.6625 | C120: =P119 -> 1750.1175 | D120: =Q119 -> 508.545 | E120: 0 | F120: 0 | G120: 0 | H120: 0 | I120: 0 | J120: 0 | K120: 0 | L120: 0 | M120: 0 | N120: 0 | P120: =C120+(SUM(I120:N120)+(SUM(E120:F120))) -> 1750.1175 | Q120: =D120+G120+H120+O120 -> 508.545 | R120: =P120+Q120 -> 2258.6625
... A133: 46153 | B133: =R132 -> 662.3225 | C133: =P132 -> 76.0925 | D133: =Q132 -> 586.23 | E133: 0 | F133: 0 | G133: 0 | H133: 0 | I133: 0 | J133: 0 | K133: 0 | L133: 0 | M133: 0 | N133: 0 | P133: =C133+(SUM(I133:N133)+(SUM(E133:F133))) -> 76.0925 | Q133: =D133+G133+H133+O133 -> 586.23 | R133: =P133+Q133 -> 662.3225
A134: 46154 | B134: =R133 -> 662.3225 | C134: =P133 -> 76.0925 | D134: =Q133 -> 586.23 | E134: 0 | F134: 0 | G134: 0 | H134: 0 | I134: 0 | J134: 0 | K134: 0 | L134: 0 | M134: -51.2 | N134: 0 | O134: 0.01 | P134: =C134+(SUM(I134:N134)+(SUM(E134:F134))) -> 24.8925 | Q134: =D134+G134+H134+O134 -> 586.24 | R134: =P134+Q134 -> 611.1325
A135: 46155 | B135: =R134 -> 611.1325 | C135: =P134 -> 24.8925 | D135: =Q134 -> 586.24 | E135: 611.16 | F135: 1221.82 | G135: 77.835 | H135: 156.18 | I135: 0 | J135: 0 | K135: 0 | L135: 0 | M135: 0 | N135: 0 | P135: =C135+(SUM(I135:N135)+(SUM(E135:F135))) -> 1857.8725 | Q135: =D135+G135+H135+O135 -> 820.255 | R135: =P135+Q135 -> 2678.1275
A136: 46156 | B136: =R135 -> 2678.1275 | C136: =P135 -> 1857.8725 | D136: =Q135 -> 820.255 | E136: 0 | F136: 0 | G136: 0 | H136: 0 | I136: 0 | J136: 0 | K136: 0 | L136: 0 | M136: 0 | N136: 0 | P136: =C136+(SUM(I136:N136)+(SUM(E136:F136))) -> 1857.8725 | Q136: =D136+G136+H136+O136 -> 820.255 | R136: =P136+Q136 -> 2678.1275
A137: 46157 | B137: =R136 -> 2678.1275 | C137: =P136 -> 1857.8725 | D137: =Q136 -> 820.255 | E137: 0 | F137: 0 | G137: 0 | H137: 0 | I137: 0 | J137: 0 | K137: 0 | L137: 0 | M137: 0 | N137: 0 | P137: =C137+(SUM(I137:N137)+(SUM(E137:F137))) -> 1857.8725 | Q137: =D137+G137+H137+O137 -> 820.255 | R137: =P137+Q137 -> 2678.1275
A138: 46158 | B138: =R137 -> 2678.1275 | C138: =P137 -> 1857.8725 | D138: =Q137 -> 820.255 | E138: 0 | F138: 0 | G138: 0 | H138: 0 | I138: 0 | J138: 0 | K138: 0 | L138: 0 | M138: 0 | N138: 0 | P138: =C138+(SUM(I138:N138)+(SUM(E138:F138))) -> 1857.8725 | Q138: =D138+G138+H138+O138 -> 820.255 | R138: =P138+Q138 -> 2678.1275
...

Sheet HOA Savings
E1: Credits | I1: Outgoing Payments (Debits)
A2: Date | B2: Total Beg Balance | C2: Regular Beg Balance | D2: Extra Beg Balance | E2: Jon Credit | F2: Ronnie Credit | G2: Jon Extra Credit | H2: Ronnie Extra Credit | I2: HOA Payment | K2: Other $ (Credit or Debit) | L2: Regular Ending Balance | M2: Extra Ending Balance | N2: Total Ending Balance | O2: Other Explination
A3: 46022 | B3: 2791.0332 | C3: 2177.21 | D3: 613.82317 | E3: 0 | F3: 0 | G3: 0 | H3: 0 | L3: 2177.21 | M3: 613.82317 | N3: 2791.0332
A4: 46023 | B4: 2791.0332 | C4: 2177.21 | D4: 613.82317 | E4: 0 | F4: 197 | G4: 0 | H4: 25 | L4: 2374.21 | M4: 638.82317 | N4: 3013.0332
A5: 46024 | B5: 3013.0332 | C5: 2374.21 | D5: 638.82317 | E5: 0 | F5: 0 | G5: 0 | H5: 0 | L5: 2374.21 | M5: 638.82317 | N5: 3013.0332
A6: 46025 | B6: 3013.0332 | C6: 2374.21 | D6: 638.82317 | E6: 0 | F6: 0 | G6: 0 | H6: 0 | K6: 0.02 | L6: 2374.23 | M6: 638.82317 | N6: 3013.0532
A7: 46026 | B7: 3013.0532 | C7: 2374.23 | D7: 638.82317 | E7: 0 | F7: 0 | G7: 0 | H7: 0 | L7: 2374.23 | M7: 638.82317 | N7: 3013.0532
A8: 46027 | B8: 3013.0532 | C8: 2374.23 | D8: 638.82317 | E8: 0 | F8: 0 | G8: 0 | H8: 0 | L8: 2374.23 | M8: 638.82317 | N8: 3013.0532
A9: 46028 | B9: 3013.0532 | C9: 2374.23 | D9: 638.82317 | E9: 0 | F9: 0 | G9: 0 | H9: 0 | L9: 2374.23 | M9: 638.82317 | N9: 3013.0532
A10: 46029 | B10: 3013.0532 | C10: 2374.23 | D10: 638.82317 | E10: 0 | F10: 0 | G10: 0 | H10: 0 | I10: -2353.95 | L10: 20.28 | M10: 638.82317 | N10: 659.10317
A11: 46030 | B11: 659.10317 | C11: 20.28 | D11: 638.82317 | E11: 0 | F11: 0 | G11: 0 | H11: 0 | L11: 20.28 | M11: 638.82317 | N11: 659.10317
A12: 46031 | B12: 659.10317 | C12: 20.28 | D12: 638.82317 | E12: 0 | F12: 0 | G12: 0 | H12: 0 | L12: 20.28 | M12: 638.82317 | N12: 659.10317
A13: 46032 | B13: 659.10317 | C13: 20.28 | D13: 638.82317 | E13: 0 | F13: 0 | G13: 0 | H13: 0 | L13: 20.28 | M13: 638.82317 | N13: 659.10317
A14: 46033 | B14: 659.10317 | C14: 20.28 | D14: 638.82317 | E14: 0 | F14: 0 | G14: 0 | H14: 0 | L14: 20.28 | M14: 638.82317 | N14: 659.10317
A15: 46034 | B15: 659.10317 | C15: 20.28 | D15: 638.82317 | E15: 0 | F15: 0 | G15: 0 | H15: 0 | L15: 20.28 | M15: 638.82317 | N15: 659.10317
A16: 46035 | B16: 659.10317 | C16: 20.28 | D16: 638.82317 | E16: 0 | F16: 0 | G16: 0 | H16: 0 | L16: 20.28 | M16: 638.82317 | N16: 659.10317
A17: 46036 | B17: 659.10317 | C17: 20.28 | D17: 638.82317 | E17: 98.5 | F17: 0 | G17: 12.5 | H17: 0 | L17: 118.78 | M17: 651.32317 | N17: 770.10317
A18: 46037 | B18: 770.10317 | C18: 118.78 | D18: 651.32317 | E18: 0 | F18: 0 | G18: 0 | H18: 0 | L18: 118.78 | M18: 651.32317 | N18: 770.10317
A19: 46038 | B19: 770.10317 | C19: 118.78 | D19: 651.32317 | E19: 0 | F19: 0 | G19: 0 | H19: 0 | L19: 118.78 | M19: 651.32317 | N19: 770.10317
A20: 46039 | B20: 770.10317 | C20: 118.78 | D20: 651.32317 | E20: 0 | F20: 0 | G20: 0 | H20: 0 | L20: 118.78 | M20: 651.32317 | N20: 770.10317
A21: 46040 | B21: 770.10317 | C21: 118.78 | D21: 651.32317 | E21: 0 | F21: 0 | G21: 0 | H21: 0 | L21: 118.78 | M21: 651.32317 | N21: 770.10317
A22: 46041 | B22: 770.10317 | C22: 118.78 | D22: 651.32317 | E22: 0 | F22: 0 | G22: 0 | H22: 0 | L22: 118.78 | M22: 651.32317 | N22: 770.10317
... A32: 46051 | B32: 770.10317 | C32: 118.78 | D32: 651.32317 | E32: 0 | F32: 0 | G32: 0 | H32: 0 | L32: 118.78 | M32: 651.32317 | N32: 770.10317
A33: 46052 | B33: 770.10317 | C33: 118.78 | D33: 651.32317 | E33: 98.5 | F33: 0 | G33: 12.5 | H33: 0 | K33: 0.01 | L33: 217.29 | M33: 663.82317 | N33: 881.11317
A34: 46053 | B34: 881.11317 | C34: 217.29 | D34: 663.82317 | E34: 0 | F34: 0 | G34: 0 | H34: 0 | L34: 217.29 | M34: 663.82317 | N34: 881.11317
A35: 46054 | B35: 881.11317 | C35: 217.29 | D35: 663.82317 | E35: 0 | F35: 197 | G35: 0 | H35: 25 | L35: 414.29 | M35: 688.82317 | N35: 1103.1132
A36: 46055 | B36: 1103.1132 | C36: 414.29 | D36: 688.82317 | E36: 0 | F36: 0 | G36: 0 | H36: 0 | L36: 414.29 | M36: 688.82317 | N36: 1103.1132
A37: 46056 | B37: 1103.1132 | C37: 414.29 | D37: 688.82317 | E37: 0 | F37: 0 | G37: 0 | H37: 0 | L37: 414.29 | M37: 688.82317 | N37: 1103.1132
A38: 46057 | B38: 1103.1132 | C38: 414.29 | D38: 688.82317 | E38: 0 | F38: 0 | G38: 0 | H38: 0 | L38: 414.29 | M38: 688.82317 | N38: 1103.1132
A39: 46058 | B39: 1103.1132 | C39: 414.29 | D39: 688.82317 | E39: 0 | F39: 0 | G39: 0 | H39: 0 | L39: 414.29 | M39: 688.82317 | N39: 1103.1132
A40: 46059 | B40: 1103.1132 | C40: 414.29 | D40: 688.82317 | E40: 0 | F40: 0 | G40: 0 | H40: 0 | L40: 414.29 | M40: 688.82317 | N40: 1103.1132
A41: 46060 | B41: 1103.1132 | C41: 414.29 | D41: 688.82317 | E41: 0 | F41: 0 | G41: 0 | H41: 0 | L41: 414.29 | M41: 688.82317 | N41: 1103.1132
A42: 46061 | B42: 1103.1132 | C42: 414.29 | D42: 688.82317 | E42: 0 | F42: 0 | G42: 0 | H42: 0 | L42: 414.29 | M42: 688.82317 | N42: 1103.1132
A43: 46062 | B43: 1103.1132 | C43: 414.29 | D43: 688.82317 | E43: 0 | F43: 0 | G43: 0 | H43: 0 | L43: 414.29 | M43: 688.82317 | N43: 1103.1132
A44: 46063 | B44: 1103.1132 | C44: 414.29 | D44: 688.82317 | E44: 0 | F44: 0 | G44: 0 | H44: 0 | L44: 414.29 | M44: 688.82317 | N44: 1103.1132
A45: 46064 | B45: 1103.1132 | C45: 414.29 | D45: 688.82317 | E45: 0 | F45: 0 | G45: 0 | H45: 0 | L45: 414.29 | M45: 688.82317 | N45: 1103.1132
... A100: 46119 | B100: 1991.1132 | C100: 1202.29 | D100: 788.82317 | E100: 0 | F100: 0 | G100: 0 | H100: 0 | L100: 1202.29 | M100: 788.82317 | N100: 1991.1132
A101: 46120 | B101: 1991.1132 | C101: 1202.29 | D101: 788.82317 | E101: 0 | F101: 0 | G101: 0 | H101: 0 | K101: 0.02 | L101: 1202.31 | M101: 788.82317 | N101: 1991.1332
A102: 46121 | B102: 1991.1332 | C102: 1202.31 | D102: 788.82317 | E102: 0 | F102: 0 | G102: 0 | H102: 0 | L102: 1202.31 | M102: 788.82317 | N102: 1991.1332
A103: 46122 | B103: 1991.1332 | C103: 1202.31 | D103: 788.82317 | E103: 0 | F103: 0 | G103: 0 | H103: 0 | L103: 1202.31 | M103: 788.82317 | N103: 1991.1332
A104: 46123 | B104: 1991.1332 | C104: 1202.31 | D104: 788.82317 | E104: 0 | F104: 0 | G104: 0 | H104: 0 | L104: 1202.31 | M104: 788.82317 | N104: 1991.1332 | O104: New Weber Spirit Grill
A105: 46124 | B105: 1430.1332 | C105: 1202.31 | D105: 227.82317 | E105: 0 | F105: 0 | G105: 0 | H105: 0 | L105: 1202.31 | M105: 227.82317 | N105: 1430.1332
A106: 46125 | B106: 1430.1332 | C106: 1202.31 | D106: 227.82317 | E106: 0 | F106: 0 | G106: 0 | H106: 0 | L106: 1202.31 | M106: 227.82317 | N106: 1430.1332
A107: 46126 | B107: 1430.1332 | C107: 1202.31 | D107: 227.82317 | E107: 98.5 | F107: 0 | G107: 12.5 | H107: 0 | L107: 1300.81 | M107: 240.32317 | N107: 1541.1332
A108: 46127 | B108: 1541.1332 | C108: 1300.81 | D108: 240.32317 | E108: 0 | F108: 0 | G108: 0 | H108: 0 | L108: 1300.81 | M108: 240.32317 | N108: 1541.1332
A109: 46128 | B109: 1541.1332 | C109: 1300.81 | D109: 240.32317 | E109: 0 | F109: 0 | G109: 0 | H109: 0 | L109: 1300.81 | M109: 240.32317 | N109: 1541.1332
A110: 46129 | B110: 1541.1332 | C110: 1300.81 | D110: 240.32317 | E110: 0 | F110: 0 | G110: 0 | H110: 0 | L110: 1300.81 | M110: 240.32317 | N110: 1541.1332
A111: 46130 | B111: 1541.1332 | C111: 1300.81 | D111: 240.32317 | E111: 0 | F111: 0 | G111: 0 | H111: 0 | L111: 1300.81 | M111: 240.32317 | N111: 1541.1332
A112: 46131 | B112: 1541.1332 | C112: 1300.81 | D112: 240.32317 | E112: 0 | F112: 0 | G112: 0 | H112: 0 | L112: 1300.81 | M112: 240.32317 | N112: 1541.1332
A113: 46132 | B113: 1541.1332 | C113: 1300.81 | D113: 240.32317 | E113: 0 | F113: 0 | G113: 0 | H113: 0 | L113: 1300.81 | M113: 240.32317 | N113: 1541.1332
A114: 46133 | B114: 1541.1332 | C114: 1300.81 | D114: 240.32317 | E114: 0 | F114: 0 | G114: 0 | H114: 0 | L114: 1300.81 | M114: 240.32317 | N114: 1541.1332
A115: 46134 | B115: 1541.1332 | C115: 1300.81 | D115: 240.32317 | E115: 0 | F115: 0 | G115: 0 | H115: 0 | L115: 1300.81 | M115: 240.32317 | N115: 1541.1332
A116: 46135 | B116: 1541.1332 | C116: 1300.81 | D116: 240.32317 | E116: 0 | F116: 0 | G116: 0 | H116: 0 | L116: 1300.81 | M116: 240.32317 | N116: 1541.1332
... A122: 46141 | B122: 1763.1332 | C122: 1497.81 | D122: 265.32317 | E122: 98.5 | F122: 0 | G122: 12.5 | H122: 0 | L122: 1596.31 | M122: 277.82317 | N122: 1874.1332
A123: 46142 | B123: 1874.1332 | C123: 1596.31 | D123: 277.82317 | E123: 0 | F123: 0 | G123: 0 | H123: 0 | K123: 0.01 | L123: 1596.32 | M123: 277.82317 | N123: 1874.1432
A124: 46143 | B124: 1874.1432 | C124: 1596.32 | D124: 277.82317 | E124: 0 | F124: 0 | G124: 0 | H124: 0 | L124: 1596.32 | M124: 277.82317 | N124: 1874.1432
A125: 46144 | B125: 1874.1432 | C125: 1596.32 | D125: 277.82317 | E125: 0 | F125: 0 | G125: 0 | H125: 0 | L125: 1596.32 | M125: 277.82317 | N125: 1874.1432
A126: 46145 | B126: 1874.1432 | C126: 1596.32 | D126: 277.82317 | E126: 0 | F126: 0 | G126: 0 | H126: 0 | L126: 1596.32 | M126: 277.82317 | N126: 1874.1432
A127: 46146 | B127: 1874.1432 | C127: 1596.32 | D127: 277.82317 | E127: 0 | F127: 0 | G127: 0 | H127: 0 | L127: 1596.32 | M127: 277.82317 | N127: 1874.1432
A128: 46147 | B128: 1874.1432 | C128: 1596.32 | D128: 277.82317 | E128: 0 | F128: 0 | G128: 0 | H128: 0 | L128: 1596.32 | M128: 277.82317 | N128: 1874.1432
A129: 46148 | B129: 1874.1432 | C129: 1596.32 | D129: 277.82317 | E129: 0 | F129: 0 | G129: 0 | H129: 0 | L129: 1596.32 | M129: 277.82317 | N129: 1874.1432
A130: 46149 | B130: 1874.1432 | C130: 1596.32 | D130: 277.82317 | E130: 0 | F130: 0 | G130: 0 | H130: 0 | L130: 1596.32 | M130: 277.82317 | N130: 1874.1432
A131: 46150 | B131: 1874.1432 | C131: 1596.32 | D131: 277.82317 | E131: 0 | F131: 0 | G131: 0 | H131: 0 | L131: 1596.32 | M131: 277.82317 | N131: 1874.1432
A132: 46151 | B132: 1874.1432 | C132: 1596.32 | D132: 277.82317 | E132: 0 | F132: 0 | G132: 0 | H132: 0 | L132: 1596.32 | M132: 277.82317 | N132: 1874.1432
A133: 46152 | B133: 1874.1432 | C133: 1596.32 | D133: 277.82317 | E133: 0 | F133: 0 | G133: 0 | H133: 0 | L133: 1596.32 | M133: 277.82317 | N133: 1874.1432
A134: 46153 | B134: 1874.1432 | C134: 1596.32 | D134: 277.82317 | E134: 0 | F134: 0 | G134: 0 | H134: 0 | L134: 1596.32 | M134: 277.82317 | N134: 1874.1432
A135: 46154 | B135: 1874.1432 | C135: 1596.32 | D135: 277.82317 | E135: 0 | F135: 0 | G135: 0 | H135: 0 | L135: 1596.32 | M135: 277.82317 | N135: 1874.1432
... A186: 46205 | B186: 2762.1432 | C186: 2384.32 | D186: 377.82317 | E186: 0 | F186: 0 | G186: 0 | H186: 0 | L186: 2384.32 | M186: 377.82317 | N186: 2762.1432
A187: 46206 | B187: 2762.1432 | C187: 2384.32 | D187: 377.82317 | E187: 0 | F187: 0 | G187: 0 | H187: 0 | K187: 0 | L187: 2384.34 | M187: 377.82317 | N187: 2762.1632
A188: 46207 | B188: 2762.1632 | C188: 2384.34 | D188: 377.82317 | E188: 0 | F188: 0 | G188: 0 | H188: 0 | L188: 2384.34 | M188: 377.82317 | N188: 2762.1632
A189: 46208 | B189: 2762.1632 | C189: 2384.34 | D189: 377.82317 | E189: 0 | F189: 0 | G189: 0 | H189: 0 | L189: 2384.34 | M189: 377.82317 | N189: 2762.1632
A190: 46209 | B190: 2762.1632 | C190: 2384.34 | D190: 377.82317 | E190: 0 | F190: 0 | G190: 0 | H190: 0 | L190: 2384.34 | M190: 377.82317 | N190: 2762.1632
A191: 46210 | B191: 2762.1632 | C191: 2384.34 | D191: 377.82317 | E191: 0 | F191: 0 | G191: 0 | H191: 0 | I191: -2300 | J191: -3.95 | L191: 30.39 | M191: 377.82317 | N191: 408.21317
A192: 46211 | B192: 408.21317 | C192: 30.39 | D192: 377.82317 | E192: 0 | F192: 0 | G192: 0 | H192: 0 | L192: 30.39 | M192: 377.82317 | N192: 408.21317
A193: 46212 | B193: 408.21317 | C193: 30.39 | D193: 377.82317 | E193: 0 | F193: 0 | G193: 0 | H193: 0 | L193: 30.39 | M193: 377.82317 | N193: 408.21317
A194: 46213 | B194: 408.21317 | C194: 30.39 | D194: 377.82317 | E194: 0 | F194: 0 | G194: 0 | H194: 0 | L194: 30.39 | M194: 377.82317 | N194: 408.21317
A195: 46214 | B195: 408.21317 | C195: 30.39 | D195: 377.82317 | E195: 0 | F195: 0 | G195: 0 | H195: 0 | K195: 0.02 | L195: 30.41 | M195: 377.82317 | N195: 408.23317
A196: 46215 | B196: 408.23317 | C196: 30.41 | D196: 377.82317 | E196: 0 | F196: 0 | G196: 0 | H196: 0 | L196: =MAX((C196+E196+F196)+I196,0) -> 30.41 | M196: 377.82317 | N196: 408.23317
A197: 46216 | B197: 408.23317 | C197: 30.41 | D197: 377.82317 | E197: 0 | F197: 0 | G197: 0 | H197: 0 | L197: =MAX((C197+E197+F197)+I197,0) -> 30.41 | M197: 377.82317 | N197: 408.23317
A198: 46217 | B198: 408.23317 | C198: 30.41 | D198: 377.82317 | E198: 98.5 | F198: 0 | G198: 12.5 | H198: 0 | L198: =MAX((C198+E198+F198)+I198,0) -> 128.91 | M198: 390.32317 | N198: 519.23317
A199: 46218 | B199: 519.23317 | C199: 128.91 | D199: 390.32317 | E199: 0 | F199: 0 | G199: 0 | H199: 0 | L199: =MAX((C199+E199+F199)+I199,0) -> 128.91 | M199: 390.32317 | N199: 519.23317
A200: 46219 | B200: 519.23317 | C200: 128.91 | D200: 390.32317 | E200: 0 | F200: 0 | G200: 0 | H200: 0 | L200: =MAX((C200+E200+F200)+I200,0) -> 128.91 | M200: 390.32317 | N200: 519.23317
A201: 46220 | B201: 519.23317 | C201: 128.91 | D201: 390.32317 | E201: 0 | F201: 0 | G201: 0 | H201: 0 | L201: =MAX((C201+E201+F201)+I201,0) -> 128.91 | M201: 390.32317 | N201: 519.23317
A202: 46221 | B202: 519.23317 | C202: 128.91 | D202: 390.32317 | E202: 0 | F202: 0 | G202: 0 | H202: 0 | L202: =MAX((C202+E202+F202)+I202,0) -> 128.91 | M202: 390.32317 | N202: 519.23317
A203: 46222 | B203: 519.23317 | C203: 128.91 | D203: 390.32317 | E203: 0 | F203: 0 | G203: 0 | H203: 0 | L203: =MAX((C203+E203+F203)+I203,0) -> 128.91 | M203: 390.32317 | N203: 519.23317
A204: 46223 | B204: 519.23317 | C204: 128.91 | D204: 390.32317 | E204: 0 | F204: 197 | G204: 0 | H204: 25 | L204: =MAX((C204+E204+F204)+I204,0) -> 325.91 | M204: 415.32317 | N204: 741.23317
A205: 46224 | B205: 741.23317 | C205: 325.91 | D205: 415.32317 | E205: 0 | F205: 0 | G205: 0 | H205: 0 | L205: =MAX((C205+E205+F205)+I205,0) -> 325.91 | M205: 415.32317 | N205: 741.23317
A206: 46225 | B206: 741.23317 | C206: 325.91 | D206: 415.32317 | E206: 0 | F206: 0 | G206: 0 | H206: 0 | L206: =MAX((C206+E206+F206)+I206,0) -> 325.91 | M206: 415.32317 | N206: 741.23317
A207: 46226 | B207: 741.23317 | C207: 325.91 | D207: 415.32317 | E207: 0 | F207: 0 | G207: 0 | H207: 0 | L207: =MAX((C207+E207+F207)+I207,0) -> 325.91 | M207: 415.32317 | N207: 741.23317
... A209: 46228 | B209: 741.23317 | C209: 325.91 | D209: 415.32317 | E209: 0 | F209: 0 | G209: 0 | H209: 0 | L209: =MAX((C209+E209+F209)+I209,0) -> 325.91 | M209: 415.32317 | N209: 741.23317
A210: 46229 | B210: 741.23317 | C210: 325.91 | D210: 415.32317 | E210: 0 | F210: 0 | G210: 0 | H210: 0 | L210: =MAX((C210+E210+F210)+I210,0) -> 325.91 | M210: =D210+G210+H210+K210 -> 415.32317 | N210: =L210+M210 -> 741.23317
A211: 46230 | B211: 741.23317 | C211: 325.91 | D211: 415.32317 | E211: 0 | F211: 0 | G211: 0 | H211: 0 | L211: =MAX((C211+E211+F211)+I211,0) -> 325.91 | M211: =D211+G211+H211+K211 -> 415.32317 | N211: =L211+M211 -> 741.23317
A212: 46231 | B212: =N211 -> 741.23317 | C212: =L211 -> 325.91 | D212: =M211 -> 415.32317 | E212: =-(IF(DAY(A212+2)=1,'Main Budget'!$I$14,IF(DAY(A212+1)=15,'Main Budget'!$I$14,0))) -> 0 | F212: =-(IF(DAY(A212)=20,'Main Budget'!$F$14,0)) -> 0 | G212: =-(IF(DAY(A212+2)=1,'Main Budget'!$I$15,IF(DAY(A212+1)=15,'Main Budget'!$I$15,0))) -> 0 | H212: =-(IF(DAY(A212)=20,'Main Budget'!$F$15,0)) -> 0 | L212: =MAX((C212+E212+F212)+I212,0) -> 325.91 | M212: =D212+G212+H212+K212 -> 415.32317 | N212: =L212+M212 -> 741.23317
A213: 46232 | B213: =N212 -> 741.23317 | C213: =L212 -> 325.91 | D213: =M212 -> 415.32317 | E213: =-(IF(DAY(A213+2)=1,'Main Budget'!$I$14,IF(DAY(A213+1)=15,'Main Budget'!$I$14,0))) -> 0 | F213: =-(IF(DAY(A213)=20,'Main Budget'!$F$14,0)) -> 0 | G213: =-(IF(DAY(A213+2)=1,'Main Budget'!$I$15,IF(DAY(A213+1)=15,'Main Budget'!$I$15,0))) -> 0 | H213: =-(IF(DAY(A213)=20,'Main Budget'!$F$15,0)) -> 0 | L213: =MAX((C213+E213+F213)+I213,0) -> 325.91 | M213: =D213+G213+H213+K213 -> 415.32317 | N213: =L213+M213 -> 741.23317
A214: 46233 | B214: =N213 -> 741.23317 | C214: =L213 -> 325.91 | D214: =M213 -> 415.32317 | E214: =-(IF(DAY(A214+2)=1,'Main Budget'!$I$14,IF(DAY(A214+1)=15,'Main Budget'!$I$14,0))) -> 98.08125 | F214: =-(IF(DAY(A214)=20,'Main Budget'!$F$14,0)) -> 0 | G214: =-(IF(DAY(A214+2)=1,'Main Budget'!$I$15,IF(DAY(A214+1)=15,'Main Budget'!$I$15,0))) -> 12.5 | H214: =-(IF(DAY(A214)=20,'Main Budget'!$F$15,0)) -> 0 | K214: 0.43 | L214: =MAX((C214+E214+F214)+I214,0) -> 423.99125 | M214: =D214+G214+H214+K214 -> 428.25317 | N214: =L214+M214 -> 852.24442
A215: 46234 | B215: =N214 -> 852.24442 | C215: =L214 -> 423.99125 | D215: =M214 -> 428.25317 | E215: =-(IF(DAY(A215+2)=1,'Main Budget'!$I$14,IF(DAY(A215+1)=15,'Main Budget'!$I$14,0))) -> 0 | F215: =-(IF(DAY(A215)=20,'Main Budget'!$F$14,0)) -> 0 | G215: =-(IF(DAY(A215+2)=1,'Main Budget'!$I$15,IF(DAY(A215+1)=15,'Main Budget'!$I$15,0))) -> 0 | H215: =-(IF(DAY(A215)=20,'Main Budget'!$F$15,0)) -> 0 | L215: =MAX((C215+E215+F215)+I215,0) -> 423.99125 | M215: =D215+G215+H215+K215 -> 428.25317 | N215: =L215+M215 -> 852.24442
A216: 46235 | B216: =N215 -> 852.24442 | C216: =L215 -> 423.99125 | D216: =M215 -> 428.25317 | E216: =-(IF(DAY(A216+2)=1,'Main Budget'!$I$14,IF(DAY(A216+1)=15,'Main Budget'!$I$14,0))) -> 0 | F216: =-(IF(DAY(A216)=20,'Main Budget'!$F$14,0)) -> 0 | G216: =-(IF(DAY(A216+2)=1,'Main Budget'!$I$15,IF(DAY(A216+1)=15,'Main Budget'!$I$15,0))) -> 0 | H216: =-(IF(DAY(A216)=20,'Main Budget'!$F$15,0)) -> 0 | L216: =MAX((C216+E216+F216)+I216,0) -> 423.99125 | M216: =D216+G216+H216+K216 -> 428.25317 | N216: =L216+M216 -> 852.24442
A217: 46236 | B217: =N216 -> 852.24442 | C217: =L216 -> 423.99125 | D217: =M216 -> 428.25317 | E217: =-(IF(DAY(A217+2)=1,'Main Budget'!$I$14,IF(DAY(A217+1)=15,'Main Budget'!$I$14,0))) -> 0 | F217: =-(IF(DAY(A217)=20,'Main Budget'!$F$14,0)) -> 0 | G217: =-(IF(DAY(A217+2)=1,'Main Budget'!$I$15,IF(DAY(A217+1)=15,'Main Budget'!$I$15,0))) -> 0 | H217: =-(IF(DAY(A217)=20,'Main Budget'!$F$15,0)) -> 0 | L217: =MAX((C217+E217+F217)+I217,0) -> 423.99125 | M217: =D217+G217+H217+K217 -> 428.25317 | N217: =L217+M217 -> 852.24442
A218: 46237 | B218: =N217 -> 852.24442 | C218: =L217 -> 423.99125 | D218: =M217 -> 428.25317 | E218: =-(IF(DAY(A218+2)=1,'Main Budget'!$I$14,IF(DAY(A218+1)=15,'Main Budget'!$I$14,0))) -> 0 | F218: =-(IF(DAY(A218)=20,'Main Budget'!$F$14,0)) -> 0 | G218: =-(IF(DAY(A218+2)=1,'Main Budget'!$I$15,IF(DAY(A218+1)=15,'Main Budget'!$I$15,0))) -> 0 | H218: =-(IF(DAY(A218)=20,'Main Budget'!$F$15,0)) -> 0 | L218: =MAX((C218+E218+F218)+I218,0) -> 423.99125 | M218: =D218+G218+H218+K218 -> 428.25317 | N218: =L218+M218 -> 852.24442
A219: 46238 | B219: =N218 -> 852.24442 | C219: =L218 -> 423.99125 | D219: =M218 -> 428.25317 | E219: =-(IF(DAY(A219+2)=1,'Main Budget'!$I$14,IF(DAY(A219+1)=15,'Main Budget'!$I$14,0))) -> 0 | F219: =-(IF(DAY(A219)=20,'Main Budget'!$F$14,0)) -> 0 | G219: =-(IF(DAY(A219+2)=1,'Main Budget'!$I$15,IF(DAY(A219+1)=15,'Main Budget'!$I$15,0))) -> 0 | H219: =-(IF(DAY(A219)=20,'Main Budget'!$F$15,0)) -> 0 | L219: =MAX((C219+E219+F219)+I219,0) -> 423.99125 | M219: =D219+G219+H219+K219 -> 428.25317 | N219: =L219+M219 -> 852.24442
...

Sheet Bills Checking
E1: Credits | G1: Outgoing Payments (Debits)
A2: Date | B2: Total Beg Balance | C2: Regular Beg Balance | D2: Extra Beg Balance | E2: Jon Credit | F2: Gym Credit | G2: Cell Service | H2: Gym | I2: Insurance Payment | J2: Other $ (Credit or Debit) | K2: Regular Ending Balance | L2: Extra Ending Balance | M2: Total Ending Balance | N2: Other Explination
A3: 46022 | B3: 204.1 | C3: =B3 -> 204.1 | D3: 0 | E3: 0 | F3: 0 | G3: 0 | H3: 0 | K3: 204.1 | L3: 0 | M3: =K3+L3 -> 204.1
A4: 46023 | B4: 204.1 | C4: =K3 -> 204.1 | D4: 0 | E4: 0 | F4: 11.25 | G4: 0 | H4: 0 | K4: 215.35 | L4: 0 | M4: =K4+L4 -> 215.35
A5: 46024 | B5: 215.35 | C5: =K4 -> 215.35 | D5: 0 | E5: 0 | F5: 0 | G5: 0 | H5: 0 | K5: 215.35 | L5: 0 | M5: =K5+L5 -> 215.35
A6: 46025 | B6: 215.35 | C6: =K5 -> 215.35 | D6: 0 | E6: 0 | F6: 0 | G6: 0 | H6: 0 | K6: 215.35 | L6: 0 | M6: =K6+L6 -> 215.35
A7: 46026 | B7: 215.35 | C7: =K6 -> 215.35 | D7: 0 | E7: 0 | F7: 0 | G7: 0 | H7: 0 | K7: 215.35 | L7: 0 | M7: =K7+L7 -> 215.35
A8: 46027 | B8: 215.35 | C8: =K7 -> 215.35 | D8: 0 | E8: 0 | F8: 0 | G8: 0 | H8: 0 | K8: 215.35 | L8: 0 | M8: =K8+L8 -> 215.35
A9: 46028 | B9: 215.35 | C9: =K8 -> 215.35 | D9: 0 | E9: 0 | F9: 0 | G9: 0 | H9: 0 | K9: 215.35 | L9: 0 | M9: =K9+L9 -> 215.35
A10: 46029 | B10: 215.35 | C10: =K9 -> 215.35 | D10: 0 | E10: 0 | F10: 0 | G10: 0 | H10: 0 | K10: 215.35 | L10: 0 | M10: =K10+L10 -> 215.35
A11: 46030 | B11: 215.35 | C11: =K10 -> 215.35 | D11: 0 | E11: 0 | F11: 0 | G11: 0 | H11: 0 | K11: 215.35 | L11: 0 | M11: =K11+L11 -> 215.35
A12: 46031 | B12: 215.35 | C12: =K11 -> 215.35 | D12: 0 | E12: 0 | F12: 0 | G12: 0 | H12: 0 | K12: 215.35 | L12: 0 | M12: =K12+L12 -> 215.35
A13: 46032 | B13: 215.35 | C13: =K12 -> 215.35 | D13: 0 | E13: 0 | F13: 0 | G13: 0 | H13: 0 | K13: 215.35 | L13: 0 | M13: =K13+L13 -> 215.35
A14: 46033 | B14: 215.35 | C14: =K13 -> 215.35 | D14: 0 | E14: 0 | F14: 0 | G14: 0 | H14: 0 | K14: 215.35 | L14: 0 | M14: =K14+L14 -> 215.35
A15: 46034 | B15: 215.35 | C15: =K14 -> 215.35 | D15: 0 | E15: 0 | F15: 0 | G15: 0 | H15: 0 | K15: 215.35 | L15: 0 | M15: =K15+L15 -> 215.35
... A178: 46197 | B178: 824.16 | C178: =K177 -> 824.16 | D178: 0 | E178: 0 | F178: 0 | G178: 0 | H178: 0 | K178: 824.16 | L178: 0 | M178: =K178+L178 -> 824.16
A179: 46198 | B179: 824.16 | C179: =K178 -> 824.16 | D179: 0 | E179: 0 | F179: 0 | G179: 0 | H179: 0 | I179: -622 | K179: 202.16 | L179: 0 | M179: =K179+L179 -> 202.16 | N179: Car Insurance
A180: 46199 | B180: 202.16 | C180: =K179 -> 202.16 | D180: 0 | E180: 0 | F180: 0 | G180: 0 | H180: 0 | K180: 202.16 | L180: 0 | M180: =K180+L180 -> 202.16
A181: 46200 | B181: 202.16 | C181: =K180 -> 202.16 | D181: 0 | E181: 0 | F181: 0 | G181: 0 | H181: 0 | K181: 202.16 | L181: 0 | M181: =K181+L181 -> 202.16
A182: 46201 | B182: 202.16 | C182: =K181 -> 202.16 | D182: 0 | E182: 0 | F182: 0 | G182: 0 | H182: 0 | K182: 202.16 | L182: 0 | M182: =K182+L182 -> 202.16
A183: 46202 | B183: 202.16 | C183: =K182 -> 202.16 | D183: 0 | E183: 85 | F183: 0 | G183: 0 | H183: 0 | K183: 287.16 | L183: 0 | M183: =K183+L183 -> 287.16
A184: 46203 | B184: 287.16 | C184: =K183 -> 287.16 | D184: 0 | E184: 0 | F184: 0 | G184: 0 | H184: 0 | K184: 287.16 | L184: 0 | M184: =K184+L184 -> 287.16
A185: 46204 | B185: 287.16 | C185: =K184 -> 287.16 | D185: 0 | E185: 0 | F185: 11.25 | G185: 0 | H185: 0 | J185: 500 | K185: 798.41 | L185: 0 | M185: =K185+L185 -> 798.41 | N185: Pay for Auction
A186: 46205 | B186: 798.41 | C186: =K185 -> 798.41 | D186: 0 | E186: 0 | F186: 0 | G186: 0 | H186: 0 | J186: -491.01 | K186: 307.4 | L186: 0 | M186: =K186+L186 -> 307.4 | N186: Prestine Auction
A187: 46206 | B187: 307.4 | C187: =K186 -> 307.4 | D187: 0 | E187: 0 | F187: 0 | G187: 0 | H187: 0 | K187: 307.4 | L187: 0 | M187: =K187+L187 -> 307.4
A188: 46207 | B188: 307.4 | C188: =K187 -> 307.4 | D188: 0 | E188: 0 | F188: 0 | G188: 0 | H188: 0 | K188: 307.4 | L188: 0 | M188: =K188+L188 -> 307.4
A189: 46208 | B189: 307.4 | C189: =K188 -> 307.4 | D189: 0 | E189: 0 | F189: 0 | G189: 0 | H189: 0 | K189: 307.4 | L189: 0 | M189: =K189+L189 -> 307.4
A190: 46209 | B190: 307.4 | C190: =K189 -> 307.4 | D190: 0 | E190: 0 | F190: 0 | G190: 0 | H190: 0 | K190: 307.4 | L190: 0 | M190: =K190+L190 -> 307.4
A191: 46210 | B191: 307.4 | C191: =K190 -> 307.4 | D191: 0 | E191: 0 | F191: 0 | G191: 0 | H191: 0 | K191: 307.4 | L191: 0 | M191: =K191+L191 -> 307.4
A192: 46211 | B192: 307.4 | C192: =K191 -> 307.4 | D192: 0 | E192: 0 | F192: 0 | G192: 0 | H192: 0 | K192: 307.4 | L192: 0 | M192: =K192+L192 -> 307.4
A193: 46212 | B193: 307.4 | C193: =K192 -> 307.4 | D193: 0 | E193: 0 | F193: 0 | G193: 0 | H193: 0 | J193: -216.63 | K193: 90.77 | L193: 0 | M193: =K193+L193 -> 90.77 | N193: Prestine Auction
A194: 46213 | B194: 90.77 | C194: =K193 -> 90.77 | D194: 0 | E194: 0 | F194: 0 | G194: 0 | H194: 0 | K194: 90.77 | L194: 0 | M194: =K194+L194 -> 90.77
A195: 46214 | B195: 90.77 | C195: =K194 -> 90.77 | D195: 0 | E195: 0 | F195: 0 | G195: 0 | H195: 0 | K195: 90.77 | L195: 0 | M195: =K195+L195 -> 90.77
A196: 46215 | B196: 90.77 | C196: =K195 -> 90.77 | D196: 0 | E196: 0 | F196: 0 | G196: 0 | H196: 0 | K196: 90.77 | L196: =D196+IF(E196>0,'Main Budget'!$I$9,0) -> 0 | M196: =K196+L196 -> 90.77
A197: 46216 | B197: =M196 -> 90.77 | C197: =K196 -> 90.77 | D197: =L196 -> 0 | E197: =IF(DAY(A197+2)=1,'Main Budget'!$E$29,IF(DAY(A197+2)=15,'Main Budget'!$E$29,0)) -> 84.998333 | F197: 0 | G197: 0 | H197: 0 | K197: =C197+SUM(E197:J197)-IF(E197>0,-'Main Budget'!$I$9,0) -> 168.84833 | L197: =D197+IF(E197>0,-'Main Budget'!$I$9,0) -> 6.92 | M197: =K197+L197 -> 175.76833
A198: 46217 | B198: =M197 -> 175.76833 | C198: =K197 -> 168.84833 | D198: =L197 -> 6.92 | E198: =IF(DAY(A198+2)=1,'Main Budget'!$E$29,IF(DAY(A198+2)=15,'Main Budget'!$E$29,0)) -> 0 | F198: 11.25 | G198: 0 | H198: 0 | K198: =K197+SUM(E198:J198)-IF(E198>0,-'Main Budget'!$I$9,0) -> 180.09833 | L198: =D198+IF(E198>0,-'Main Budget'!$I$9,0) -> 6.92 | M198: =K198+L198 -> 187.01833
A199: 46218 | B199: =M198 -> 187.01833 | C199: =K198 -> 180.09833 | D199: =L198 -> 6.92 | E199: =IF(DAY(A199+2)=1,'Main Budget'!$E$29,IF(DAY(A199+2)=15,'Main Budget'!$E$29,0)) -> 0 | F199: 0 | G199: 0 | H199: 0 | K199: =K198+SUM(E199:J199)-IF(E199>0,-'Main Budget'!$I$9,0) -> 180.09833 | L199: =D199+IF(E199>0,-'Main Budget'!$I$9,0) -> 6.92 | M199: =K199+L199 -> 187.01833
A200: 46219 | B200: =M199 -> 187.01833 | C200: =K199 -> 180.09833 | D200: =L199 -> 6.92 | E200: =IF(DAY(A200+2)=1,'Main Budget'!$E$29,IF(DAY(A200+2)=15,'Main Budget'!$E$29,0)) -> 0 | F200: 0 | G200: -30 | H200: 0 | K200: =K199+SUM(E200:J200)-IF(E200>0,-'Main Budget'!$I$9,0) -> 150.09833 | L200: =D200+IF(E200>0,-'Main Budget'!$I$9,0) -> 6.92 | M200: =K200+L200 -> 157.01833
A201: 46220 | B201: =M200 -> 157.01833 | C201: =K200 -> 150.09833 | D201: =L200 -> 6.92 | E201: =IF(DAY(A201+2)=1,'Main Budget'!$E$29,IF(DAY(A201+2)=15,'Main Budget'!$E$29,0)) -> 0 | F201: 0 | G201: 0 | H201: -44.99 | K201: =K200+SUM(E201:J201)-IF(E201>0,-'Main Budget'!$I$9,0) -> 105.10833 | L201: =D201+IF(E201>0,-'Main Budget'!$I$9,0) -> 6.92 | M201: =K201+L201 -> 112.02833
A202: 46221 | B202: =M201 -> 112.02833 | C202: =K201 -> 105.10833 | D202: =L201 -> 6.92 | E202: =IF(DAY(A202+2)=1,'Main Budget'!$E$29,IF(DAY(A202+2)=15,'Main Budget'!$E$29,0)) -> 0 | F202: =IF(OR(DAY(A202)=1,DAY(A202)=14),11.25,0) -> 0 | G202: =IF(DAY(A202)='Main Budget'!$K$7,('Main Budget'!$E$7),0) -> 0 | H202: =IF(DAY(A202)='Main Budget'!$K$8,('Main Budget'!$E$8)*2,0) -> 0 | K202: =K201+SUM(E202:J202)-IF(E202>0,-'Main Budget'!$I$9,0) -> 105.10833 | L202: =D202+IF(E202>0,-'Main Budget'!$I$9,0) -> 6.92 | M202: =K202+L202 -> 112.02833
A203: 46222 | B203: =M202 -> 112.02833 | C203: =K202 -> 105.10833 | D203: =L202 -> 6.92 | E203: =IF(DAY(A203+2)=1,'Main Budget'!$E$29,IF(DAY(A203+2)=15,'Main Budget'!$E$29,0)) -> 0 | F203: =IF(OR(DAY(A203)=1,DAY(A203)=14),11.25,0) -> 0 | G203: =IF(DAY(A203)='Main Budget'!$K$7,('Main Budget'!$E$7),0) -> 0 | H203: =IF(DAY(A203)='Main Budget'!$K$8,('Main Budget'!$E$8)*2,0) -> 0 | K203: =K202+SUM(E203:J203)-IF(E203>0,-'Main Budget'!$I$9,0) -> 105.10833 | L203: =D203+IF(E203>0,-'Main Budget'!$I$9,0) -> 6.92 | M203: =K203+L203 -> 112.02833
A204: 46223 | B204: =M203 -> 112.02833 | C204: =K203 -> 105.10833 | D204: =L203 -> 6.92 | E204: =IF(DAY(A204+2)=1,'Main Budget'!$E$29,IF(DAY(A204+2)=15,'Main Budget'!$E$29,0)) -> 0 | F204: =IF(OR(DAY(A204)=1,DAY(A204)=14),11.25,0) -> 0 | G204: =IF(DAY(A204)='Main Budget'!$K$7,('Main Budget'!$E$7),0) -> 0 | H204: =IF(DAY(A204)='Main Budget'!$K$8,('Main Budget'!$E$8)*2,0) -> 0 | K204: =K203+SUM(E204:J204)-IF(E204>0,-'Main Budget'!$I$9,0) -> 105.10833 | L204: =D204+IF(E204>0,-'Main Budget'!$I$9,0) -> 6.92 | M204: =K204+L204 -> 112.02833
A205: 46224 | B205: =M204 -> 112.02833 | C205: =K204 -> 105.10833 | D205: =L204 -> 6.92 | E205: =IF(DAY(A205+2)=1,'Main Budget'!$E$29,IF(DAY(A205+2)=15,'Main Budget'!$E$29,0)) -> 0 | F205: =IF(OR(DAY(A205)=1,DAY(A205)=14),11.25,0) -> 0 | G205: =IF(DAY(A205)='Main Budget'!$K$7,('Main Budget'!$E$7),0) -> 0 | H205: =IF(DAY(A205)='Main Budget'!$K$8,('Main Budget'!$E$8)*2,0) -> 0 | K205: =K204+SUM(E205:J205)-IF(E205>0,-'Main Budget'!$I$9,0) -> 105.10833 | L205: =D205+IF(E205>0,-'Main Budget'!$I$9,0) -> 6.92 | M205: =K205+L205 -> 112.02833
A206: 46225 | B206: =M205 -> 112.02833 | C206: =K205 -> 105.10833 | D206: =L205 -> 6.92 | E206: =IF(DAY(A206+2)=1,'Main Budget'!$E$29,IF(DAY(A206+2)=15,'Main Budget'!$E$29,0)) -> 0 | F206: =IF(OR(DAY(A206)=1,DAY(A206)=14),11.25,0) -> 0 | G206: =IF(DAY(A206)='Main Budget'!$K$7,('Main Budget'!$E$7),0) -> 0 | H206: =IF(DAY(A206)='Main Budget'!$K$8,('Main Budget'!$E$8)*2,0) -> 0 | K206: =K205+SUM(E206:J206)-IF(E206>0,-'Main Budget'!$I$9,0) -> 105.10833 | L206: =D206+IF(E206>0,-'Main Budget'!$I$9,0) -> 6.92 | M206: =K206+L206 -> 112.02833
A207: 46226 | B207: =M206 -> 112.02833 | C207: =K206 -> 105.10833 | D207: =L206 -> 6.92 | E207: =IF(DAY(A207+2)=1,'Main Budget'!$E$29,IF(DAY(A207+2)=15,'Main Budget'!$E$29,0)) -> 0 | F207: =IF(OR(DAY(A207)=1,DAY(A207)=14),11.25,0) -> 0 | G207: =IF(DAY(A207)='Main Budget'!$K$7,('Main Budget'!$E$7),0) -> 0 | H207: =IF(DAY(A207)='Main Budget'!$K$8,('Main Budget'!$E$8)*2,0) -> 0 | K207: =K206+SUM(E207:J207)-IF(E207>0,-'Main Budget'!$I$9,0) -> 105.10833 | L207: =D207+IF(E207>0,-'Main Budget'!$I$9,0) -> 6.92 | M207: =K207+L207 -> 112.02833
A208: 46227 | B208: =M207 -> 112.02833 | C208: =K207 -> 105.10833 | D208: =L207 -> 6.92 | E208: =IF(DAY(A208+2)=1,'Main Budget'!$E$29,IF(DAY(A208+2)=15,'Main Budget'!$E$29,0)) -> 0 | F208: =IF(OR(DAY(A208)=1,DAY(A208)=14),11.25,0) -> 0 | G208: =IF(DAY(A208)='Main Budget'!$K$7,('Main Budget'!$E$7),0) -> 0 | H208: =IF(DAY(A208)='Main Budget'!$K$8,('Main Budget'!$E$8)*2,0) -> 0 | K208: =K207+SUM(E208:J208)-IF(E208>0,-'Main Budget'!$I$9,0) -> 105.10833 | L208: =D208+IF(E208>0,-'Main Budget'!$I$9,0) -> 6.92 | M208: =K208+L208 -> 112.02833
A209: 46228 | B209: =M208 -> 112.02833 | C209: =K208 -> 105.10833 | D209: =L208 -> 6.92 | E209: =IF(DAY(A209+2)=1,'Main Budget'!$E$29,IF(DAY(A209+2)=15,'Main Budget'!$E$29,0)) -> 0 | F209: =IF(OR(DAY(A209)=1,DAY(A209)=14),11.25,0) -> 0 | G209: =IF(DAY(A209)='Main Budget'!$K$7,('Main Budget'!$E$7),0) -> 0 | H209: =IF(DAY(A209)='Main Budget'!$K$8,('Main Budget'!$E$8)*2,0) -> 0 | K209: =K208+SUM(E209:J209)-IF(E209>0,-'Main Budget'!$I$9,0) -> 105.10833 | L209: =D209+IF(E209>0,-'Main Budget'!$I$9,0) -> 6.92 | M209: =K209+L209 -> 112.02833
A210: 46229 | B210: =M209 -> 112.02833 | C210: =K209 -> 105.10833 | D210: =L209 -> 6.92 | E210: =IF(DAY(A210+2)=1,'Main Budget'!$E$29,IF(DAY(A210+2)=15,'Main Budget'!$E$29,0)) -> 0 | F210: =IF(OR(DAY(A210)=1,DAY(A210)=14),11.25,0) -> 0 | G210: =IF(DAY(A210)='Main Budget'!$K$7,('Main Budget'!$E$7),0) -> 0 | H210: =IF(DAY(A210)='Main Budget'!$K$8,('Main Budget'!$E$8)*2,0) -> 0 | K210: =K209+SUM(E210:J210)-IF(E210>0,-'Main Budget'!$I$9,0) -> 105.10833 | L210: =D210+IF(E210>0,-'Main Budget'!$I$9,0) -> 6.92 | M210: =K210+L210 -> 112.02833
A211: 46230 | B211: =M210 -> 112.02833 | C211: =K210 -> 105.10833 | D211: =L210 -> 6.92 | E211: =IF(DAY(A211+2)=1,'Main Budget'!$E$29,IF(DAY(A211+2)=15,'Main Budget'!$E$29,0)) -> 0 | F211: =IF(OR(DAY(A211)=1,DAY(A211)=14),11.25,0) -> 0 | G211: =IF(DAY(A211)='Main Budget'!$K$7,('Main Budget'!$E$7),0) -> 0 | H211: =IF(DAY(A211)='Main Budget'!$K$8,('Main Budget'!$E$8)*2,0) -> 0 | K211: =K210+SUM(E211:J211)-IF(E211>0,-'Main Budget'!$I$9,0) -> 105.10833 | L211: =D211+IF(E211>0,-'Main Budget'!$I$9,0) -> 6.92 | M211: =K211+L211 -> 112.02833
A212: 46231 | B212: =M211 -> 112.02833 | C212: =K211 -> 105.10833 | D212: =L211 -> 6.92 | E212: =IF(DAY(A212+2)=1,'Main Budget'!$E$29,IF(DAY(A212+2)=15,'Main Budget'!$E$29,0)) -> 0 | F212: =IF(OR(DAY(A212)=1,DAY(A212)=14),11.25,0) -> 0 | G212: =IF(DAY(A212)='Main Budget'!$K$7,('Main Budget'!$E$7),0) -> 0 | H212: =IF(DAY(A212)='Main Budget'!$K$8,('Main Budget'!$E$8)*2,0) -> 0 | K212: =K211+SUM(E212:J212)-IF(E212>0,-'Main Budget'!$I$9,0) -> 105.10833 | L212: =D212+IF(E212>0,-'Main Budget'!$I$9,0) -> 6.92 | M212: =K212+L212 -> 112.02833
A213: 46232 | B213: =M212 -> 112.02833 | C213: =K212 -> 105.10833 | D213: =L212 -> 6.92 | E213: =IF(DAY(A213+2)=1,'Main Budget'!$E$29,IF(DAY(A213+2)=15,'Main Budget'!$E$29,0)) -> 0 | F213: =IF(OR(DAY(A213)=1,DAY(A213)=14),11.25,0) -> 0 | G213: =IF(DAY(A213)='Main Budget'!$K$7,('Main Budget'!$E$7),0) -> 0 | H213: =IF(DAY(A213)='Main Budget'!$K$8,('Main Budget'!$E$8)*2,0) -> 0 | J213: 6.59 | K213: =K212+SUM(E213:J213)-IF(E213>0,-'Main Budget'!$I$9,0) -> 111.69833 | L213: =D213+IF(E213>0,-'Main Budget'!$I$9,0) -> 6.92 | M213: =K213+L213 -> 118.61833
A214: 46233 | B214: =M213 -> 118.61833 | C214: =K213 -> 111.69833 | D214: =L213 -> 6.92 | E214: =IF(DAY(A214+2)=1,'Main Budget'!$E$29,IF(DAY(A214+2)=15,'Main Budget'!$E$29,0)) -> 84.998333 | F214: =IF(OR(DAY(A214)=1,DAY(A214)=14),11.25,0) -> 0 | G214: =IF(DAY(A214)='Main Budget'!$K$7,('Main Budget'!$E$7),0) -> 0 | H214: =IF(DAY(A214)='Main Budget'!$K$8,('Main Budget'!$E$8)*2,0) -> 0 | K214: =K213+SUM(E214:J214)-IF(E214>0,-'Main Budget'!$I$9,0) -> 189.77667 | L214: =D214+IF(E214>0,-'Main Budget'!$I$9,0) -> 13.84 | M214: =K214+L214 -> 203.61667
A215: 46234 | B215: =M214 -> 203.61667 | C215: =K214 -> 189.77667 | D215: =L214 -> 13.84 | E215: =IF(DAY(A215+2)=1,'Main Budget'!$E$29,IF(DAY(A215+2)=15,'Main Budget'!$E$29,0)) -> 0 | F215: =IF(OR(DAY(A215)=1,DAY(A215)=14),11.25,0) -> 0 | G215: =IF(DAY(A215)='Main Budget'!$K$7,('Main Budget'!$E$7),0) -> 0 | H215: =IF(DAY(A215)='Main Budget'!$K$8,('Main Budget'!$E$8)*2,0) -> 0 | K215: =K214+SUM(E215:J215)-IF(E215>0,-'Main Budget'!$I$9,0) -> 189.77667 | L215: =D215+IF(E215>0,-'Main Budget'!$I$9,0) -> 13.84 | M215: =K215+L215 -> 203.61667
A216: 46235 | B216: =M215 -> 203.61667 | C216: =K215 -> 189.77667 | D216: =L215 -> 13.84 | E216: =IF(DAY(A216+2)=1,'Main Budget'!$E$29,IF(DAY(A216+2)=15,'Main Budget'!$E$29,0)) -> 0 | F216: =IF(OR(DAY(A216)=1,DAY(A216)=14),11.25,0) -> 11.25 | G216: =IF(DAY(A216)='Main Budget'!$K$7,('Main Budget'!$E$7),0) -> 0 | H216: =IF(DAY(A216)='Main Budget'!$K$8,('Main Budget'!$E$8)*2,0) -> 0 | K216: =K215+SUM(E216:J216)-IF(E216>0,-'Main Budget'!$I$9,0) -> 201.02667 | L216: =D216+IF(E216>0,-'Main Budget'!$I$9,0) -> 13.84 | M216: =K216+L216 -> 214.86667
A217: 46236 | B217: =M216 -> 214.86667 | C217: =K216 -> 201.02667 | D217: =L216 -> 13.84 | E217: =IF(DAY(A217+2)=1,'Main Budget'!$E$29,IF(DAY(A217+2)=15,'Main Budget'!$E$29,0)) -> 0 | F217: =IF(OR(DAY(A217)=1,DAY(A217)=14),11.25,0) -> 0 | G217: =IF(DAY(A217)='Main Budget'!$K$7,('Main Budget'!$E$7),0) -> 0 | H217: =IF(DAY(A217)='Main Budget'!$K$8,('Main Budget'!$E$8)*2,0) -> 0 | K217: =K216+SUM(E217:J217)-IF(E217>0,-'Main Budget'!$I$9,0) -> 201.02667 | L217: =D217+IF(E217>0,-'Main Budget'!$I$9,0) -> 13.84 | M217: =K217+L217 -> 214.86667
A218: 46237 | B218: =M217 -> 214.86667 | C218: =K217 -> 201.02667 | D218: =L217 -> 13.84 | E218: =IF(DAY(A218+2)=1,'Main Budget'!$E$29,IF(DAY(A218+2)=15,'Main Budget'!$E$29,0)) -> 0 | F218: =IF(OR(DAY(A218)=1,DAY(A218)=14),11.25,0) -> 0 | G218: =IF(DAY(A218)='Main Budget'!$K$7,('Main Budget'!$E$7),0) -> 0 | H218: =IF(DAY(A218)='Main Budget'!$K$8,('Main Budget'!$E$8)*2,0) -> 0 | K218: =K217+SUM(E218:J218)-IF(E218>0,-'Main Budget'!$I$9,0) -> 201.02667 | L218: =D218+IF(E218>0,-'Main Budget'!$I$9,0) -> 13.84 | M218: =K218+L218 -> 214.86667
A219: 46238 | B219: =M218 -> 214.86667 | C219: =K218 -> 201.02667 | D219: =L218 -> 13.84 | E219: =IF(DAY(A219+2)=1,'Main Budget'!$E$29,IF(DAY(A219+2)=15,'Main Budget'!$E$29,0)) -> 0 | F219: =IF(OR(DAY(A219)=1,DAY(A219)=14),11.25,0) -> 0 | G219: =IF(DAY(A219)='Main Budget'!$K$7,('Main Budget'!$E$7),0) -> 0 | H219: =IF(DAY(A219)='Main Budget'!$K$8,('Main Budget'!$E$8)*2,0) -> 0 | K219: =K218+SUM(E219:J219)-IF(E219>0,-'Main Budget'!$I$9,0) -> 201.02667 | L219: =D219+IF(E219>0,-'Main Budget'!$I$9,0) -> 13.84 | M219: =K219+L219 -> 214.86667
A220: 46239 | B220: =M219 -> 214.86667 | C220: =K219 -> 201.02667 | D220: =L219 -> 13.84 | E220: =IF(DAY(A220+2)=1,'Main Budget'!$E$29,IF(DAY(A220+2)=15,'Main Budget'!$E$29,0)) -> 0 | F220: =IF(OR(DAY(A220)=1,DAY(A220)=14),11.25,0) -> 0 | G220: =IF(DAY(A220)='Main Budget'!$K$7,('Main Budget'!$E$7),0) -> 0 | H220: =IF(DAY(A220)='Main Budget'!$K$8,('Main Budget'!$E$8)*2,0) -> 0 | K220: =K219+SUM(E220:J220)-IF(E220>0,-'Main Budget'!$I$9,0) -> 201.02667 | L220: =D220+IF(E220>0,-'Main Budget'!$I$9,0) -> 13.84 | M220: =K220+L220 -> 214.86667
A221: 46240 | B221: =M220 -> 214.86667 | C221: =K220 -> 201.02667 | D221: =L220 -> 13.84 | E221: =IF(DAY(A221+2)=1,'Main Budget'!$E$29,IF(DAY(A221+2)=15,'Main Budget'!$E$29,0)) -> 0 | F221: =IF(OR(DAY(A221)=1,DAY(A221)=14),11.25,0) -> 0 | G221: =IF(DAY(A221)='Main Budget'!$K$7,('Main Budget'!$E$7),0) -> 0 | H221: =IF(DAY(A221)='Main Budget'!$K$8,('Main Budget'!$E$8)*2,0) -> 0 | K221: =K220+SUM(E221:J221)-IF(E221>0,-'Main Budget'!$I$9,0) -> 201.02667 | L221: =D221+IF(E221>0,-'Main Budget'!$I$9,0) -> 13.84 | M221: =K221+L221 -> 214.86667
A222: 46241 | B222: =M221 -> 214.86667 | C222: =K221 -> 201.02667 | D222: =L221 -> 13.84 | E222: =IF(DAY(A222+2)=1,'Main Budget'!$E$29,IF(DAY(A222+2)=15,'Main Budget'!$E$29,0)) -> 0 | F222: =IF(OR(DAY(A222)=1,DAY(A222)=14),11.25,0) -> 0 | G222: =IF(DAY(A222)='Main Budget'!$K$7,('Main Budget'!$E$7),0) -> 0 | H222: =IF(DAY(A222)='Main Budget'!$K$8,('Main Budget'!$E$8)*2,0) -> 0 | K222: =K221+SUM(E222:J222)-IF(E222>0,-'Main Budget'!$I$9,0) -> 201.02667 | L222: =D222+IF(E222>0,-'Main Budget'!$I$9,0) -> 13.84 | M222: =K222+L222 -> 214.86667
A223: 46242 | B223: =M222 -> 214.86667 | C223: =K222 -> 201.02667 | D223: =L222 -> 13.84 | E223: =IF(DAY(A223+2)=1,'Main Budget'!$E$29,IF(DAY(A223+2)=15,'Main Budget'!$E$29,0)) -> 0 | F223: =IF(OR(DAY(A223)=1,DAY(A223)=14),11.25,0) -> 0 | G223: =IF(DAY(A223)='Main Budget'!$K$7,('Main Budget'!$E$7),0) -> 0 | H223: =IF(DAY(A223)='Main Budget'!$K$8,('Main Budget'!$E$8)*2,0) -> 0 | K223: =K222+SUM(E223:J223)-IF(E223>0,-'Main Budget'!$I$9,0) -> 201.02667 | L223: =D223+IF(E223>0,-'Main Budget'!$I$9,0) -> 13.84 | M223: =K223+L223 -> 214.86667
A224: 46243 | B224: =M223 -> 214.86667 | C224: =K223 -> 201.02667 | D224: =L223 -> 13.84 | E224: =IF(DAY(A224+2)=1,'Main Budget'!$E$29,IF(DAY(A224+2)=15,'Main Budget'!$E$29,0)) -> 0 | F224: =IF(OR(DAY(A224)=1,DAY(A224)=14),11.25,0) -> 0 | G224: =IF(DAY(A224)='Main Budget'!$K$7,('Main Budget'!$E$7),0) -> 0 | H224: =IF(DAY(A224)='Main Budget'!$K$8,('Main Budget'!$E$8)*2,0) -> 0 | K224: =K223+SUM(E224:J224)-IF(E224>0,-'Main Budget'!$I$9,0) -> 201.02667 | L224: =D224+IF(E224>0,-'Main Budget'!$I$9,0) -> 13.84 | M224: =K224+L224 -> 214.86667
A225: 46244 | B225: =M224 -> 214.86667 | C225: =K224 -> 201.02667 | D225: =L224 -> 13.84 | E225: =IF(DAY(A225+2)=1,'Main Budget'!$E$29,IF(DAY(A225+2)=15,'Main Budget'!$E$29,0)) -> 0 | F225: =IF(OR(DAY(A225)=1,DAY(A225)=14),11.25,0) -> 0 | G225: =IF(DAY(A225)='Main Budget'!$K$7,('Main Budget'!$E$7),0) -> 0 | H225: =IF(DAY(A225)='Main Budget'!$K$8,('Main Budget'!$E$8)*2,0) -> 0 | K225: =K224+SUM(E225:J225)-IF(E225>0,-'Main Budget'!$I$9,0) -> 201.02667 | L225: =D225+IF(E225>0,-'Main Budget'!$I$9,0) -> 13.84 | M225: =K225+L225 -> 214.86667
... A243: 46262 | B243: =M242 -> 191.135 | C243: =K242 -> 170.375 | D243: =L242 -> 20.76 | E243: =IF(DAY(A243+2)=1,'Main Budget'!$E$29,IF(DAY(A243+2)=15,'Main Budget'!$E$29,0)) -> 0 | F243: =IF(OR(DAY(A243)=1,DAY(A243)=14),11.25,0) -> 0 | G243: =IF(DAY(A243)='Main Budget'!$K$7,('Main Budget'!$E$7),0) -> 0 | H243: =IF(DAY(A243)='Main Budget'!$K$8,('Main Budget'!$E$8)*2,0) -> 0 | K243: =K242+SUM(E243:J243)-IF(E243>0,-'Main Budget'!$I$9,0) -> 170.375 | L243: =D243+IF(E243>0,-'Main Budget'!$I$9,0) -> 20.76 | M243: =K243+L243 -> 191.135
