Workbook
Name PlatformFees: 'Fee Reference'!$A$4:$C$15
Name PlatformList: 'Fee Reference'!$A$4:$A$15

Sheet Dashboard
B2: PRESTINE AUCTION — COLLECTION TRACKER
B3: Last Refreshed: | C3: =NOW() -> 46232.57
B5: Total Items | E5: Total Invested | H5: Items Sold | K5: Realized Profit
B6: =COUNTA(Inventory!A2:A35) -> 34 | E6: =Inventory!N36 -> 1067.14 | H6: =COUNTIF(Inventory!B2:B35,"Sold") -> 0 | K6: =SUM('Sales Log'!P4:P303) -> 0
B8: Items Listed | E8: Capital Tied Up | H8: Sell-Through Rate | K8: Blended ROI %
B9: =COUNTIF(Inventory!B2:B35,"Listed") -> 16 | E9: =SUMIF(Inventory!B2:B35,"<>Sold",Inventory!N2:N35) -> 1067.14 | H9: =IFERROR(COUNTIF(Inventory!B2:B35,"Sold")/COUNTA(Inventory!A2:A35),0) -> 0 | K9: =IFERROR(SUM('Sales Log'!P4:P303)/SUMIF('Sales Log'!F4:F303,">0",'Sales Log'!O4:O303),0) -> 0
B11: Gross Revenue | E11: Avg Days on Market | H11: Avg Cost / Item | K11: Highest Item Cost
B12: =SUM('Sales Log'!F4:F303) -> 0 | E12: =IFERROR(AVERAGEIF(Inventory!AE2:AE35,"<>",Inventory!AG2:AG35),0) -> 11.8125 | H12: =IFERROR(Inventory!N36/COUNTA(Inventory!A2:A35),0) -> 31.386471 | K12: =MAX(Inventory!N2:N35) -> 72.346756
B14: COST BREAKDOWN | H14: PROFIT SNAPSHOT
B15: Base Item Cost | E15: =SUM(Inventory!E2:E35) -> 974.59 | H15: Realized Gross Revenue | K15: =SUM('Sales Log'!F4:F303) -> 0
B16: Discounts Saved | E16: =SUM(Inventory!I2:I35) -> 221 | H16: Total Fees Paid | K16: =SUM('Sales Log'!K4:K303)+SUM('Sales Log'!L4:L303)+SUM('Sales Log'!M4:M303) -> 0
B17: Shipping | E17: =SUM(Inventory!K2:K35) -> 218.78 | H17: COGS (Items Sold) | K17: =SUMIF('Sales Log'!F4:F303,">0",'Sales Log'!O4:O303) -> 0
B18: Tax | E18: =SUM(Inventory!M2:M35) -> 94.77 | H18: Realized Net Profit | J18: {=SUMPRODUCT((Inventory!$B$2:$B$35<>"Sold")*(Inventory!$B$2:$B$35<>"Kept for Self")*IFERROR(Inventory!$U$2:$U$35-Inventory!$U$2:$U$35*(Inventory!$P$2:$P$35+Inventory!$S$2:$S$35)-Inventory!$Q$2:$Q$35-Inventory!$R$2:$R$35-Inventory!$N$2:$N$35,0))} -> 859.07233 | K18: =SUM('Sales Log'!P4:P303) -> 0
B19: Net Total Landed Cost | E19: =SUM(Inventory!N2:N35) -> 1067.14 | H19: Unrealized Potential Profit | K19: {=SUMPRODUCT((Inventory!$B$2:$B$35<>"Sold")*(Inventory!$B$2:$B$35<>"Kept for Self")*IFERROR(Inventory!$U$2:$U$35-Inventory!$U$2:$U$35*(Inventory!$P$2:$P$35+Inventory!$S$2:$S$35)-Inventory!$Q$2:$Q$35-Inventory!$R$2:$R$35-Inventory!$N$2:$N$35,0))} -> 859.07233
B21: TOP 5 MOST EXPENSIVE ITEMS (BY LANDED COST) | H21: BEST-PERFORMING CATEGORIES (BY REALIZED PROFIT)
B22: Rank | C22: Item Name | E22: Category | F22: True Cost | H22: Rank | I22: Category | K22: Profit
B23: 1 | C23: =INDEX(Inventory!$A$2:$A$35,MATCH(LARGE(Inventory!$N$2:$N$35,1),Inventory!$N$2:$N$35,0)) -> Charlie Sheen, Tom Berenger & Corbin Bernsen Signed Jersey (Beckett) | E23: =INDEX(Inventory!$Y$2:$Y$35,MATCH(LARGE(Inventory!$N$2:$N$35,1),Inventory!$N$2:$N$35,0)) -> Jersey | F23: =LARGE(Inventory!$N$2:$N$35,1) -> 72.346756 | H23: 1 | I23: =IFERROR(INDEX(Categories!$A$5:$A$13,MATCH(LARGE(Categories!$G$5:$G$13,1),Categories!$G$5:$G$13,0)),"—") -> Jersey | K23: =IFERROR(LARGE(Categories!$G$5:$G$13,1),0) -> 0
B24: 2 | C24: =INDEX(Inventory!$A$2:$A$35,MATCH(LARGE(Inventory!$N$2:$N$35,2),Inventory!$N$2:$N$35,0)) -> Ari Lehman Signed "Friday the 13th" Jason Voorhees Mask Inscribed "Jason 1" (Beckett) | E24: =INDEX(Inventory!$Y$2:$Y$35,MATCH(LARGE(Inventory!$N$2:$N$35,2),Inventory!$N$2:$N$35,0)) -> Mask | F24: =LARGE(Inventory!$N$2:$N$35,2) -> 55.90334 | H24: 2 | I24: =IFERROR(INDEX(Categories!$A$5:$A$13,MATCH(LARGE(Categories!$G$5:$G$13,2),Categories!$G$5:$G$13,0)),"—") -> Jersey | K24: =IFERROR(LARGE(Categories!$G$5:$G$13,2),0) -> 0
B25: 3 | C25: =INDEX(Inventory!$A$2:$A$35,MATCH(LARGE(Inventory!$N$2:$N$35,3),Inventory!$N$2:$N$35,0)) -> Steve Spurrier Signed Florida Gators 8x10 Photo Inscribed "Go Gators" (ACOA) | E25: =INDEX(Inventory!$Y$2:$Y$35,MATCH(LARGE(Inventory!$N$2:$N$35,3),Inventory!$N$2:$N$35,0)) -> Photo | F25: =LARGE(Inventory!$N$2:$N$35,3) -> 54.934251 | H25: 3 | I25: =IFERROR(INDEX(Categories!$A$5:$A$13,MATCH(LARGE(Categories!$G$5:$G$13,3),Categories!$G$5:$G$13,0)),"—") -> Jersey | K25: =IFERROR(LARGE(Categories!$G$5:$G$13,3),0) -> 0
B26: 4 | C26: =INDEX(Inventory!$A$2:$A$35,MATCH(LARGE(Inventory!$N$2:$N$35,4),Inventory!$N$2:$N$35,0)) -> Chad Smith Signed 16" Drum Stick (Beckett) | E26: =INDEX(Inventory!$Y$2:$Y$35,MATCH(LARGE(Inventory!$N$2:$N$35,4),Inventory!$N$2:$N$35,0)) -> Drum Stick | F26: =LARGE(Inventory!$N$2:$N$35,4) -> 47.480319 | H26: 4 | I26: =IFERROR(INDEX(Categories!$A$5:$A$13,MATCH(LARGE(Categories!$G$5:$G$13,4),Categories!$G$5:$G$13,0)),"—") -> Jersey | K26: =IFERROR(LARGE(Categories!$G$5:$G$13,4),0) -> 0
B27: 5 | C27: =INDEX(Inventory!$A$2:$A$35,MATCH(LARGE(Inventory!$N$2:$N$35,5),Inventory!$N$2:$N$35,0)) -> Shawn Kemp Signed Jersey (JSA) | E27: =INDEX(Inventory!$Y$2:$Y$35,MATCH(LARGE(Inventory!$N$2:$N$35,5),Inventory!$N$2:$N$35,0)) -> Jersey | F27: =LARGE(Inventory!$N$2:$N$35,5) -> 44.722672 | H27: 5 | I27: =IFERROR(INDEX(Categories!$A$5:$A$13,MATCH(LARGE(Categories!$G$5:$G$13,5),Categories!$G$5:$G$13,0)),"—") -> Jersey | K27: =IFERROR(LARGE(Categories!$G$5:$G$13,5),0) -> 0
B30: QUICK NAVIGATION
B31: ▶ True Cost | D31: ▶ Sales Log | F31: ▶ Pricing Intelligence
B32: 💡 Click sheet tabs at bottom of Excel to navigate, or use Ctrl+Page Down / Ctrl+Page Up

Sheet Inventory
A1: Item Name | B1: Status | C1: Invoice ID | D1: Unit Price | E1: Item Base Total | F1: Invoice Base Total | G1: Proration Weight | H1: Invoice Total Discount | I1: Prorated Discount | J1: Invoice Total Shipping | K1: Prorated Shipping | L1: Invoice Total Tax | M1: Prorated Tax | N1: True Total Cost | O1: Platform | P1: Platform Fee % | Q1: Platform Flat Fee | R1: Est. Shipping Cost | S1: Boost % | T1: Min Sell Price | U1: Suggested List Price | V1: Current List Price | W1: Actual Sell Price | X1: Profit/Loss | Y1: Category | Z1: Sport / Genre | AA1: Athlete / Person | AB1: Authenticator | AC1: Cert # | AD1: Date Acquired | AE1: Date Listed | AF1: Date Sold | AG1: Days on Market | AH1: eBay Sold Comps | AI1: ROI % (Actual) | AJ1: Margin % (Target) | AK1: Notes | AL1: Best Listing Window
A2: Shawn Kemp Signed 1990-91 Hoops #279 RC (JSA) | B2: Kept for Self | C2: 4809173 | D2: 17.01 | E2: =D2 -> 17.01 | F2: =SUMIF(C:C, C2, E:E) -> 140.13 | G2: =E2/F2 -> 0.12138728 | H2: 45 | I2: =H2*G2 -> 5.4624277 | J2: 25.77 | K2: =J2*G2 -> 3.1281503 | L2: 13.01 | M2: =L2*G2 -> 1.5792486 | N2: =E2-I2+K2+M2 -> 16.254971 | O2: eBay | P2: =IFERROR(VLOOKUP(O2,PlatformFees,2,FALSE()),0) -> 0.136 | Q2: =IFERROR(VLOOKUP(O2,PlatformFees,3,FALSE()),0) -> 0.4 | R2: 6.5 | S2: 0 | T2: =(N2+R2+Q2)/(1-(P2+S2)) -> 26.799735 | U2: =MAX(MAX(T2*1.5, T2+15), IFERROR(VLOOKUP(A2,'Pricing Intelligence'!A:J,10,FALSE),0)) -> 51.33 | V2: 0 | W2: =IFERROR(_xlfn.XLOOKUP(A2,'Sales Log'!$C$4:$C$303,'Sales Log'!$F$4:$F$303,0),0) -> 0 | X2: =IF(W2=0,0,W2-(W2*(P2+S2))-Q2-R2-N2) -> 0 | Y2: =IFERROR(IF(ISNUMBER(SEARCH("Jersey",A2)),"Jersey",IF(ISNUMBER(SEARCH("Photo",A2)),"Photo",IF(ISNUMBER(SEARCH("Baseball Bat",A2)),"Bat",IF(ISNUMBER(SEARCH("Bat",A2)),"Bat",IF(ISNUMBER(SEARCH("Baseball",A2)),"Baseball",IF(ISNUMBER(SEARCH("Football",A2)),"Football",IF(ISNUMBER(SEARCH("Mask",A2)),"Mask",IF(ISNUMBER(SEARCH("Drum",A2)),"Drum Stick",IF(ISNUMBER(SEARCH("Card",A2)),"Card",IF(ISNUMBER(SEARCH("RC",A2)),"Card","Other")))))))))),"Other") -> Card | Z2: Basketball | AA2: =IFERROR(TRIM(LEFT(A2,FIND(" Signed",A2)-1)),LEFT(A2,20)) -> Shawn Kemp | AB2: =IF(ISNUMBER(SEARCH("(Beckett)",A2)),"Beckett",IF(ISNUMBER(SEARCH("(JSA)",A2)),"JSA",IF(ISNUMBER(SEARCH("(PSA)",A2)),"PSA",IF(ISNUMBER(SEARCH("(ACOA)",A2)),"ACOA",IF(ISNUMBER(SEARCH("(Schwartz)",A2)),"Schwartz","Unlabeled"))))) -> JSA | AD2: 46197 | AG2: =IF(AE2="","",IF(AF2="",TODAY()-AE2,AF2-AE2)) | AH2: =HYPERLINK("https://www.ebay.com/sch/i.html?_nkw="&SUBSTITUTE(SUBSTITUTE(A2," ","+"),"""","")&"&LH_Sold=1&LH_Complete=1","View Sold Comps") -> View Sold Comps | AI2: =IF(OR(N2=0,W2=0),"",X2/N2) | AJ2: =IF(U2=0,"",(U2-U2*P2-Q2-R2-N2)/U2) -> 0.41289984 | AL2: =IF(B2="Kept for Self","—",IF(Z2="Baseball","Apr – Oct (MLB Season)",IF(Z2="Football","Aug – Feb (NFL Season)",IF(Z2="Basketball","Oct – Jun (NBA Season)",IF(OR(Z2="Movie",Z2="TV"),IF(ISNUMBER(SEARCH("Friday the 13th",A2)),"Sep – Oct (Halloween)","Year-Round"),IF(Z2="Music","Year-Round","Year-Round")))))) -> —
A3: Mark Henn Signed "The Lion King" 8x10 Photo (Beckett) | B3: Listed | C3: 4809173 | D3: 17.82 | E3: =D3 -> 17.82 | F3: =SUMIF(C:C, C3, E:E) -> 140.13 | G3: =E3/F3 -> 0.12716763 | H3: 45 | I3: =H3*G3 -> 5.7225434 | J3: 25.77 | K3: =J3*G3 -> 3.2771098 | L3: 13.01 | M3: =L3*G3 -> 1.6544509 | N3: =E3-I3+K3+M3 -> 17.029017 | O3: eBay | P3: =IFERROR(VLOOKUP(O3,PlatformFees,2,FALSE()),0) -> 0.136 | Q3: =IFERROR(VLOOKUP(O3,PlatformFees,3,FALSE()),0) -> 0.4 | R3: 6.5 | S3: 0.05 | T3: =(N3+R3+Q3)/(1-(P3+S3)) -> 29.396827 | U3: =MAX(MAX(T3*1.5, T3+15), IFERROR(VLOOKUP(A3,'Pricing Intelligence'!A:J,10,FALSE),0)) -> 44.396827 | V3: 51.29 | W3: =IFERROR(_xlfn.XLOOKUP(A3,'Sales Log'!$C$4:$C$303,'Sales Log'!$F$4:$F$303,0),0) -> 0 | X3: =IF(W3=0,0,W3-(W3*(P3+S3))-Q3-R3-N3) -> 0 | Y3: =IFERROR(IF(ISNUMBER(SEARCH("Jersey",A3)),"Jersey",IF(ISNUMBER(SEARCH("Photo",A3)),"Photo",IF(ISNUMBER(SEARCH("Baseball Bat",A3)),"Bat",IF(ISNUMBER(SEARCH("Bat",A3)),"Bat",IF(ISNUMBER(SEARCH("Baseball",A3)),"Baseball",IF(ISNUMBER(SEARCH("Football",A3)),"Football",IF(ISNUMBER(SEARCH("Mask",A3)),"Mask",IF(ISNUMBER(SEARCH("Drum",A3)),"Drum Stick",IF(ISNUMBER(SEARCH("Card",A3)),"Card",IF(ISNUMBER(SEARCH("RC",A3)),"Card","Other")))))))))),"Other") -> Photo | Z3: Movie | AA3: =IFERROR(TRIM(LEFT(A3,FIND(" Signed",A3)-1)),LEFT(A3,20)) -> Mark Henn | AB3: =IF(ISNUMBER(SEARCH("(Beckett)",A3)),"Beckett",IF(ISNUMBER(SEARCH("(JSA)",A3)),"JSA",IF(ISNUMBER(SEARCH("(PSA)",A3)),"PSA",IF(ISNUMBER(SEARCH("(ACOA)",A3)),"ACOA",IF(ISNUMBER(SEARCH("(Schwartz)",A3)),"Schwartz","Unlabeled"))))) -> Beckett | AD3: 46197 | AE3: 46211 | AG3: =IF(AE3="","",IF(AF3="",TODAY()-AE3,AF3-AE3)) -> 21 | AH3: =HYPERLINK("https://www.ebay.com/sch/i.html?_nkw="&SUBSTITUTE(SUBSTITUTE(A3," ","+"),"""","")&"&LH_Sold=1&LH_Complete=1","View Sold Comps") -> View Sold Comps | AI3: =IF(OR(N3=0,W3=0),"",X3/N3) | AJ3: =IF(U3=0,"",(U3-U3*P3-Q3-R3-N3)/U3) -> 0.32501965 | AL3: =IF(B3="Kept for Self","—",IF(Z3="Baseball","Apr – Oct (MLB Season)",IF(Z3="Football","Aug – Feb (NFL Season)",IF(Z3="Basketball","Oct – Jun (NBA Season)",IF(OR(Z3="Movie",Z3="TV"),IF(ISNUMBER(SEARCH("Friday the 13th",A3)),"Sep – Oct (Halloween)","Year-Round"),IF(Z3="Music","Year-Round","Year-Round")))))) -> Year-Round
A4: Ari Lehman Signed "Friday the 13th" Jason Voorhees Mask Inscribed "Jason 1" (Beckett) | B4: Listed | C4: 4809173 | D4: 58.5 | E4: =D4 -> 58.5 | F4: =SUMIF(C:C, C4, E:E) -> 140.13 | G4: =E4/F4 -> 0.41746949 | H4: 45 | I4: =H4*G4 -> 18.786127 | J4: 25.77 | K4: =J4*G4 -> 10.758189 | L4: 13.01 | M4: =L4*G4 -> 5.4312781 | N4: =E4-I4+K4+M4 -> 55.90334 | O4: eBay | P4: =IFERROR(VLOOKUP(O4,PlatformFees,2,FALSE()),0) -> 0.136 | Q4: =IFERROR(VLOOKUP(O4,PlatformFees,3,FALSE()),0) -> 0.4 | R4: 6.5 | S4: 0.02 | T4: =(N4+R4+Q4)/(1-(P4+S4)) -> 74.41154 | U4: =MAX(MAX(T4*1.5, T4+15), IFERROR(VLOOKUP(A4,'Pricing Intelligence'!A:J,10,FALSE),0)) -> 111.61731 | V4: 39 | W4: =IFERROR(_xlfn.XLOOKUP(A4,'Sales Log'!$C$4:$C$303,'Sales Log'!$F$4:$F$303,0),0) -> 0 | X4: =IF(W4=0,0,W4-(W4*(P4+S4))-Q4-R4-N4) -> 0 | Y4: =IFERROR(IF(ISNUMBER(SEARCH("Jersey",A4)),"Jersey",IF(ISNUMBER(SEARCH("Photo",A4)),"Photo",IF(ISNUMBER(SEARCH("Baseball Bat",A4)),"Bat",IF(ISNUMBER(SEARCH("Bat",A4)),"Bat",IF(ISNUMBER(SEARCH("Baseball",A4)),"Baseball",IF(ISNUMBER(SEARCH("Football",A4)),"Football",IF(ISNUMBER(SEARCH("Mask",A4)),"Mask",IF(ISNUMBER(SEARCH("Drum",A4)),"Drum Stick",IF(ISNUMBER(SEARCH("Card",A4)),"Card",IF(ISNUMBER(SEARCH("RC",A4)),"Card","Other")))))))))),"Other") -> Mask | Z4: Movie | AA4: =IFERROR(TRIM(LEFT(A4,FIND(" Signed",A4)-1)),LEFT(A4,20)) -> Ari Lehman | AB4: =IF(ISNUMBER(SEARCH("(Beckett)",A4)),"Beckett",IF(ISNUMBER(SEARCH("(JSA)",A4)),"JSA",IF(ISNUMBER(SEARCH("(PSA)",A4)),"PSA",IF(ISNUMBER(SEARCH("(ACOA)",A4)),"ACOA",IF(ISNUMBER(SEARCH("(Schwartz)",A4)),"Schwartz","Unlabeled"))))) -> Beckett | AD4: 46197 | AE4: 46211 | AG4: =IF(AE4="","",IF(AF4="",TODAY()-AE4,AF4-AE4)) -> 21 | AH4: =HYPERLINK("https://www.ebay.com/sch/i.html?_nkw="&SUBSTITUTE(SUBSTITUTE(A4," ","+"),"""","")&"&LH_Sold=1&LH_Complete=1","View Sold Comps") -> View Sold Comps | AI4: =IF(OR(N4=0,W4=0),"",X4/N4) | AJ4: =IF(U4=0,"",(U4-U4*P4-Q4-R4-N4)/U4) -> 0.30133333 | AL4: =IF(B4="Kept for Self","—",IF(Z4="Baseball","Apr – Oct (MLB Season)",IF(Z4="Football","Aug – Feb (NFL Season)",IF(Z4="Basketball","Oct – Jun (NBA Season)",IF(OR(Z4="Movie",Z4="TV"),IF(ISNUMBER(SEARCH("Friday the 13th",A4)),"Sep – Oct (Halloween)","Year-Round"),IF(Z4="Music","Year-Round","Year-Round")))))) -> Sep – Oct (Halloween)
A5: Shawn Kemp Signed Jersey (JSA) | B5: Kept for Self | C5: 4809173 | D5: 46.8 | E5: =D5 -> 46.8 | F5: =SUMIF(C:C, C5, E:E) -> 140.13 | G5: =E5/F5 -> 0.33397559 | H5: 45 | I5: =H5*G5 -> 15.028902 | J5: 25.77 | K5: =J5*G5 -> 8.6065511 | L5: 13.01 | M5: =L5*G5 -> 4.3450225 | N5: =E5-I5+K5+M5 -> 44.722672 | O5: eBay | P5: =IFERROR(VLOOKUP(O5,PlatformFees,2,FALSE()),0) -> 0.136 | Q5: =IFERROR(VLOOKUP(O5,PlatformFees,3,FALSE()),0) -> 0.4 | R5: 6.5 | S5: 0 | T5: =(N5+R5+Q5)/(1-(P5+S5)) -> 59.748463 | U5: =MAX(MAX(T5*1.5, T5+15), IFERROR(VLOOKUP(A5,'Pricing Intelligence'!A:J,10,FALSE),0)) -> 89.622694 | V5: 0 | W5: =IFERROR(_xlfn.XLOOKUP(A5,'Sales Log'!$C$4:$C$303,'Sales Log'!$F$4:$F$303,0),0) -> 0 | X5: =IF(W5=0,0,W5-(W5*(P5+S5))-Q5-R5-N5) -> 0 | Y5: =IFERROR(IF(ISNUMBER(SEARCH("Jersey",A5)),"Jersey",IF(ISNUMBER(SEARCH("Photo",A5)),"Photo",IF(ISNUMBER(SEARCH("Baseball Bat",A5)),"Bat",IF(ISNUMBER(SEARCH("Bat",A5)),"Bat",IF(ISNUMBER(SEARCH("Baseball",A5)),"Baseball",IF(ISNUMBER(SEARCH("Football",A5)),"Football",IF(ISNUMBER(SEARCH("Mask",A5)),"Mask",IF(ISNUMBER(SEARCH("Drum",A5)),"Drum Stick",IF(ISNUMBER(SEARCH("Card",A5)),"Card",IF(ISNUMBER(SEARCH("RC",A5)),"Card","Other")))))))))),"Other") -> Jersey | Z5: Basketball | AA5: =IFERROR(TRIM(LEFT(A5,FIND(" Signed",A5)-1)),LEFT(A5,20)) -> Shawn Kemp | AB5: =IF(ISNUMBER(SEARCH("(Beckett)",A5)),"Beckett",IF(ISNUMBER(SEARCH("(JSA)",A5)),"JSA",IF(ISNUMBER(SEARCH("(PSA)",A5)),"PSA",IF(ISNUMBER(SEARCH("(ACOA)",A5)),"ACOA",IF(ISNUMBER(SEARCH("(Schwartz)",A5)),"Schwartz","Unlabeled"))))) -> JSA | AD5: 46197 | AG5: =IF(AE5="","",IF(AF5="",TODAY()-AE5,AF5-AE5)) | AH5: =HYPERLINK("https://www.ebay.com/sch/i.html?_nkw="&SUBSTITUTE(SUBSTITUTE(A5," ","+"),"""","")&"&LH_Sold=1&LH_Complete=1","View Sold Comps") -> View Sold Comps | AI5: =IF(OR(N5=0,W5=0),"",X5/N5) | AJ5: =IF(U5=0,"",(U5-U5*P5-Q5-R5-N5)/U5) -> 0.288 | AL5: =IF(B5="Kept for Self","—",IF(Z5="Baseball","Apr – Oct (MLB Season)",IF(Z5="Football","Aug – Feb (NFL Season)",IF(Z5="Basketball","Oct – Jun (NBA Season)",IF(OR(Z5="Movie",Z5="TV"),IF(ISNUMBER(SEARCH("Friday the 13th",A5)),"Sep – Oct (Halloween)","Year-Round"),IF(Z5="Music","Year-Round","Year-Round")))))) -> —
A6: Cheech Marin & Tommy Chong Signed "The Simpsons" 8x10 Photo (JSA) | B6: Available | C6: 4814462 | D6: 26.43 | E6: =D6 -> 26.43 | F6: =SUMIF(C:C, C6, E:E) -> 84.15 | G6: =E6/F6 -> 0.314082 | H6: 45 | I6: =H6*G6 -> 14.13369 | J6: 5.77 | K6: =J6*G6 -> 1.8122531 | L6: 7.09 | M6: =L6*G6 -> 2.2268414 | N6: =E6-I6+K6+M6 -> 16.335405 | O6: eBay | P6: =IFERROR(VLOOKUP(O6,PlatformFees,2,FALSE()),0) -> 0.136 | Q6: =IFERROR(VLOOKUP(O6,PlatformFees,3,FALSE()),0) -> 0.4 | R6: 6.5 | S6: 0 | T6: =(N6+R6+Q6)/(1-(P6+S6)) -> 26.892829 | U6: =MAX(MAX(T6*1.5, T6+15), IFERROR(VLOOKUP(A6,'Pricing Intelligence'!A:J,10,FALSE),0)) -> 59.983333 | V6: 0 | W6: =IFERROR(_xlfn.XLOOKUP(A6,'Sales Log'!$C$4:$C$303,'Sales Log'!$F$4:$F$303,0),0) -> 0 | X6: =IF(W6=0,0,W6-(W6*(P6+S6))-Q6-R6-N6) -> 0 | Y6: =IFERROR(IF(ISNUMBER(SEARCH("Jersey",A6)),"Jersey",IF(ISNUMBER(SEARCH("Photo",A6)),"Photo",IF(ISNUMBER(SEARCH("Baseball Bat",A6)),"Bat",IF(ISNUMBER(SEARCH("Bat",A6)),"Bat",IF(ISNUMBER(SEARCH("Baseball",A6)),"Baseball",IF(ISNUMBER(SEARCH("Football",A6)),"Football",IF(ISNUMBER(SEARCH("Mask",A6)),"Mask",IF(ISNUMBER(SEARCH("Drum",A6)),"Drum Stick",IF(ISNUMBER(SEARCH("Card",A6)),"Card",IF(ISNUMBER(SEARCH("RC",A6)),"Card","Other")))))))))),"Other") -> Photo | Z6: TV | AA6: =IFERROR(TRIM(LEFT(A6,FIND(" Signed",A6)-1)),LEFT(A6,20)) -> Cheech Marin & Tommy Chong | AB6: =IF(ISNUMBER(SEARCH("(Beckett)",A6)),"Beckett",IF(ISNUMBER(SEARCH("(JSA)",A6)),"JSA",IF(ISNUMBER(SEARCH("(PSA)",A6)),"PSA",IF(ISNUMBER(SEARCH("(ACOA)",A6)),"ACOA",IF(ISNUMBER(SEARCH("(Schwartz)",A6)),"Schwartz","Unlabeled"))))) -> JSA | AD6: 46199 | AG6: =IF(AE6="","",IF(AF6="",TODAY()-AE6,AF6-AE6)) | AH6: =HYPERLINK("https://www.ebay.com/sch/i.html?_nkw="&SUBSTITUTE(SUBSTITUTE(A6," ","+"),"""","")&"&LH_Sold=1&LH_Complete=1","View Sold Comps") -> View Sold Comps | AI6: =IF(OR(N6=0,W6=0),"",X6/N6) | AJ6: =IF(U6=0,"",(U6-U6*P6-Q6-R6-N6)/U6) -> 0.47663565 | AL6: =IF(B6="Kept for Self","—",IF(Z6="Baseball","Apr – Oct (MLB Season)",IF(Z6="Football","Aug – Feb (NFL Season)",IF(Z6="Basketball","Oct – Jun (NBA Season)",IF(OR(Z6="Movie",Z6="TV"),IF(ISNUMBER(SEARCH("Friday the 13th",A6)),"Sep – Oct (Halloween)","Year-Round"),IF(Z6="Music","Year-Round","Year-Round")))))) -> Year-Round
A7: Chris Cooper Signed "Cars 3" 8x10 Photo Inscribed "AKA 'Smokey'" & "Best Wishes" (ACOA) | B7: Listed | C7: 4814462 | D7: 13.51 | E7: =D7 -> 13.51 | F7: =SUMIF(C:C, C7, E:E) -> 84.15 | G7: =E7/F7 -> 0.16054664 | H7: 45 | I7: =H7*G7 -> 7.2245989 | J7: 5.77 | K7: =J7*G7 -> 0.92635413 | L7: 7.09 | M7: =L7*G7 -> 1.1382757 | N7: =E7-I7+K7+M7 -> 8.3500309 | O7: eBay | P7: =IFERROR(VLOOKUP(O7,PlatformFees,2,FALSE()),0) -> 0.136 | Q7: =IFERROR(VLOOKUP(O7,PlatformFees,3,FALSE()),0) -> 0.4 | R7: 6.5 | S7: 0.05 | T7: =(N7+R7+Q7)/(1-(P7+S7)) -> 18.734682 | U7: =MAX(MAX(T7*1.5, T7+15), IFERROR(VLOOKUP(A7,'Pricing Intelligence'!A:J,10,FALSE),0)) -> 33.734682 | V7: 24.99 | W7: =IFERROR(_xlfn.XLOOKUP(A7,'Sales Log'!$C$4:$C$303,'Sales Log'!$F$4:$F$303,0),0) -> 0 | X7: =IF(W7=0,0,W7-(W7*(P7+S7))-Q7-R7-N7) -> 0 | Y7: =IFERROR(IF(ISNUMBER(SEARCH("Jersey",A7)),"Jersey",IF(ISNUMBER(SEARCH("Photo",A7)),"Photo",IF(ISNUMBER(SEARCH("Baseball Bat",A7)),"Bat",IF(ISNUMBER(SEARCH("Bat",A7)),"Bat",IF(ISNUMBER(SEARCH("Baseball",A7)),"Baseball",IF(ISNUMBER(SEARCH("Football",A7)),"Football",IF(ISNUMBER(SEARCH("Mask",A7)),"Mask",IF(ISNUMBER(SEARCH("Drum",A7)),"Drum Stick",IF(ISNUMBER(SEARCH("Card",A7)),"Card",IF(ISNUMBER(SEARCH("RC",A7)),"Card","Other")))))))))),"Other") -> Photo | Z7: Movie | AA7: =IFERROR(TRIM(LEFT(A7,FIND(" Signed",A7)-1)),LEFT(A7,20)) -> Chris Cooper | AB7: =IF(ISNUMBER(SEARCH("(Beckett)",A7)),"Beckett",IF(ISNUMBER(SEARCH("(JSA)",A7)),"JSA",IF(ISNUMBER(SEARCH("(PSA)",A7)),"PSA",IF(ISNUMBER(SEARCH("(ACOA)",A7)),"ACOA",IF(ISNUMBER(SEARCH("(Schwartz)",A7)),"Schwartz","Unlabeled"))))) -> ACOA | AD7: 46199 | AE7: 46211 | AG7: =IF(AE7="","",IF(AF7="",TODAY()-AE7,AF7-AE7)) -> 21 | AH7: =HYPERLINK("https://www.ebay.com/sch/i.html?_nkw="&SUBSTITUTE(SUBSTITUTE(A7," ","+"),"""","")&"&LH_Sold=1&LH_Complete=1","View Sold Comps") -> View Sold Comps | AI7: =IF(OR(N7=0,W7=0),"",X7/N7) | AJ7: =IF(U7=0,"",(U7-U7*P7-Q7-R7-N7)/U7) -> 0.41194205 | AL7: =IF(B7="Kept for Self","—",IF(Z7="Baseball","Apr – Oct (MLB Season)",IF(Z7="Football","Aug – Feb (NFL Season)",IF(Z7="Basketball","Oct – Jun (NBA Season)",IF(OR(Z7="Movie",Z7="TV"),IF(ISNUMBER(SEARCH("Friday the 13th",A7)),"Sep – Oct (Halloween)","Year-Round"),IF(Z7="Music","Year-Round","Year-Round")))))) -> Year-Round
A8: Frank Thomas Signed OML Baseball (JSA) | B8: Listed | C8: 4814462 | D8: 44.21 | E8: =D8 -> 44.21 | F8: =SUMIF(C:C, C8, E:E) -> 84.15 | G8: =E8/F8 -> 0.52537136 | H8: 45 | I8: =H8*G8 -> 23.641711 | J8: 5.77 | K8: =J8*G8 -> 3.0313928 | L8: 7.09 | M8: =L8*G8 -> 3.7248829 | N8: =E8-I8+K8+M8 -> 27.324564 | O8: eBay | P8: =IFERROR(VLOOKUP(O8,PlatformFees,2,FALSE()),0) -> 0.136 | Q8: =IFERROR(VLOOKUP(O8,PlatformFees,3,FALSE()),0) -> 0.4 | R8: 6.5 | S8: 0 | T8: =(N8+R8+Q8)/(1-(P8+S8)) -> 39.611764 | U8: =MAX(MAX(T8*1.5, T8+15), IFERROR(VLOOKUP(A8,'Pricing Intelligence'!A:J,10,FALSE),0)) -> 59.417647 | V8: 45 | W8: =IFERROR(_xlfn.XLOOKUP(A8,'Sales Log'!$C$4:$C$303,'Sales Log'!$F$4:$F$303,0),0) -> 0 | X8: =IF(W8=0,0,W8-(W8*(P8+S8))-Q8-R8-N8) -> 0 | Y8: =IFERROR(IF(ISNUMBER(SEARCH("Jersey",A8)),"Jersey",IF(ISNUMBER(SEARCH("Photo",A8)),"Photo",IF(ISNUMBER(SEARCH("Baseball Bat",A8)),"Bat",IF(ISNUMBER(SEARCH("Bat",A8)),"Bat",IF(ISNUMBER(SEARCH("Baseball",A8)),"Baseball",IF(ISNUMBER(SEARCH("Football",A8)),"Football",IF(ISNUMBER(SEARCH("Mask",A8)),"Mask",IF(ISNUMBER(SEARCH("Drum",A8)),"Drum Stick",IF(ISNUMBER(SEARCH("Card",A8)),"Card",IF(ISNUMBER(SEARCH("RC",A8)),"Card","Other")))))))))),"Other") -> Baseball | Z8: Baseball | AA8: =IFERROR(TRIM(LEFT(A8,FIND(" Signed",A8)-1)),LEFT(A8,20)) -> Frank Thomas | AB8: =IF(ISNUMBER(SEARCH("(Beckett)",A8)),"Beckett",IF(ISNUMBER(SEARCH("(JSA)",A8)),"JSA",IF(ISNUMBER(SEARCH("(PSA)",A8)),"PSA",IF(ISNUMBER(SEARCH("(ACOA)",A8)),"ACOA",IF(ISNUMBER(SEARCH("(Schwartz)",A8)),"Schwartz","Unlabeled"))))) -> JSA | AD8: 46199 | AE8: 46226 | AG8: =IF(AE8="","",IF(AF8="",TODAY()-AE8,AF8-AE8)) -> 6 | AH8: =HYPERLINK("https://www.ebay.com/sch/i.html?_nkw="&SUBSTITUTE(SUBSTITUTE(A8," ","+"),"""","")&"&LH_Sold=1&LH_Complete=1","View Sold Comps") -> View Sold Comps | AI8: =IF(OR(N8=0,W8=0),"",X8/N8) | AJ8: =IF(U8=0,"",(U8-U8*P8-Q8-R8-N8)/U8) -> 0.288 | AL8: =IF(B8="Kept for Self","—",IF(Z8="Baseball","Apr – Oct (MLB Season)",IF(Z8="Football","Aug – Feb (NFL Season)",IF(Z8="Basketball","Oct – Jun (NBA Season)",IF(OR(Z8="Movie",Z8="TV"),IF(ISNUMBER(SEARCH("Friday the 13th",A8)),"Sep – Oct (Halloween)","Year-Round"),IF(Z8="Music","Year-Round","Year-Round")))))) -> Apr – Oct (MLB Season)
A9: Jimbo Covert Signed NFL Football Inscribed "SB XX Champs" (JSA) | B9: Listed | C9: 4814637 | D9: 32.25 | E9: =D9 -> 32.25 | F9: =SUMIF(C:C, C9, E:E) -> 32.25 | G9: =E9/F9 -> 1 | H9: 20 | I9: =H9*G9 -> 20 | J9: 19.37 | K9: =J9*G9 -> 19.37 | L9: 4.06 | M9: =L9*G9 -> 4.06 | N9: =E9-I9+K9+M9 -> 35.68 | O9: eBay | P9: =IFERROR(VLOOKUP(O9,PlatformFees,2,FALSE()),0) -> 0.136 | Q9: =IFERROR(VLOOKUP(O9,PlatformFees,3,FALSE()),0) -> 0.4 | R9: 6.5 | S9: 0.03 | T9: =(N9+R9+Q9)/(1-(P9+S9)) -> 51.055156 | U9: =MAX(MAX(T9*1.5, T9+15), IFERROR(VLOOKUP(A9,'Pricing Intelligence'!A:J,10,FALSE),0)) -> 111 | V9: 129 | W9: =IFERROR(_xlfn.XLOOKUP(A9,'Sales Log'!$C$4:$C$303,'Sales Log'!$F$4:$F$303,0),0) -> 0 | X9: =IF(W9=0,0,W9-(W9*(P9+S9))-Q9-R9-N9) -> 0 | Y9: =IFERROR(IF(ISNUMBER(SEARCH("Jersey",A9)),"Jersey",IF(ISNUMBER(SEARCH("Photo",A9)),"Photo",IF(ISNUMBER(SEARCH("Baseball Bat",A9)),"Bat",IF(ISNUMBER(SEARCH("Bat",A9)),"Bat",IF(ISNUMBER(SEARCH("Baseball",A9)),"Baseball",IF(ISNUMBER(SEARCH("Football",A9)),"Football",IF(ISNUMBER(SEARCH("Mask",A9)),"Mask",IF(ISNUMBER(SEARCH("Drum",A9)),"Drum Stick",IF(ISNUMBER(SEARCH("Card",A9)),"Card",IF(ISNUMBER(SEARCH("RC",A9)),"Card","Other")))))))))),"Other") -> Football | Z9: Football | AA9: =IFERROR(TRIM(LEFT(A9,FIND(" Signed",A9)-1)),LEFT(A9,20)) -> Jimbo Covert | AB9: =IF(ISNUMBER(SEARCH("(Beckett)",A9)),"Beckett",IF(ISNUMBER(SEARCH("(JSA)",A9)),"JSA",IF(ISNUMBER(SEARCH("(PSA)",A9)),"PSA",IF(ISNUMBER(SEARCH("(ACOA)",A9)),"ACOA",IF(ISNUMBER(SEARCH("(Schwartz)",A9)),"Schwartz","Unlabeled"))))) -> JSA | AD9: 46199 | AE9: 46211 | AG9: =IF(AE9="","",IF(AF9="",TODAY()-AE9,AF9-AE9)) -> 21 | AH9: =HYPERLINK("https://www.ebay.com/sch/i.html?_nkw="&SUBSTITUTE(SUBSTITUTE(A9," ","+"),"""","")&"&LH_Sold=1&LH_Complete=1","View Sold Comps") -> View Sold Comps | AI9: =IF(OR(N9=0,W9=0),"",X9/N9) | AJ9: =IF(U9=0,"",(U9-U9*P9-Q9-R9-N9)/U9) -> 0.4803964 | AL9: =IF(B9="Kept for Self","—",IF(Z9="Baseball","Apr – Oct (MLB Season)",IF(Z9="Football","Aug – Feb (NFL Season)",IF(Z9="Basketball","Oct – Jun (NBA Season)",IF(OR(Z9="Movie",Z9="TV"),IF(ISNUMBER(SEARCH("Friday the 13th",A9)),"Sep – Oct (Halloween)","Year-Round"),IF(Z9="Music","Year-Round","Year-Round")))))) -> Aug – Feb (NFL Season)
A10: Moisés Ballesteros Signed OML Baseball (Beckett) | B10: Listed | C10: 4824728 | D10: 24.57 | E10: =D10 -> 24.57 | F10: =SUMIF(C:C, C10, E:E) -> 384.34 | G10: =E10/F10 -> 0.063927772 | H10: 31 | I10: =H10*G10 -> 1.9817609 | J10: 99 | K10: =J10*G10 -> 6.3288495 | L10: 38.67 | M10: =L10*G10 -> 2.472087 | N10: =E10-I10+K10+M10 -> 31.389175 | O10: eBay | P10: =IFERROR(VLOOKUP(O10,PlatformFees,2,FALSE()),0) -> 0.136 | Q10: =IFERROR(VLOOKUP(O10,PlatformFees,3,FALSE()),0) -> 0.4 | R10: 6.5 | S10: 0 | T10: =(N10+R10+Q10)/(1-(P10+S10)) -> 44.316175 | U10: =MAX(MAX(T10*1.5, T10+15), IFERROR(VLOOKUP(A10,'Pricing Intelligence'!A:J,10,FALSE),0)) -> 66.474263 | V10: 65.99 | W10: =IFERROR(_xlfn.XLOOKUP(A10,'Sales Log'!$C$4:$C$303,'Sales Log'!$F$4:$F$303,0),0) -> 0 | X10: =IF(W10=0,0,W10-(W10*(P10+S10))-Q10-R10-N10) -> 0 | Y10: =IFERROR(IF(ISNUMBER(SEARCH("Jersey",A10)),"Jersey",IF(ISNUMBER(SEARCH("Photo",A10)),"Photo",IF(ISNUMBER(SEARCH("Baseball Bat",A10)),"Bat",IF(ISNUMBER(SEARCH("Bat",A10)),"Bat",IF(ISNUMBER(SEARCH("Baseball",A10)),"Baseball",IF(ISNUMBER(SEARCH("Football",A10)),"Football",IF(ISNUMBER(SEARCH("Mask",A10)),"Mask",IF(ISNUMBER(SEARCH("Drum",A10)),"Drum Stick",IF(ISNUMBER(SEARCH("Card",A10)),"Card",IF(ISNUMBER(SEARCH("RC",A10)),"Card","Other")))))))))),"Other") -> Baseball | Z10: Baseball | AA10: =IFERROR(TRIM(LEFT(A10,FIND(" Signed",A10)-1)),LEFT(A10,20)) -> Moisés Ballesteros | AB10: =IF(ISNUMBER(SEARCH("(Beckett)",A10)),"Beckett",IF(ISNUMBER(SEARCH("(JSA)",A10)),"JSA",IF(ISNUMBER(SEARCH("(PSA)",A10)),"PSA",IF(ISNUMBER(SEARCH("(ACOA)",A10)),"ACOA",IF(ISNUMBER(SEARCH("(Schwartz)",A10)),"Schwartz","Unlabeled"))))) -> Beckett | AD10: 46204 | AE10: 46226 | AG10: =IF(AE10="","",IF(AF10="",TODAY()-AE10,AF10-AE10)) -> 6 | AH10: =HYPERLINK("https://www.ebay.com/sch/i.html?_nkw="&SUBSTITUTE(SUBSTITUTE(A10," ","+"),"""","")&"&LH_Sold=1&LH_Complete=1","View Sold Comps") -> View Sold Comps | AI10: =IF(OR(N10=0,W10=0),"",X10/N10) | AJ10: =IF(U10=0,"",(U10-U10*P10-Q10-R10-N10)/U10) -> 0.288 | AL10: =IF(B10="Kept for Self","—",IF(Z10="Baseball","Apr – Oct (MLB Season)",IF(Z10="Football","Aug – Feb (NFL Season)",IF(Z10="Basketball","Oct – Jun (NBA Season)",IF(OR(Z10="Movie",Z10="TV"),IF(ISNUMBER(SEARCH("Friday the 13th",A10)),"Sep – Oct (Halloween)","Year-Round"),IF(Z10="Music","Year-Round","Year-Round")))))) -> Apr – Oct (MLB Season)
A11: Moisés Ballesteros Signed Jersey Inscribed "Mo Baller" (Beckett) | B11: Listed | C11: 4824728 | D11: 24.57 | E11: =D11 -> 24.57 | F11: =SUMIF(C:C, C11, E:E) -> 384.34 | G11: =E11/F11 -> 0.063927772 | H11: 31 | I11: =H11*G11 -> 1.9817609 | J11: 99 | K11: =J11*G11 -> 6.3288495 | L11: 38.67 | M11: =L11*G11 -> 2.472087 | N11: =E11-I11+K11+M11 -> 31.389175 | O11: eBay | P11: =IFERROR(VLOOKUP(O11,PlatformFees,2,FALSE()),0) -> 0.136 | Q11: =IFERROR(VLOOKUP(O11,PlatformFees,3,FALSE()),0) -> 0.4 | R11: 6.5 | S11: 0 | T11: =(N11+R11+Q11)/(1-(P11+S11)) -> 44.316175 | U11: =MAX(MAX(T11*1.5, T11+15), IFERROR(VLOOKUP(A11,'Pricing Intelligence'!A:J,10,FALSE),0)) -> 99.5 | V11: 125 | W11: =IFERROR(_xlfn.XLOOKUP(A11,'Sales Log'!$C$4:$C$303,'Sales Log'!$F$4:$F$303,0),0) -> 0 | X11: =IF(W11=0,0,W11-(W11*(P11+S11))-Q11-R11-N11) -> 0 | Y11: =IFERROR(IF(ISNUMBER(SEARCH("Jersey",A11)),"Jersey",IF(ISNUMBER(SEARCH("Photo",A11)),"Photo",IF(ISNUMBER(SEARCH("Baseball Bat",A11)),"Bat",IF(ISNUMBER(SEARCH("Bat",A11)),"Bat",IF(ISNUMBER(SEARCH("Baseball",A11)),"Baseball",IF(ISNUMBER(SEARCH("Football",A11)),"Football",IF(ISNUMBER(SEARCH("Mask",A11)),"Mask",IF(ISNUMBER(SEARCH("Drum",A11)),"Drum Stick",IF(ISNUMBER(SEARCH("Card",A11)),"Card",IF(ISNUMBER(SEARCH("RC",A11)),"Card","Other")))))))))),"Other") -> Jersey | Z11: Baseball | AA11: =IFERROR(TRIM(LEFT(A11,FIND(" Signed",A11)-1)),LEFT(A11,20)) -> Moisés Ballesteros | AB11: =IF(ISNUMBER(SEARCH("(Beckett)",A11)),"Beckett",IF(ISNUMBER(SEARCH("(JSA)",A11)),"JSA",IF(ISNUMBER(SEARCH("(PSA)",A11)),"PSA",IF(ISNUMBER(SEARCH("(ACOA)",A11)),"ACOA",IF(ISNUMBER(SEARCH("(Schwartz)",A11)),"Schwartz","Unlabeled"))))) -> Beckett | AD11: 46204 | AE11: 46226 | AG11: =IF(AE11="","",IF(AF11="",TODAY()-AE11,AF11-AE11)) -> 6 | AH11: =HYPERLINK("https://www.ebay.com/sch/i.html?_nkw="&SUBSTITUTE(SUBSTITUTE(A11," ","+"),"""","")&"&LH_Sold=1&LH_Complete=1","View Sold Comps") -> View Sold Comps | AI11: =IF(OR(N11=0,W11=0),"",X11/N11) | AJ11: =IF(U11=0,"",(U11-U11*P11-Q11-R11-N11)/U11) -> 0.47918417 | AL11: =IF(B11="Kept for Self","—",IF(Z11="Baseball","Apr – Oct (MLB Season)",IF(Z11="Football","Aug – Feb (NFL Season)",IF(Z11="Basketball","Oct – Jun (NBA Season)",IF(OR(Z11="Movie",Z11="TV"),IF(ISNUMBER(SEARCH("Friday the 13th",A11)),"Sep – Oct (Halloween)","Year-Round"),IF(Z11="Music","Year-Round","Year-Round")))))) -> Apr – Oct (MLB Season)
A12: Moisés Ballesteros Signed Louisville Slugger Baseball Bat (Beckett) | B12: Available | C12: 4824728 | D12: 24.57 | E12: =D12 -> 24.57 | F12: =SUMIF(C:C, C12, E:E) -> 384.34 | G12: =E12/F12 -> 0.063927772 | H12: 31 | I12: =H12*G12 -> 1.9817609 | J12: 99 | K12: =J12*G12 -> 6.3288495 | L12: 38.67 | M12: =L12*G12 -> 2.472087 | N12: =E12-I12+K12+M12 -> 31.389175 | O12: eBay | P12: =IFERROR(VLOOKUP(O12,PlatformFees,2,FALSE()),0) -> 0.136 | Q12: =IFERROR(VLOOKUP(O12,PlatformFees,3,FALSE()),0) -> 0.4 | R12: 6.5 | S12: 0 | T12: =(N12+R12+Q12)/(1-(P12+S12)) -> 44.316175 | U12: =MAX(MAX(T12*1.5, T12+15), IFERROR(VLOOKUP(A12,'Pricing Intelligence'!A:J,10,FALSE),0)) -> 122.99333 | V12: 0 | W12: =IFERROR(_xlfn.XLOOKUP(A12,'Sales Log'!$C$4:$C$303,'Sales Log'!$F$4:$F$303,0),0) -> 0 | X12: =IF(W12=0,0,W12-(W12*(P12+S12))-Q12-R12-N12) -> 0 | Y12: =IFERROR(IF(ISNUMBER(SEARCH("Jersey",A12)),"Jersey",IF(ISNUMBER(SEARCH("Photo",A12)),"Photo",IF(ISNUMBER(SEARCH("Baseball Bat",A12)),"Bat",IF(ISNUMBER(SEARCH("Bat",A12)),"Bat",IF(ISNUMBER(SEARCH("Baseball",A12)),"Baseball",IF(ISNUMBER(SEARCH("Football",A12)),"Football",IF(ISNUMBER(SEARCH("Mask",A12)),"Mask",IF(ISNUMBER(SEARCH("Drum",A12)),"Drum Stick",IF(ISNUMBER(SEARCH("Card",A12)),"Card",IF(ISNUMBER(SEARCH("RC",A12)),"Card","Other")))))))))),"Other") -> Bat | Z12: Baseball | AA12: =IFERROR(TRIM(LEFT(A12,FIND(" Signed",A12)-1)),LEFT(A12,20)) -> Moisés Ballesteros | AB12: =IF(ISNUMBER(SEARCH("(Beckett)",A12)),"Beckett",IF(ISNUMBER(SEARCH("(JSA)",A12)),"JSA",IF(ISNUMBER(SEARCH("(PSA)",A12)),"PSA",IF(ISNUMBER(SEARCH("(ACOA)",A12)),"ACOA",IF(ISNUMBER(SEARCH("(Schwartz)",A12)),"Schwartz","Unlabeled"))))) -> Beckett | AD12: 46204 | AG12: =IF(AE12="","",IF(AF12="",TODAY()-AE12,AF12-AE12)) | AH12: =HYPERLINK("https://www.ebay.com/sch/i.html?_nkw="&SUBSTITUTE(SUBSTITUTE(A12," ","+"),"""","")&"&LH_Sold=1&LH_Complete=1","View Sold Comps") -> View Sold Comps | AI12: =IF(OR(N12=0,W12=0),"",X12/N12) | AJ12: =IF(U12=0,"",(U12-U12*P12-Q12-R12-N12)/U12) -> 0.55268902 | AL12: =IF(B12="Kept for Self","—",IF(Z12="Baseball","Apr – Oct (MLB Season)",IF(Z12="Football","Aug – Feb (NFL Season)",IF(Z12="Basketball","Oct – Jun (NBA Season)",IF(OR(Z12="Movie",Z12="TV"),IF(ISNUMBER(SEARCH("Friday the 13th",A12)),"Sep – Oct (Halloween)","Year-Round"),IF(Z12="Music","Year-Round","Year-Round")))))) -> Apr – Oct (MLB Season)
A13: Moisés Ballesteros Signed Jersey (Beckett) | B13: Listed | C13: 4824728 | D13: 24.57 | E13: =D13 -> 24.57 | F13: =SUMIF(C:C, C13, E:E) -> 384.34 | G13: =E13/F13 -> 0.063927772 | H13: 31 | I13: =H13*G13 -> 1.9817609 | J13: 99 | K13: =J13*G13 -> 6.3288495 | L13: 38.67 | M13: =L13*G13 -> 2.472087 | N13: =E13-I13+K13+M13 -> 31.389175 | O13: eBay | P13: =IFERROR(VLOOKUP(O13,PlatformFees,2,FALSE()),0) -> 0.136 | Q13: =IFERROR(VLOOKUP(O13,PlatformFees,3,FALSE()),0) -> 0.4 | R13: 6.5 | S13: 0 | T13: =(N13+R13+Q13)/(1-(P13+S13)) -> 44.316175 | U13: =MAX(MAX(T13*1.5, T13+15), IFERROR(VLOOKUP(A13,'Pricing Intelligence'!A:J,10,FALSE),0)) -> 99.5 | V13: 109.99 | W13: =IFERROR(_xlfn.XLOOKUP(A13,'Sales Log'!$C$4:$C$303,'Sales Log'!$F$4:$F$303,0),0) -> 0 | X13: =IF(W13=0,0,W13-(W13*(P13+S13))-Q13-R13-N13) -> 0 | Y13: =IFERROR(IF(ISNUMBER(SEARCH("Jersey",A13)),"Jersey",IF(ISNUMBER(SEARCH("Photo",A13)),"Photo",IF(ISNUMBER(SEARCH("Baseball Bat",A13)),"Bat",IF(ISNUMBER(SEARCH("Bat",A13)),"Bat",IF(ISNUMBER(SEARCH("Baseball",A13)),"Baseball",IF(ISNUMBER(SEARCH("Football",A13)),"Football",IF(ISNUMBER(SEARCH("Mask",A13)),"Mask",IF(ISNUMBER(SEARCH("Drum",A13)),"Drum Stick",IF(ISNUMBER(SEARCH("Card",A13)),"Card",IF(ISNUMBER(SEARCH("RC",A13)),"Card","Other")))))))))),"Other") -> Jersey | Z13: Baseball | AA13: =IFERROR(TRIM(LEFT(A13,FIND(" Signed",A13)-1)),LEFT(A13,20)) -> Moisés Ballesteros | AB13: =IF(ISNUMBER(SEARCH("(Beckett)",A13)),"Beckett",IF(ISNUMBER(SEARCH("(JSA)",A13)),"JSA",IF(ISNUMBER(SEARCH("(PSA)",A13)),"PSA",IF(ISNUMBER(SEARCH("(ACOA)",A13)),"ACOA",IF(ISNUMBER(SEARCH("(Schwartz)",A13)),"Schwartz","Unlabeled"))))) -> Beckett | AD13: 46204 | AE13: 46226 | AG13: =IF(AE13="","",IF(AF13="",TODAY()-AE13,AF13-AE13)) -> 6 | AH13: =HYPERLINK("https://www.ebay.com/sch/i.html?_nkw="&SUBSTITUTE(SUBSTITUTE(A13," ","+"),"""","")&"&LH_Sold=1&LH_Complete=1","View Sold Comps") -> View Sold Comps | AI13: =IF(OR(N13=0,W13=0),"",X13/N13) | AJ13: =IF(U13=0,"",(U13-U13*P13-Q13-R13-N13)/U13) -> 0.47918417 | AL13: =IF(B13="Kept for Self","—",IF(Z13="Baseball","Apr – Oct (MLB Season)",IF(Z13="Football","Aug – Feb (NFL Season)",IF(Z13="Basketball","Oct – Jun (NBA Season)",IF(OR(Z13="Movie",Z13="TV"),IF(ISNUMBER(SEARCH("Friday the 13th",A13)),"Sep – Oct (Halloween)","Year-Round"),IF(Z13="Music","Year-Round","Year-Round")))))) -> Apr – Oct (MLB Season)
A14: Sammy Sosa Signed Louisville Slugger Baseball Bat (Beckett) | B14: Available | C14: 4824728 | D14: 30.72 | E14: =D14 -> 30.72 | F14: =SUMIF(C:C, C14, E:E) -> 384.34 | G14: =E14/F14 -> 0.079929229 | H14: 31 | I14: =H14*G14 -> 2.4778061 | J14: 99 | K14: =J14*G14 -> 7.9129937 | L14: 38.67 | M14: =L14*G14 -> 3.0908633 | N14: =E14-I14+K14+M14 -> 39.246051 | O14: eBay | P14: =IFERROR(VLOOKUP(O14,PlatformFees,2,FALSE()),0) -> 0.136 | Q14: =IFERROR(VLOOKUP(O14,PlatformFees,3,FALSE()),0) -> 0.4 | R14: 6.5 | S14: 0 | T14: =(N14+R14+Q14)/(1-(P14+S14)) -> 53.409781 | U14: =MAX(MAX(T14*1.5, T14+15), IFERROR(VLOOKUP(A14,'Pricing Intelligence'!A:J,10,FALSE),0)) -> 106.66667 | V14: 0 | W14: =IFERROR(_xlfn.XLOOKUP(A14,'Sales Log'!$C$4:$C$303,'Sales Log'!$F$4:$F$303,0),0) -> 0 | X14: =IF(W14=0,0,W14-(W14*(P14+S14))-Q14-R14-N14) -> 0 | Y14: =IFERROR(IF(ISNUMBER(SEARCH("Jersey",A14)),"Jersey",IF(ISNUMBER(SEARCH("Photo",A14)),"Photo",IF(ISNUMBER(SEARCH("Baseball Bat",A14)),"Bat",IF(ISNUMBER(SEARCH("Bat",A14)),"Bat",IF(ISNUMBER(SEARCH("Baseball",A14)),"Baseball",IF(ISNUMBER(SEARCH("Football",A14)),"Football",IF(ISNUMBER(SEARCH("Mask",A14)),"Mask",IF(ISNUMBER(SEARCH("Drum",A14)),"Drum Stick",IF(ISNUMBER(SEARCH("Card",A14)),"Card",IF(ISNUMBER(SEARCH("RC",A14)),"Card","Other")))))))))),"Other") -> Bat | Z14: Baseball | AA14: =IFERROR(TRIM(LEFT(A14,FIND(" Signed",A14)-1)),LEFT(A14,20)) -> Sammy Sosa | AB14: =IF(ISNUMBER(SEARCH("(Beckett)",A14)),"Beckett",IF(ISNUMBER(SEARCH("(JSA)",A14)),"JSA",IF(ISNUMBER(SEARCH("(PSA)",A14)),"PSA",IF(ISNUMBER(SEARCH("(ACOA)",A14)),"ACOA",IF(ISNUMBER(SEARCH("(Schwartz)",A14)),"Schwartz","Unlabeled"))))) -> Beckett | AD14: 46204 | AG14: =IF(AE14="","",IF(AF14="",TODAY()-AE14,AF14-AE14)) | AH14: =HYPERLINK("https://www.ebay.com/sch/i.html?_nkw="&SUBSTITUTE(SUBSTITUTE(A14," ","+"),"""","")&"&LH_Sold=1&LH_Complete=1","View Sold Comps") -> View Sold Comps | AI14: =IF(OR(N14=0,W14=0),"",X14/N14) | AJ14: =IF(U14=0,"",(U14-U14*P14-Q14-R14-N14)/U14) -> 0.43138077 | AL14: =IF(B14="Kept for Self","—",IF(Z14="Baseball","Apr – Oct (MLB Season)",IF(Z14="Football","Aug – Feb (NFL Season)",IF(Z14="Basketball","Oct – Jun (NBA Season)",IF(OR(Z14="Movie",Z14="TV"),IF(ISNUMBER(SEARCH("Friday the 13th",A14)),"Sep – Oct (Halloween)","Year-Round"),IF(Z14="Music","Year-Round","Year-Round")))))) -> Apr – Oct (MLB Season)
A15: Sammy Sosa Signed Louisville Slugger Baseball Bat (JSA) | B15: Available | C15: 4824728 | D15: 30.72 | E15: =D15 -> 30.72 | F15: =SUMIF(C:C, C15, E:E) -> 384.34 | G15: =E15/F15 -> 0.079929229 | H15: 31 | I15: =H15*G15 -> 2.4778061 | J15: 99 | K15: =J15*G15 -> 7.9129937 | L15: 38.67 | M15: =L15*G15 -> 3.0908633 | N15: =E15-I15+K15+M15 -> 39.246051 | O15: eBay | P15: =IFERROR(VLOOKUP(O15,PlatformFees,2,FALSE()),0) -> 0.136 | Q15: =IFERROR(VLOOKUP(O15,PlatformFees,3,FALSE()),0) -> 0.4 | R15: 6.5 | S15: 0 | T15: =(N15+R15+Q15)/(1-(P15+S15)) -> 53.409781 | U15: =MAX(MAX(T15*1.5, T15+15), IFERROR(VLOOKUP(A15,'Pricing Intelligence'!A:J,10,FALSE),0)) -> 108 | V15: 0 | W15: =IFERROR(_xlfn.XLOOKUP(A15,'Sales Log'!$C$4:$C$303,'Sales Log'!$F$4:$F$303,0),0) -> 0 | X15: =IF(W15=0,0,W15-(W15*(P15+S15))-Q15-R15-N15) -> 0 | Y15: =IFERROR(IF(ISNUMBER(SEARCH("Jersey",A15)),"Jersey",IF(ISNUMBER(SEARCH("Photo",A15)),"Photo",IF(ISNUMBER(SEARCH("Baseball Bat",A15)),"Bat",IF(ISNUMBER(SEARCH("Bat",A15)),"Bat",IF(ISNUMBER(SEARCH("Baseball",A15)),"Baseball",IF(ISNUMBER(SEARCH("Football",A15)),"Football",IF(ISNUMBER(SEARCH("Mask",A15)),"Mask",IF(ISNUMBER(SEARCH("Drum",A15)),"Drum Stick",IF(ISNUMBER(SEARCH("Card",A15)),"Card",IF(ISNUMBER(SEARCH("RC",A15)),"Card","Other")))))))))),"Other") -> Bat | Z15: Baseball | AA15: =IFERROR(TRIM(LEFT(A15,FIND(" Signed",A15)-1)),LEFT(A15,20)) -> Sammy Sosa | AB15: =IF(ISNUMBER(SEARCH("(Beckett)",A15)),"Beckett",IF(ISNUMBER(SEARCH("(JSA)",A15)),"JSA",IF(ISNUMBER(SEARCH("(PSA)",A15)),"PSA",IF(ISNUMBER(SEARCH("(ACOA)",A15)),"ACOA",IF(ISNUMBER(SEARCH("(Schwartz)",A15)),"Schwartz","Unlabeled"))))) -> JSA | AD15: 46204 | AG15: =IF(AE15="","",IF(AF15="",TODAY()-AE15,AF15-AE15)) | AH15: =HYPERLINK("https://www.ebay.com/sch/i.html?_nkw="&SUBSTITUTE(SUBSTITUTE(A15," ","+"),"""","")&"&LH_Sold=1&LH_Complete=1","View Sold Comps") -> View Sold Comps | AI15: =IF(OR(N15=0,W15=0),"",X15/N15) | AJ15: =IF(U15=0,"",(U15-U15*P15-Q15-R15-N15)/U15) -> 0.43672175 | AL15: =IF(B15="Kept for Self","—",IF(Z15="Baseball","Apr – Oct (MLB Season)",IF(Z15="Football","Aug – Feb (NFL Season)",IF(Z15="Basketball","Oct – Jun (NBA Season)",IF(OR(Z15="Movie",Z15="TV"),IF(ISNUMBER(SEARCH("Friday the 13th",A15)),"Sep – Oct (Halloween)","Year-Round"),IF(Z15="Music","Year-Round","Year-Round")))))) -> Apr – Oct (MLB Season)
A16: Sammy Sosa Signed Jersey (JSA) | B16: Listed | C16: 4824728 | D16: 26.48 | E16: =D16 -> 26.48 | F16: =SUMIF(C:C, C16, E:E) -> 384.34 | G16: =E16/F16 -> 0.06889733 | H16: 31 | I16: =H16*G16 -> 2.1358172 | J16: 99 | K16: =J16*G16 -> 6.8208357 | L16: 38.67 | M16: =L16*G16 -> 2.6642598 | N16: =E16-I16+K16+M16 -> 33.829278 | O16: eBay | P16: =IFERROR(VLOOKUP(O16,PlatformFees,2,FALSE()),0) -> 0.136 | Q16: =IFERROR(VLOOKUP(O16,PlatformFees,3,FALSE()),0) -> 0.4 | R16: 6.5 | S16: 0 | T16: =(N16+R16+Q16)/(1-(P16+S16)) -> 47.140368 | U16: =MAX(MAX(T16*1.5, T16+15), IFERROR(VLOOKUP(A16,'Pricing Intelligence'!A:J,10,FALSE),0)) -> 70.710553 | V16: 63 | W16: =IFERROR(_xlfn.XLOOKUP(A16,'Sales Log'!$C$4:$C$303,'Sales Log'!$F$4:$F$303,0),0) -> 0 | X16: =IF(W16=0,0,W16-(W16*(P16+S16))-Q16-R16-N16) -> 0 | Y16: =IFERROR(IF(ISNUMBER(SEARCH("Jersey",A16)),"Jersey",IF(ISNUMBER(SEARCH("Photo",A16)),"Photo",IF(ISNUMBER(SEARCH("Baseball Bat",A16)),"Bat",IF(ISNUMBER(SEARCH("Bat",A16)),"Bat",IF(ISNUMBER(SEARCH("Baseball",A16)),"Baseball",IF(ISNUMBER(SEARCH("Football",A16)),"Football",IF(ISNUMBER(SEARCH("Mask",A16)),"Mask",IF(ISNUMBER(SEARCH("Drum",A16)),"Drum Stick",IF(ISNUMBER(SEARCH("Card",A16)),"Card",IF(ISNUMBER(SEARCH("RC",A16)),"Card","Other")))))))))),"Other") -> Jersey | Z16: Baseball | AA16: =IFERROR(TRIM(LEFT(A16,FIND(" Signed",A16)-1)),LEFT(A16,20)) -> Sammy Sosa | AB16: =IF(ISNUMBER(SEARCH("(Beckett)",A16)),"Beckett",IF(ISNUMBER(SEARCH("(JSA)",A16)),"JSA",IF(ISNUMBER(SEARCH("(PSA)",A16)),"PSA",IF(ISNUMBER(SEARCH("(ACOA)",A16)),"ACOA",IF(ISNUMBER(SEARCH("(Schwartz)",A16)),"Schwartz","Unlabeled"))))) -> JSA | AD16: 46204 | AE16: 46226 | AG16: =IF(AE16="","",IF(AF16="",TODAY()-AE16,AF16-AE16)) -> 6 | AH16: =HYPERLINK("https://www.ebay.com/sch/i.html?_nkw="&SUBSTITUTE(SUBSTITUTE(A16," ","+"),"""","")&"&LH_Sold=1&LH_Complete=1","View Sold Comps") -> View Sold Comps | AI16: =IF(OR(N16=0,W16=0),"",X16/N16) | AJ16: =IF(U16=0,"",(U16-U16*P16-Q16-R16-N16)/U16) -> 0.288 | AL16: =IF(B16="Kept for Self","—",IF(Z16="Baseball","Apr – Oct (MLB Season)",IF(Z16="Football","Aug – Feb (NFL Season)",IF(Z16="Basketball","Oct – Jun (NBA Season)",IF(OR(Z16="Movie",Z16="TV"),IF(ISNUMBER(SEARCH("Friday the 13th",A16)),"Sep – Oct (Halloween)","Year-Round"),IF(Z16="Music","Year-Round","Year-Round")))))) -> Apr – Oct (MLB Season)
A17: Sammy Sosa Signed Jersey (JSA) | B17: Listed | C17: 4824728 | D17: 34.21 | E17: =D17 -> 34.21 | F17: =SUMIF(C:C, C17, E:E) -> 384.34 | G17: =E17/F17 -> 0.089009731 | H17: 31 | I17: =H17*G17 -> 2.7593017 | J17: 99 | K17: =J17*G17 -> 8.8119634 | L17: 38.67 | M17: =L17*G17 -> 3.4420063 | N17: =E17-I17+K17+M17 -> 43.704668 | O17: eBay | P17: =IFERROR(VLOOKUP(O17,PlatformFees,2,FALSE()),0) -> 0.136 | Q17: =IFERROR(VLOOKUP(O17,PlatformFees,3,FALSE()),0) -> 0.4 | R17: 6.5 | S17: 0 | T17: =(N17+R17+Q17)/(1-(P17+S17)) -> 58.570218 | U17: =MAX(MAX(T17*1.5, T17+15), IFERROR(VLOOKUP(A17,'Pricing Intelligence'!A:J,10,FALSE),0)) -> 87.855326 | V17: 63 | W17: =IFERROR(_xlfn.XLOOKUP(A17,'Sales Log'!$C$4:$C$303,'Sales Log'!$F$4:$F$303,0),0) -> 0 | X17: =IF(W17=0,0,W17-(W17*(P17+S17))-Q17-R17-N17) -> 0 | Y17: =IFERROR(IF(ISNUMBER(SEARCH("Jersey",A17)),"Jersey",IF(ISNUMBER(SEARCH("Photo",A17)),"Photo",IF(ISNUMBER(SEARCH("Baseball Bat",A17)),"Bat",IF(ISNUMBER(SEARCH("Bat",A17)),"Bat",IF(ISNUMBER(SEARCH("Baseball",A17)),"Baseball",IF(ISNUMBER(SEARCH("Football",A17)),"Football",IF(ISNUMBER(SEARCH("Mask",A17)),"Mask",IF(ISNUMBER(SEARCH("Drum",A17)),"Drum Stick",IF(ISNUMBER(SEARCH("Card",A17)),"Card",IF(ISNUMBER(SEARCH("RC",A17)),"Card","Other")))))))))),"Other") -> Jersey | Z17: Baseball | AA17: =IFERROR(TRIM(LEFT(A17,FIND(" Signed",A17)-1)),LEFT(A17,20)) -> Sammy Sosa | AB17: =IF(ISNUMBER(SEARCH("(Beckett)",A17)),"Beckett",IF(ISNUMBER(SEARCH("(JSA)",A17)),"JSA",IF(ISNUMBER(SEARCH("(PSA)",A17)),"PSA",IF(ISNUMBER(SEARCH("(ACOA)",A17)),"ACOA",IF(ISNUMBER(SEARCH("(Schwartz)",A17)),"Schwartz","Unlabeled"))))) -> JSA | AD17: 46204 | AE17: 46226 | AG17: =IF(AE17="","",IF(AF17="",TODAY()-AE17,AF17-AE17)) -> 6 | AH17: =HYPERLINK("https://www.ebay.com/sch/i.html?_nkw="&SUBSTITUTE(SUBSTITUTE(A17," ","+"),"""","")&"&LH_Sold=1&LH_Complete=1","View Sold Comps") -> View Sold Comps | AI17: =IF(OR(N17=0,W17=0),"",X17/N17) | AJ17: =IF(U17=0,"",(U17-U17*P17-Q17-R17-N17)/U17) -> 0.288 | AL17: =IF(B17="Kept for Self","—",IF(Z17="Baseball","Apr – Oct (MLB Season)",IF(Z17="Football","Aug – Feb (NFL Season)",IF(Z17="Basketball","Oct – Jun (NBA Season)",IF(OR(Z17="Movie",Z17="TV"),IF(ISNUMBER(SEARCH("Friday the 13th",A17)),"Sep – Oct (Halloween)","Year-Round"),IF(Z17="Music","Year-Round","Year-Round")))))) -> Apr – Oct (MLB Season)
A18: Sammy Sosa Signed Louisville Slugger Baseball Bat (Beckett) | B18: Available | C18: 4824728 | D18: 34.25 | E18: =D18 -> 34.25 | F18: =SUMIF(C:C, C18, E:E) -> 384.34 | G18: =E18/F18 -> 0.089113805 | H18: 31 | I18: =H18*G18 -> 2.762528 | J18: 99 | K18: =J18*G18 -> 8.8222667 | L18: 38.67 | M18: =L18*G18 -> 3.4460309 | N18: =E18-I18+K18+M18 -> 43.75577 | O18: eBay | P18: =IFERROR(VLOOKUP(O18,PlatformFees,2,FALSE()),0) -> 0.136 | Q18: =IFERROR(VLOOKUP(O18,PlatformFees,3,FALSE()),0) -> 0.4 | R18: 6.5 | S18: 0 | T18: =(N18+R18+Q18)/(1-(P18+S18)) -> 58.629363 | U18: =MAX(MAX(T18*1.5, T18+15), IFERROR(VLOOKUP(A18,'Pricing Intelligence'!A:J,10,FALSE),0)) -> 106.66667 | V18: 0 | W18: =IFERROR(_xlfn.XLOOKUP(A18,'Sales Log'!$C$4:$C$303,'Sales Log'!$F$4:$F$303,0),0) -> 0 | X18: =IF(W18=0,0,W18-(W18*(P18+S18))-Q18-R18-N18) -> 0 | Y18: =IFERROR(IF(ISNUMBER(SEARCH("Jersey",A18)),"Jersey",IF(ISNUMBER(SEARCH("Photo",A18)),"Photo",IF(ISNUMBER(SEARCH("Baseball Bat",A18)),"Bat",IF(ISNUMBER(SEARCH("Bat",A18)),"Bat",IF(ISNUMBER(SEARCH("Baseball",A18)),"Baseball",IF(ISNUMBER(SEARCH("Football",A18)),"Football",IF(ISNUMBER(SEARCH("Mask",A18)),"Mask",IF(ISNUMBER(SEARCH("Drum",A18)),"Drum Stick",IF(ISNUMBER(SEARCH("Card",A18)),"Card",IF(ISNUMBER(SEARCH("RC",A18)),"Card","Other")))))))))),"Other") -> Bat | Z18: Baseball | AA18: =IFERROR(TRIM(LEFT(A18,FIND(" Signed",A18)-1)),LEFT(A18,20)) -> Sammy Sosa | AB18: =IF(ISNUMBER(SEARCH("(Beckett)",A18)),"Beckett",IF(ISNUMBER(SEARCH("(JSA)",A18)),"JSA",IF(ISNUMBER(SEARCH("(PSA)",A18)),"PSA",IF(ISNUMBER(SEARCH("(ACOA)",A18)),"ACOA",IF(ISNUMBER(SEARCH("(Schwartz)",A18)),"Schwartz","Unlabeled"))))) -> Beckett | AD18: 46204 | AG18: =IF(AE18="","",IF(AF18="",TODAY()-AE18,AF18-AE18)) | AH18: =HYPERLINK("https://www.ebay.com/sch/i.html?_nkw="&SUBSTITUTE(SUBSTITUTE(A18," ","+"),"""","")&"&LH_Sold=1&LH_Complete=1","View Sold Comps") -> View Sold Comps | AI18: =IF(OR(N18=0,W18=0),"",X18/N18) | AJ18: =IF(U18=0,"",(U18-U18*P18-Q18-R18-N18)/U18) -> 0.38910216 | AL18: =IF(B18="Kept for Self","—",IF(Z18="Baseball","Apr – Oct (MLB Season)",IF(Z18="Football","Aug – Feb (NFL Season)",IF(Z18="Basketball","Oct – Jun (NBA Season)",IF(OR(Z18="Movie",Z18="TV"),IF(ISNUMBER(SEARCH("Friday the 13th",A18)),"Sep – Oct (Halloween)","Year-Round"),IF(Z18="Music","Year-Round","Year-Round")))))) -> Apr – Oct (MLB Season)
A19: Donte DiVincenzo Signed Jersey (Beckett) | B19: Available | C19: 4824728 | D19: 18.43 | E19: =D19 -> 18.43 | F19: =SUMIF(C:C, C19, E:E) -> 384.34 | G19: =E19/F19 -> 0.047952334 | H19: 31 | I19: =H19*G19 -> 1.4865224 | J19: 99 | K19: =J19*G19 -> 4.7472811 | L19: 38.67 | M19: =L19*G19 -> 1.8543168 | N19: =E19-I19+K19+M19 -> 23.545075 | O19: eBay | P19: =IFERROR(VLOOKUP(O19,PlatformFees,2,FALSE()),0) -> 0.136 | Q19: =IFERROR(VLOOKUP(O19,PlatformFees,3,FALSE()),0) -> 0.4 | R19: 6.5 | S19: 0 | T19: =(N19+R19+Q19)/(1-(P19+S19)) -> 35.237356 | U19: =MAX(MAX(T19*1.5, T19+15), IFERROR(VLOOKUP(A19,'Pricing Intelligence'!A:J,10,FALSE),0)) -> 52.856034 | V19: 0 | W19: =IFERROR(_xlfn.XLOOKUP(A19,'Sales Log'!$C$4:$C$303,'Sales Log'!$F$4:$F$303,0),0) -> 0 | X19: =IF(W19=0,0,W19-(W19*(P19+S19))-Q19-R19-N19) -> 0 | Y19: =IFERROR(IF(ISNUMBER(SEARCH("Jersey",A19)),"Jersey",IF(ISNUMBER(SEARCH("Photo",A19)),"Photo",IF(ISNUMBER(SEARCH("Baseball Bat",A19)),"Bat",IF(ISNUMBER(SEARCH("Bat",A19)),"Bat",IF(ISNUMBER(SEARCH("Baseball",A19)),"Baseball",IF(ISNUMBER(SEARCH("Football",A19)),"Football",IF(ISNUMBER(SEARCH("Mask",A19)),"Mask",IF(ISNUMBER(SEARCH("Drum",A19)),"Drum Stick",IF(ISNUMBER(SEARCH("Card",A19)),"Card",IF(ISNUMBER(SEARCH("RC",A19)),"Card","Other")))))))))),"Other") -> Jersey | Z19: Basketball | AA19: =IFERROR(TRIM(LEFT(A19,FIND(" Signed",A19)-1)),LEFT(A19,20)) -> Donte DiVincenzo | AB19: =IF(ISNUMBER(SEARCH("(Beckett)",A19)),"Beckett",IF(ISNUMBER(SEARCH("(JSA)",A19)),"JSA",IF(ISNUMBER(SEARCH("(PSA)",A19)),"PSA",IF(ISNUMBER(SEARCH("(ACOA)",A19)),"ACOA",IF(ISNUMBER(SEARCH("(Schwartz)",A19)),"Schwartz","Unlabeled"))))) -> Beckett | AD19: 46204 | AG19: =IF(AE19="","",IF(AF19="",TODAY()-AE19,AF19-AE19)) | AH19: =HYPERLINK("https://www.ebay.com/sch/i.html?_nkw="&SUBSTITUTE(SUBSTITUTE(A19," ","+"),"""","")&"&LH_Sold=1&LH_Complete=1","View Sold Comps") -> View Sold Comps | AI19: =IF(OR(N19=0,W19=0),"",X19/N19) | AJ19: =IF(U19=0,"",(U19-U19*P19-Q19-R19-N19)/U19) -> 0.288 | AL19: =IF(B19="Kept for Self","—",IF(Z19="Baseball","Apr – Oct (MLB Season)",IF(Z19="Football","Aug – Feb (NFL Season)",IF(Z19="Basketball","Oct – Jun (NBA Season)",IF(OR(Z19="Movie",Z19="TV"),IF(ISNUMBER(SEARCH("Friday the 13th",A19)),"Sep – Oct (Halloween)","Year-Round"),IF(Z19="Music","Year-Round","Year-Round")))))) -> Oct – Jun (NBA Season)
A20: Derek Harper Signed Jersey (JSA) | B20: Available | C20: 4824728 | D20: 24.57 | E20: =D20 -> 24.57 | F20: =SUMIF(C:C, C20, E:E) -> 384.34 | G20: =E20/F20 -> 0.063927772 | H20: 31 | I20: =H20*G20 -> 1.9817609 | J20: 99 | K20: =J20*G20 -> 6.3288495 | L20: 38.67 | M20: =L20*G20 -> 2.472087 | N20: =E20-I20+K20+M20 -> 31.389175 | O20: eBay | P20: =IFERROR(VLOOKUP(O20,PlatformFees,2,FALSE()),0) -> 0.136 | Q20: =IFERROR(VLOOKUP(O20,PlatformFees,3,FALSE()),0) -> 0.4 | R20: 6.5 | S20: 0 | T20: =(N20+R20+Q20)/(1-(P20+S20)) -> 44.316175 | U20: =MAX(MAX(T20*1.5, T20+15), IFERROR(VLOOKUP(A20,'Pricing Intelligence'!A:J,10,FALSE),0)) -> 66.474263 | V20: 0 | W20: =IFERROR(_xlfn.XLOOKUP(A20,'Sales Log'!$C$4:$C$303,'Sales Log'!$F$4:$F$303,0),0) -> 0 | X20: =IF(W20=0,0,W20-(W20*(P20+S20))-Q20-R20-N20) -> 0 | Y20: =IFERROR(IF(ISNUMBER(SEARCH("Jersey",A20)),"Jersey",IF(ISNUMBER(SEARCH("Photo",A20)),"Photo",IF(ISNUMBER(SEARCH("Baseball Bat",A20)),"Bat",IF(ISNUMBER(SEARCH("Bat",A20)),"Bat",IF(ISNUMBER(SEARCH("Baseball",A20)),"Baseball",IF(ISNUMBER(SEARCH("Football",A20)),"Football",IF(ISNUMBER(SEARCH("Mask",A20)),"Mask",IF(ISNUMBER(SEARCH("Drum",A20)),"Drum Stick",IF(ISNUMBER(SEARCH("Card",A20)),"Card",IF(ISNUMBER(SEARCH("RC",A20)),"Card","Other")))))))))),"Other") -> Jersey | Z20: Basketball | AA20: =IFERROR(TRIM(LEFT(A20,FIND(" Signed",A20)-1)),LEFT(A20,20)) -> Derek Harper | AB20: =IF(ISNUMBER(SEARCH("(Beckett)",A20)),"Beckett",IF(ISNUMBER(SEARCH("(JSA)",A20)),"JSA",IF(ISNUMBER(SEARCH("(PSA)",A20)),"PSA",IF(ISNUMBER(SEARCH("(ACOA)",A20)),"ACOA",IF(ISNUMBER(SEARCH("(Schwartz)",A20)),"Schwartz","Unlabeled"))))) -> JSA | AD20: 46204 | AG20: =IF(AE20="","",IF(AF20="",TODAY()-AE20,AF20-AE20)) | AH20: =HYPERLINK("https://www.ebay.com/sch/i.html?_nkw="&SUBSTITUTE(SUBSTITUTE(A20," ","+"),"""","")&"&LH_Sold=1&LH_Complete=1","View Sold Comps") -> View Sold Comps | AI20: =IF(OR(N20=0,W20=0),"",X20/N20) | AJ20: =IF(U20=0,"",(U20-U20*P20-Q20-R20-N20)/U20) -> 0.288 | AL20: =IF(B20="Kept for Self","—",IF(Z20="Baseball","Apr – Oct (MLB Season)",IF(Z20="Football","Aug – Feb (NFL Season)",IF(Z20="Basketball","Oct – Jun (NBA Season)",IF(OR(Z20="Movie",Z20="TV"),IF(ISNUMBER(SEARCH("Friday the 13th",A20)),"Sep – Oct (Halloween)","Year-Round"),IF(Z20="Music","Year-Round","Year-Round")))))) -> Oct – Jun (NBA Season)
A21: Jamal Anderson Signed Jersey (JSA) | B21: Available | C21: 4824728 | D21: 19.11 | E21: =D21 -> 19.11 | F21: =SUMIF(C:C, C21, E:E) -> 384.34 | G21: =E21/F21 -> 0.049721601 | H21: 31 | I21: =H21*G21 -> 1.5413696 | J21: 99 | K21: =J21*G21 -> 4.9224385 | L21: 38.67 | M21: =L21*G21 -> 1.9227343 | N21: =E21-I21+K21+M21 -> 24.413803 | O21: eBay | P21: =IFERROR(VLOOKUP(O21,PlatformFees,2,FALSE()),0) -> 0.136 | Q21: =IFERROR(VLOOKUP(O21,PlatformFees,3,FALSE()),0) -> 0.4 | R21: 6.5 | S21: 0 | T21: =(N21+R21+Q21)/(1-(P21+S21)) -> 36.242828 | U21: =MAX(MAX(T21*1.5, T21+15), IFERROR(VLOOKUP(A21,'Pricing Intelligence'!A:J,10,FALSE),0)) -> 54.364242 | V21: 0 | W21: =IFERROR(_xlfn.XLOOKUP(A21,'Sales Log'!$C$4:$C$303,'Sales Log'!$F$4:$F$303,0),0) -> 0 | X21: =IF(W21=0,0,W21-(W21*(P21+S21))-Q21-R21-N21) -> 0 | Y21: =IFERROR(IF(ISNUMBER(SEARCH("Jersey",A21)),"Jersey",IF(ISNUMBER(SEARCH("Photo",A21)),"Photo",IF(ISNUMBER(SEARCH("Baseball Bat",A21)),"Bat",IF(ISNUMBER(SEARCH("Bat",A21)),"Bat",IF(ISNUMBER(SEARCH("Baseball",A21)),"Baseball",IF(ISNUMBER(SEARCH("Football",A21)),"Football",IF(ISNUMBER(SEARCH("Mask",A21)),"Mask",IF(ISNUMBER(SEARCH("Drum",A21)),"Drum Stick",IF(ISNUMBER(SEARCH("Card",A21)),"Card",IF(ISNUMBER(SEARCH("RC",A21)),"Card","Other")))))))))),"Other") -> Jersey | Z21: Football | AA21: =IFERROR(TRIM(LEFT(A21,FIND(" Signed",A21)-1)),LEFT(A21,20)) -> Jamal Anderson | AB21: =IF(ISNUMBER(SEARCH("(Beckett)",A21)),"Beckett",IF(ISNUMBER(SEARCH("(JSA)",A21)),"JSA",IF(ISNUMBER(SEARCH("(PSA)",A21)),"PSA",IF(ISNUMBER(SEARCH("(ACOA)",A21)),"ACOA",IF(ISNUMBER(SEARCH("(Schwartz)",A21)),"Schwartz","Unlabeled"))))) -> JSA | AD21: 46204 | AG21: =IF(AE21="","",IF(AF21="",TODAY()-AE21,AF21-AE21)) | AH21: =HYPERLINK("https://www.ebay.com/sch/i.html?_nkw="&SUBSTITUTE(SUBSTITUTE(A21," ","+"),"""","")&"&LH_Sold=1&LH_Complete=1","View Sold Comps") -> View Sold Comps | AI21: =IF(OR(N21=0,W21=0),"",X21/N21) | AJ21: =IF(U21=0,"",(U21-U21*P21-Q21-R21-N21)/U21) -> 0.288 | AL21: =IF(B21="Kept for Self","—",IF(Z21="Baseball","Apr – Oct (MLB Season)",IF(Z21="Football","Aug – Feb (NFL Season)",IF(Z21="Basketball","Oct – Jun (NBA Season)",IF(OR(Z21="Movie",Z21="TV"),IF(ISNUMBER(SEARCH("Friday the 13th",A21)),"Sep – Oct (Halloween)","Year-Round"),IF(Z21="Music","Year-Round","Year-Round")))))) -> Aug – Feb (NFL Season)
A22: Kyle Tucker Signed Jersey (JSA) | B22: Listed | C22: 4824728 | D22: 24.57 | E22: =D22 -> 24.57 | F22: =SUMIF(C:C, C22, E:E) -> 384.34 | G22: =E22/F22 -> 0.063927772 | H22: 31 | I22: =H22*G22 -> 1.9817609 | J22: 99 | K22: =J22*G22 -> 6.3288495 | L22: 38.67 | M22: =L22*G22 -> 2.472087 | N22: =E22-I22+K22+M22 -> 31.389175 | O22: eBay | P22: =IFERROR(VLOOKUP(O22,PlatformFees,2,FALSE()),0) -> 0.136 | Q22: =IFERROR(VLOOKUP(O22,PlatformFees,3,FALSE()),0) -> 0.4 | R22: 6.5 | S22: 0 | T22: =(N22+R22+Q22)/(1-(P22+S22)) -> 44.316175 | U22: =MAX(MAX(T22*1.5, T22+15), IFERROR(VLOOKUP(A22,'Pricing Intelligence'!A:J,10,FALSE),0)) -> 66.474263 | V22: 125 | W22: =IFERROR(_xlfn.XLOOKUP(A22,'Sales Log'!$C$4:$C$303,'Sales Log'!$F$4:$F$303,0),0) -> 0 | X22: =IF(W22=0,0,W22-(W22*(P22+S22))-Q22-R22-N22) -> 0 | Y22: =IFERROR(IF(ISNUMBER(SEARCH("Jersey",A22)),"Jersey",IF(ISNUMBER(SEARCH("Photo",A22)),"Photo",IF(ISNUMBER(SEARCH("Baseball Bat",A22)),"Bat",IF(ISNUMBER(SEARCH("Bat",A22)),"Bat",IF(ISNUMBER(SEARCH("Baseball",A22)),"Baseball",IF(ISNUMBER(SEARCH("Football",A22)),"Football",IF(ISNUMBER(SEARCH("Mask",A22)),"Mask",IF(ISNUMBER(SEARCH("Drum",A22)),"Drum Stick",IF(ISNUMBER(SEARCH("Card",A22)),"Card",IF(ISNUMBER(SEARCH("RC",A22)),"Card","Other")))))))))),"Other") -> Jersey | Z22: Baseball | AA22: =IFERROR(TRIM(LEFT(A22,FIND(" Signed",A22)-1)),LEFT(A22,20)) -> Kyle Tucker | AB22: =IF(ISNUMBER(SEARCH("(Beckett)",A22)),"Beckett",IF(ISNUMBER(SEARCH("(JSA)",A22)),"JSA",IF(ISNUMBER(SEARCH("(PSA)",A22)),"PSA",IF(ISNUMBER(SEARCH("(ACOA)",A22)),"ACOA",IF(ISNUMBER(SEARCH("(Schwartz)",A22)),"Schwartz","Unlabeled"))))) -> JSA | AD22: 46204 | AE22: 46226 | AG22: =IF(AE22="","",IF(AF22="",TODAY()-AE22,AF22-AE22)) -> 6 | AH22: =HYPERLINK("https://www.ebay.com/sch/i.html?_nkw="&SUBSTITUTE(SUBSTITUTE(A22," ","+"),"""","")&"&LH_Sold=1&LH_Complete=1","View Sold Comps") -> View Sold Comps | AI22: =IF(OR(N22=0,W22=0),"",X22/N22) | AJ22: =IF(U22=0,"",(U22-U22*P22-Q22-R22-N22)/U22) -> 0.288 | AL22: =IF(B22="Kept for Self","—",IF(Z22="Baseball","Apr – Oct (MLB Season)",IF(Z22="Football","Aug – Feb (NFL Season)",IF(Z22="Basketball","Oct – Jun (NBA Season)",IF(OR(Z22="Movie",Z22="TV"),IF(ISNUMBER(SEARCH("Friday the 13th",A22)),"Sep – Oct (Halloween)","Year-Round"),IF(Z22="Music","Year-Round","Year-Round")))))) -> Apr – Oct (MLB Season)
A23: Steve Spurrier Signed Florida Gators 8x10 Photo Inscribed "Go Gators" (ACOA) | B23: Available | C23: 4824728 | D23: 43 | E23: =D23 -> 43 | F23: =SUMIF(C:C, C23, E:E) -> 384.34 | G23: =E23/F23 -> 0.11188011 | H23: 31 | I23: =H23*G23 -> 3.4682833 | J23: 99 | K23: =J23*G23 -> 11.076131 | L23: 38.67 | M23: =L23*G23 -> 4.3264037 | N23: =E23-I23+K23+M23 -> 54.934251 | O23: eBay | P23: =IFERROR(VLOOKUP(O23,PlatformFees,2,FALSE()),0) -> 0.136 | Q23: =IFERROR(VLOOKUP(O23,PlatformFees,3,FALSE()),0) -> 0.4 | R23: 6.5 | S23: 0 | T23: =(N23+R23+Q23)/(1-(P23+S23)) -> 71.56742 | U23: =MAX(MAX(T23*1.5, T23+15), IFERROR(VLOOKUP(A23,'Pricing Intelligence'!A:J,10,FALSE),0)) -> 107.35113 | V23: 0 | W23: =IFERROR(_xlfn.XLOOKUP(A23,'Sales Log'!$C$4:$C$303,'Sales Log'!$F$4:$F$303,0),0) -> 0 | X23: =IF(W23=0,0,W23-(W23*(P23+S23))-Q23-R23-N23) -> 0 | Y23: =IFERROR(IF(ISNUMBER(SEARCH("Jersey",A23)),"Jersey",IF(ISNUMBER(SEARCH("Photo",A23)),"Photo",IF(ISNUMBER(SEARCH("Baseball Bat",A23)),"Bat",IF(ISNUMBER(SEARCH("Bat",A23)),"Bat",IF(ISNUMBER(SEARCH("Baseball",A23)),"Baseball",IF(ISNUMBER(SEARCH("Football",A23)),"Football",IF(ISNUMBER(SEARCH("Mask",A23)),"Mask",IF(ISNUMBER(SEARCH("Drum",A23)),"Drum Stick",IF(ISNUMBER(SEARCH("Card",A23)),"Card",IF(ISNUMBER(SEARCH("RC",A23)),"Card","Other")))))))))),"Other") -> Photo | Z23: Football | AA23: =IFERROR(TRIM(LEFT(A23,FIND(" Signed",A23)-1)),LEFT(A23,20)) -> Steve Spurrier | AB23: =IF(ISNUMBER(SEARCH("(Beckett)",A23)),"Beckett",IF(ISNUMBER(SEARCH("(JSA)",A23)),"JSA",IF(ISNUMBER(SEARCH("(PSA)",A23)),"PSA",IF(ISNUMBER(SEARCH("(ACOA)",A23)),"ACOA",IF(ISNUMBER(SEARCH("(Schwartz)",A23)),"Schwartz","Unlabeled"))))) -> ACOA | AD23: 46204 | AG23: =IF(AE23="","",IF(AF23="",TODAY()-AE23,AF23-AE23)) | AH23: =HYPERLINK("https://www.ebay.com/sch/i.html?_nkw="&SUBSTITUTE(SUBSTITUTE(A23," ","+"),"""","")&"&LH_Sold=1&LH_Complete=1","View Sold Comps") -> View Sold Comps | AI23: =IF(OR(N23=0,W23=0),"",X23/N23) | AJ23: =IF(U23=0,"",(U23-U23*P23-Q23-R23-N23)/U23) -> 0.288 | AL23: =IF(B23="Kept for Self","—",IF(Z23="Baseball","Apr – Oct (MLB Season)",IF(Z23="Football","Aug – Feb (NFL Season)",IF(Z23="Basketball","Oct – Jun (NBA Season)",IF(OR(Z23="Movie",Z23="TV"),IF(ISNUMBER(SEARCH("Friday the 13th",A23)),"Sep – Oct (Halloween)","Year-Round"),IF(Z23="Music","Year-Round","Year-Round")))))) -> Aug – Feb (NFL Season)
A24: Joe Johnson Signed Jersey (Beckett) | B24: Available | C24: 4824988 | D24: 18.46 | E24: =D24 -> 18.46 | F24: =SUMIF(C:C, C24, E:E) -> 18.46 | G24: =E24/F24 -> 1 | H24: 20 | I24: =H24*G24 -> 20 | J24: 4.11 | K24: =J24*G24 -> 4.11 | L24: 1.8 | M24: =L24*G24 -> 1.8 | N24: =E24-I24+K24+M24 -> 4.37 | O24: eBay | P24: =IFERROR(VLOOKUP(O24,PlatformFees,2,FALSE()),0) -> 0.136 | Q24: =IFERROR(VLOOKUP(O24,PlatformFees,3,FALSE()),0) -> 0.4 | R24: 6.5 | S24: 0 | T24: =(N24+R24+Q24)/(1-(P24+S24)) -> 13.043981 | U24: =MAX(MAX(T24*1.5, T24+15), IFERROR(VLOOKUP(A24,'Pricing Intelligence'!A:J,10,FALSE),0)) -> 28.043981 | V24: 0 | W24: =IFERROR(_xlfn.XLOOKUP(A24,'Sales Log'!$C$4:$C$303,'Sales Log'!$F$4:$F$303,0),0) -> 0 | X24: =IF(W24=0,0,W24-(W24*(P24+S24))-Q24-R24-N24) -> 0 | Y24: =IFERROR(IF(ISNUMBER(SEARCH("Jersey",A24)),"Jersey",IF(ISNUMBER(SEARCH("Photo",A24)),"Photo",IF(ISNUMBER(SEARCH("Baseball Bat",A24)),"Bat",IF(ISNUMBER(SEARCH("Bat",A24)),"Bat",IF(ISNUMBER(SEARCH("Baseball",A24)),"Baseball",IF(ISNUMBER(SEARCH("Football",A24)),"Football",IF(ISNUMBER(SEARCH("Mask",A24)),"Mask",IF(ISNUMBER(SEARCH("Drum",A24)),"Drum Stick",IF(ISNUMBER(SEARCH("Card",A24)),"Card",IF(ISNUMBER(SEARCH("RC",A24)),"Card","Other")))))))))),"Other") -> Jersey | Z24: Basketball | AA24: =IFERROR(TRIM(LEFT(A24,FIND(" Signed",A24)-1)),LEFT(A24,20)) -> Joe Johnson | AB24: =IF(ISNUMBER(SEARCH("(Beckett)",A24)),"Beckett",IF(ISNUMBER(SEARCH("(JSA)",A24)),"JSA",IF(ISNUMBER(SEARCH("(PSA)",A24)),"PSA",IF(ISNUMBER(SEARCH("(ACOA)",A24)),"ACOA",IF(ISNUMBER(SEARCH("(Schwartz)",A24)),"Schwartz","Unlabeled"))))) -> Beckett | AD24: 46204 | AG24: =IF(AE24="","",IF(AF24="",TODAY()-AE24,AF24-AE24)) | AH24: =HYPERLINK("https://www.ebay.com/sch/i.html?_nkw="&SUBSTITUTE(SUBSTITUTE(A24," ","+"),"""","")&"&LH_Sold=1&LH_Complete=1","View Sold Comps") -> View Sold Comps | AI24: =IF(OR(N24=0,W24=0),"",X24/N24) | AJ24: =IF(U24=0,"",(U24-U24*P24-Q24-R24-N24)/U24) -> 0.46213124 | AL24: =IF(B24="Kept for Self","—",IF(Z24="Baseball","Apr – Oct (MLB Season)",IF(Z24="Football","Aug – Feb (NFL Season)",IF(Z24="Basketball","Oct – Jun (NBA Season)",IF(OR(Z24="Movie",Z24="TV"),IF(ISNUMBER(SEARCH("Friday the 13th",A24)),"Sep – Oct (Halloween)","Year-Round"),IF(Z24="Music","Year-Round","Year-Round")))))) -> Oct – Jun (NBA Season)
A25: Xavier Watts Signed Jersey (JSA) | B25: Available | C25: 4825068 | D25: 30.75 | E25: =D25 -> 30.75 | F25: =SUMIF(C:C, C25, E:E) -> 110.64 | G25: =E25/F25 -> 0.27792842 | H25: 20 | I25: =H25*G25 -> 5.5585683 | J25: 31.76 | K25: =J25*G25 -> 8.8270065 | L25: 11.13 | M25: =L25*G25 -> 3.0933433 | N25: =E25-I25+K25+M25 -> 37.111781 | O25: eBay | P25: =IFERROR(VLOOKUP(O25,PlatformFees,2,FALSE()),0) -> 0.136 | Q25: =IFERROR(VLOOKUP(O25,PlatformFees,3,FALSE()),0) -> 0.4 | R25: 6.5 | S25: 0 | T25: =(N25+R25+Q25)/(1-(P25+S25)) -> 50.939562 | U25: =MAX(MAX(T25*1.5, T25+15), IFERROR(VLOOKUP(A25,'Pricing Intelligence'!A:J,10,FALSE),0)) -> 76.409343 | V25: 0 | W25: =IFERROR(_xlfn.XLOOKUP(A25,'Sales Log'!$C$4:$C$303,'Sales Log'!$F$4:$F$303,0),0) -> 0 | X25: =IF(W25=0,0,W25-(W25*(P25+S25))-Q25-R25-N25) -> 0 | Y25: =IFERROR(IF(ISNUMBER(SEARCH("Jersey",A25)),"Jersey",IF(ISNUMBER(SEARCH("Photo",A25)),"Photo",IF(ISNUMBER(SEARCH("Baseball Bat",A25)),"Bat",IF(ISNUMBER(SEARCH("Bat",A25)),"Bat",IF(ISNUMBER(SEARCH("Baseball",A25)),"Baseball",IF(ISNUMBER(SEARCH("Football",A25)),"Football",IF(ISNUMBER(SEARCH("Mask",A25)),"Mask",IF(ISNUMBER(SEARCH("Drum",A25)),"Drum Stick",IF(ISNUMBER(SEARCH("Card",A25)),"Card",IF(ISNUMBER(SEARCH("RC",A25)),"Card","Other")))))))))),"Other") -> Jersey | Z25: Football | AA25: =IFERROR(TRIM(LEFT(A25,FIND(" Signed",A25)-1)),LEFT(A25,20)) -> Xavier Watts | AB25: =IF(ISNUMBER(SEARCH("(Beckett)",A25)),"Beckett",IF(ISNUMBER(SEARCH("(JSA)",A25)),"JSA",IF(ISNUMBER(SEARCH("(PSA)",A25)),"PSA",IF(ISNUMBER(SEARCH("(ACOA)",A25)),"ACOA",IF(ISNUMBER(SEARCH("(Schwartz)",A25)),"Schwartz","Unlabeled"))))) -> JSA | AD25: 46204 | AG25: =IF(AE25="","",IF(AF25="",TODAY()-AE25,AF25-AE25)) | AH25: =HYPERLINK("https://www.ebay.com/sch/i.html?_nkw="&SUBSTITUTE(SUBSTITUTE(A25," ","+"),"""","")&"&LH_Sold=1&LH_Complete=1","View Sold Comps") -> View Sold Comps | AI25: =IF(OR(N25=0,W25=0),"",X25/N25) | AJ25: =IF(U25=0,"",(U25-U25*P25-Q25-R25-N25)/U25) -> 0.288 | AL25: =IF(B25="Kept for Self","—",IF(Z25="Baseball","Apr – Oct (MLB Season)",IF(Z25="Football","Aug – Feb (NFL Season)",IF(Z25="Basketball","Oct – Jun (NBA Season)",IF(OR(Z25="Movie",Z25="TV"),IF(ISNUMBER(SEARCH("Friday the 13th",A25)),"Sep – Oct (Halloween)","Year-Round"),IF(Z25="Music","Year-Round","Year-Round")))))) -> Aug – Feb (NFL Season)
A26: Xavier Watts Signed Jersey Inscribed "Dirty Birds!" (JSA) | B26: Available | C26: 4825068 | D26: 30.75 | E26: =D26 -> 30.75 | F26: =SUMIF(C:C, C26, E:E) -> 110.64 | G26: =E26/F26 -> 0.27792842 | H26: 20 | I26: =H26*G26 -> 5.5585683 | J26: 31.76 | K26: =J26*G26 -> 8.8270065 | L26: 11.13 | M26: =L26*G26 -> 3.0933433 | N26: =E26-I26+K26+M26 -> 37.111781 | O26: eBay | P26: =IFERROR(VLOOKUP(O26,PlatformFees,2,FALSE()),0) -> 0.136 | Q26: =IFERROR(VLOOKUP(O26,PlatformFees,3,FALSE()),0) -> 0.4 | R26: 6.5 | S26: 0 | T26: =(N26+R26+Q26)/(1-(P26+S26)) -> 50.939562 | U26: =MAX(MAX(T26*1.5, T26+15), IFERROR(VLOOKUP(A26,'Pricing Intelligence'!A:J,10,FALSE),0)) -> 76.409343 | V26: 0 | W26: =IFERROR(_xlfn.XLOOKUP(A26,'Sales Log'!$C$4:$C$303,'Sales Log'!$F$4:$F$303,0),0) -> 0 | X26: =IF(W26=0,0,W26-(W26*(P26+S26))-Q26-R26-N26) -> 0 | Y26: =IFERROR(IF(ISNUMBER(SEARCH("Jersey",A26)),"Jersey",IF(ISNUMBER(SEARCH("Photo",A26)),"Photo",IF(ISNUMBER(SEARCH("Baseball Bat",A26)),"Bat",IF(ISNUMBER(SEARCH("Bat",A26)),"Bat",IF(ISNUMBER(SEARCH("Baseball",A26)),"Baseball",IF(ISNUMBER(SEARCH("Football",A26)),"Football",IF(ISNUMBER(SEARCH("Mask",A26)),"Mask",IF(ISNUMBER(SEARCH("Drum",A26)),"Drum Stick",IF(ISNUMBER(SEARCH("Card",A26)),"Card",IF(ISNUMBER(SEARCH("RC",A26)),"Card","Other")))))))))),"Other") -> Jersey | Z26: Football | AA26: =IFERROR(TRIM(LEFT(A26,FIND(" Signed",A26)-1)),LEFT(A26,20)) -> Xavier Watts | AB26: =IF(ISNUMBER(SEARCH("(Beckett)",A26)),"Beckett",IF(ISNUMBER(SEARCH("(JSA)",A26)),"JSA",IF(ISNUMBER(SEARCH("(PSA)",A26)),"PSA",IF(ISNUMBER(SEARCH("(ACOA)",A26)),"ACOA",IF(ISNUMBER(SEARCH("(Schwartz)",A26)),"Schwartz","Unlabeled"))))) -> JSA | AD26: 46204 | AG26: =IF(AE26="","",IF(AF26="",TODAY()-AE26,AF26-AE26)) | AH26: =HYPERLINK("https://www.ebay.com/sch/i.html?_nkw="&SUBSTITUTE(SUBSTITUTE(A26," ","+"),"""","")&"&LH_Sold=1&LH_Complete=1","View Sold Comps") -> View Sold Comps | AI26: =IF(OR(N26=0,W26=0),"",X26/N26) | AJ26: =IF(U26=0,"",(U26-U26*P26-Q26-R26-N26)/U26) -> 0.288 | AL26: =IF(B26="Kept for Self","—",IF(Z26="Baseball","Apr – Oct (MLB Season)",IF(Z26="Football","Aug – Feb (NFL Season)",IF(Z26="Basketball","Oct – Jun (NBA Season)",IF(OR(Z26="Movie",Z26="TV"),IF(ISNUMBER(SEARCH("Friday the 13th",A26)),"Sep – Oct (Halloween)","Year-Round"),IF(Z26="Music","Year-Round","Year-Round")))))) -> Aug – Feb (NFL Season)
A27: Rob Gronkowski Signed Jersey | B27: Listed | C27: 4825068 | D27: 24.57 | E27: =D27 -> 24.57 | F27: =SUMIF(C:C, C27, E:E) -> 110.64 | G27: =E27/F27 -> 0.22207158 | H27: 20 | I27: =H27*G27 -> 4.4414317 | J27: 31.76 | K27: =J27*G27 -> 7.0529935 | L27: 11.13 | M27: =L27*G27 -> 2.4716567 | N27: =E27-I27+K27+M27 -> 29.653219 | O27: eBay | P27: =IFERROR(VLOOKUP(O27,PlatformFees,2,FALSE()),0) -> 0.136 | Q27: =IFERROR(VLOOKUP(O27,PlatformFees,3,FALSE()),0) -> 0.4 | R27: 6.5 | S27: 0.02 | T27: =(N27+R27+Q27)/(1-(P27+S27)) -> 43.309501 | U27: =MAX(MAX(T27*1.5, T27+15), IFERROR(VLOOKUP(A27,'Pricing Intelligence'!A:J,10,FALSE),0)) -> 64.964251 | V27: 69.99 | W27: =IFERROR(_xlfn.XLOOKUP(A27,'Sales Log'!$C$4:$C$303,'Sales Log'!$F$4:$F$303,0),0) -> 0 | X27: =IF(W27=0,0,W27-(W27*(P27+S27))-Q27-R27-N27) -> 0 | Y27: =IFERROR(IF(ISNUMBER(SEARCH("Jersey",A27)),"Jersey",IF(ISNUMBER(SEARCH("Photo",A27)),"Photo",IF(ISNUMBER(SEARCH("Baseball Bat",A27)),"Bat",IF(ISNUMBER(SEARCH("Bat",A27)),"Bat",IF(ISNUMBER(SEARCH("Baseball",A27)),"Baseball",IF(ISNUMBER(SEARCH("Football",A27)),"Football",IF(ISNUMBER(SEARCH("Mask",A27)),"Mask",IF(ISNUMBER(SEARCH("Drum",A27)),"Drum Stick",IF(ISNUMBER(SEARCH("Card",A27)),"Card",IF(ISNUMBER(SEARCH("RC",A27)),"Card","Other")))))))))),"Other") -> Jersey | Z27: Football | AA27: =IFERROR(TRIM(LEFT(A27,FIND(" Signed",A27)-1)),LEFT(A27,20)) -> Rob Gronkowski | AB27: =IF(ISNUMBER(SEARCH("(Beckett)",A27)),"Beckett",IF(ISNUMBER(SEARCH("(JSA)",A27)),"JSA",IF(ISNUMBER(SEARCH("(PSA)",A27)),"PSA",IF(ISNUMBER(SEARCH("(ACOA)",A27)),"ACOA",IF(ISNUMBER(SEARCH("(Schwartz)",A27)),"Schwartz","Unlabeled"))))) -> Unlabeled | AD27: 46204 | AE27: 46211 | AG27: =IF(AE27="","",IF(AF27="",TODAY()-AE27,AF27-AE27)) -> 21 | AH27: =HYPERLINK("https://www.ebay.com/sch/i.html?_nkw="&SUBSTITUTE(SUBSTITUTE(A27," ","+"),"""","")&"&LH_Sold=1&LH_Complete=1","View Sold Comps") -> View Sold Comps | AI27: =IF(OR(N27=0,W27=0),"",X27/N27) | AJ27: =IF(U27=0,"",(U27-U27*P27-Q27-R27-N27)/U27) -> 0.30133333 | AL27: =IF(B27="Kept for Self","—",IF(Z27="Baseball","Apr – Oct (MLB Season)",IF(Z27="Football","Aug – Feb (NFL Season)",IF(Z27="Basketball","Oct – Jun (NBA Season)",IF(OR(Z27="Movie",Z27="TV"),IF(ISNUMBER(SEARCH("Friday the 13th",A27)),"Sep – Oct (Halloween)","Year-Round"),IF(Z27="Music","Year-Round","Year-Round")))))) -> Aug – Feb (NFL Season)
A28: Joe Johnson Signed Jersey (PSA) | B28: Listed | C28: 4825068 | D28: 24.57 | E28: =D28 -> 24.57 | F28: =SUMIF(C:C, C28, E:E) -> 110.64 | G28: =E28/F28 -> 0.22207158 | H28: 20 | I28: =H28*G28 -> 4.4414317 | J28: 31.76 | K28: =J28*G28 -> 7.0529935 | L28: 11.13 | M28: =L28*G28 -> 2.4716567 | N28: =E28-I28+K28+M28 -> 29.653219 | O28: eBay | P28: =IFERROR(VLOOKUP(O28,PlatformFees,2,FALSE()),0) -> 0.136 | Q28: =IFERROR(VLOOKUP(O28,PlatformFees,3,FALSE()),0) -> 0.4 | R28: 6.5 | S28: 0.02 | T28: =(N28+R28+Q28)/(1-(P28+S28)) -> 43.309501 | U28: =MAX(MAX(T28*1.5, T28+15), IFERROR(VLOOKUP(A28,'Pricing Intelligence'!A:J,10,FALSE),0)) -> 64.964251 | V28: 64.99 | W28: =IFERROR(_xlfn.XLOOKUP(A28,'Sales Log'!$C$4:$C$303,'Sales Log'!$F$4:$F$303,0),0) -> 0 | X28: =IF(W28=0,0,W28-(W28*(P28+S28))-Q28-R28-N28) -> 0 | Y28: =IFERROR(IF(ISNUMBER(SEARCH("Jersey",A28)),"Jersey",IF(ISNUMBER(SEARCH("Photo",A28)),"Photo",IF(ISNUMBER(SEARCH("Baseball Bat",A28)),"Bat",IF(ISNUMBER(SEARCH("Bat",A28)),"Bat",IF(ISNUMBER(SEARCH("Baseball",A28)),"Baseball",IF(ISNUMBER(SEARCH("Football",A28)),"Football",IF(ISNUMBER(SEARCH("Mask",A28)),"Mask",IF(ISNUMBER(SEARCH("Drum",A28)),"Drum Stick",IF(ISNUMBER(SEARCH("Card",A28)),"Card",IF(ISNUMBER(SEARCH("RC",A28)),"Card","Other")))))))))),"Other") -> Jersey | Z28: Basketball | AA28: =IFERROR(TRIM(LEFT(A28,FIND(" Signed",A28)-1)),LEFT(A28,20)) -> Joe Johnson | AB28: =IF(ISNUMBER(SEARCH("(Beckett)",A28)),"Beckett",IF(ISNUMBER(SEARCH("(JSA)",A28)),"JSA",IF(ISNUMBER(SEARCH("(PSA)",A28)),"PSA",IF(ISNUMBER(SEARCH("(ACOA)",A28)),"ACOA",IF(ISNUMBER(SEARCH("(Schwartz)",A28)),"Schwartz","Unlabeled"))))) -> PSA | AD28: 46204 | AE28: 46211 | AG28: =IF(AE28="","",IF(AF28="",TODAY()-AE28,AF28-AE28)) -> 21 | AH28: =HYPERLINK("https://www.ebay.com/sch/i.html?_nkw="&SUBSTITUTE(SUBSTITUTE(A28," ","+"),"""","")&"&LH_Sold=1&LH_Complete=1","View Sold Comps") -> View Sold Comps | AI28: =IF(OR(N28=0,W28=0),"",X28/N28) | AJ28: =IF(U28=0,"",(U28-U28*P28-Q28-R28-N28)/U28) -> 0.30133333 | AL28: =IF(B28="Kept for Self","—",IF(Z28="Baseball","Apr – Oct (MLB Season)",IF(Z28="Football","Aug – Feb (NFL Season)",IF(Z28="Basketball","Oct – Jun (NBA Season)",IF(OR(Z28="Movie",Z28="TV"),IF(ISNUMBER(SEARCH("Friday the 13th",A28)),"Sep – Oct (Halloween)","Year-Round"),IF(Z28="Music","Year-Round","Year-Round")))))) -> Oct – Jun (NBA Season)
A29: Moses Moody Signed Jersey (Beckett) | B29: Available | C29: 4837185 | D29: 14.74 | E29: =D29 -> 14.74 | F29: =SUMIF(C:C, C29, E:E) -> 49.14 | G29: =E29/F29 -> 0.2999593 | H29: 20 | I29: =H29*G29 -> 5.999186 | J29: 11 | K29: =J29*G29 -> 3.2995523 | L29: 4.81 | M29: =L29*G29 -> 1.4428042 | N29: =E29-I29+K29+M29 -> 13.483171 | O29: eBay | P29: =IFERROR(VLOOKUP(O29,PlatformFees,2,FALSE()),0) -> 0.136 | Q29: =IFERROR(VLOOKUP(O29,PlatformFees,3,FALSE()),0) -> 0.4 | R29: 6.5 | S29: 0 | T29: =(N29+R29+Q29)/(1-(P29+S29)) -> 23.591633 | U29: =MAX(MAX(T29*1.5, T29+15), IFERROR(VLOOKUP(A29,'Pricing Intelligence'!A:J,10,FALSE),0)) -> 38.591633 | V29: 0 | W29: =IFERROR(_xlfn.XLOOKUP(A29,'Sales Log'!$C$4:$C$303,'Sales Log'!$F$4:$F$303,0),0) -> 0 | X29: =IF(W29=0,0,W29-(W29*(P29+S29))-Q29-R29-N29) -> 0 | Y29: =IFERROR(IF(ISNUMBER(SEARCH("Jersey",A29)),"Jersey",IF(ISNUMBER(SEARCH("Photo",A29)),"Photo",IF(ISNUMBER(SEARCH("Baseball Bat",A29)),"Bat",IF(ISNUMBER(SEARCH("Bat",A29)),"Bat",IF(ISNUMBER(SEARCH("Baseball",A29)),"Baseball",IF(ISNUMBER(SEARCH("Football",A29)),"Football",IF(ISNUMBER(SEARCH("Mask",A29)),"Mask",IF(ISNUMBER(SEARCH("Drum",A29)),"Drum Stick",IF(ISNUMBER(SEARCH("Card",A29)),"Card",IF(ISNUMBER(SEARCH("RC",A29)),"Card","Other")))))))))),"Other") -> Jersey | Z29: Basketball | AA29: =IFERROR(TRIM(LEFT(A29,FIND(" Signed",A29)-1)),LEFT(A29,20)) -> Moses Moody | AB29: =IF(ISNUMBER(SEARCH("(Beckett)",A29)),"Beckett",IF(ISNUMBER(SEARCH("(JSA)",A29)),"JSA",IF(ISNUMBER(SEARCH("(PSA)",A29)),"PSA",IF(ISNUMBER(SEARCH("(ACOA)",A29)),"ACOA",IF(ISNUMBER(SEARCH("(Schwartz)",A29)),"Schwartz","Unlabeled"))))) -> Beckett | AD29: 46210 | AG29: =IF(AE29="","",IF(AF29="",TODAY()-AE29,AF29-AE29)) | AH29: =HYPERLINK("https://www.ebay.com/sch/i.html?_nkw="&SUBSTITUTE(SUBSTITUTE(A29," ","+"),"""","")&"&LH_Sold=1&LH_Complete=1","View Sold Comps") -> View Sold Comps | AI29: =IF(OR(N29=0,W29=0),"",X29/N29) | AJ29: =IF(U29=0,"",(U29-U29*P29-Q29-R29-N29)/U29) -> 0.33582409 | AL29: =IF(B29="Kept for Self","—",IF(Z29="Baseball","Apr – Oct (MLB Season)",IF(Z29="Football","Aug – Feb (NFL Season)",IF(Z29="Basketball","Oct – Jun (NBA Season)",IF(OR(Z29="Movie",Z29="TV"),IF(ISNUMBER(SEARCH("Friday the 13th",A29)),"Sep – Oct (Halloween)","Year-Round"),IF(Z29="Music","Year-Round","Year-Round")))))) -> Oct – Jun (NBA Season)
A30: Grayson Allen Signed Jersey (Beckett) | B30: Available | C30: 4837185 | D30: 18.43 | E30: =D30 -> 18.43 | F30: =SUMIF(C:C, C30, E:E) -> 49.14 | G30: =E30/F30 -> 0.37505088 | H30: 20 | I30: =H30*G30 -> 7.5010175 | J30: 11 | K30: =J30*G30 -> 4.1255596 | L30: 4.81 | M30: =L30*G30 -> 1.8039947 | N30: =E30-I30+K30+M30 -> 16.858537 | O30: eBay | P30: =IFERROR(VLOOKUP(O30,PlatformFees,2,FALSE()),0) -> 0.136 | Q30: =IFERROR(VLOOKUP(O30,PlatformFees,3,FALSE()),0) -> 0.4 | R30: 6.5 | S30: 0 | T30: =(N30+R30+Q30)/(1-(P30+S30)) -> 27.498307 | U30: =MAX(MAX(T30*1.5, T30+15), IFERROR(VLOOKUP(A30,'Pricing Intelligence'!A:J,10,FALSE),0)) -> 42.498307 | V30: 0 | W30: =IFERROR(_xlfn.XLOOKUP(A30,'Sales Log'!$C$4:$C$303,'Sales Log'!$F$4:$F$303,0),0) -> 0 | X30: =IF(W30=0,0,W30-(W30*(P30+S30))-Q30-R30-N30) -> 0 | Y30: =IFERROR(IF(ISNUMBER(SEARCH("Jersey",A30)),"Jersey",IF(ISNUMBER(SEARCH("Photo",A30)),"Photo",IF(ISNUMBER(SEARCH("Baseball Bat",A30)),"Bat",IF(ISNUMBER(SEARCH("Bat",A30)),"Bat",IF(ISNUMBER(SEARCH("Baseball",A30)),"Baseball",IF(ISNUMBER(SEARCH("Football",A30)),"Football",IF(ISNUMBER(SEARCH("Mask",A30)),"Mask",IF(ISNUMBER(SEARCH("Drum",A30)),"Drum Stick",IF(ISNUMBER(SEARCH("Card",A30)),"Card",IF(ISNUMBER(SEARCH("RC",A30)),"Card","Other")))))))))),"Other") -> Jersey | Z30: Basketball | AA30: =IFERROR(TRIM(LEFT(A30,FIND(" Signed",A30)-1)),LEFT(A30,20)) -> Grayson Allen | AB30: =IF(ISNUMBER(SEARCH("(Beckett)",A30)),"Beckett",IF(ISNUMBER(SEARCH("(JSA)",A30)),"JSA",IF(ISNUMBER(SEARCH("(PSA)",A30)),"PSA",IF(ISNUMBER(SEARCH("(ACOA)",A30)),"ACOA",IF(ISNUMBER(SEARCH("(Schwartz)",A30)),"Schwartz","Unlabeled"))))) -> Beckett | AD30: 46210 | AG30: =IF(AE30="","",IF(AF30="",TODAY()-AE30,AF30-AE30)) | AH30: =HYPERLINK("https://www.ebay.com/sch/i.html?_nkw="&SUBSTITUTE(SUBSTITUTE(A30," ","+"),"""","")&"&LH_Sold=1&LH_Complete=1","View Sold Comps") -> View Sold Comps | AI30: =IF(OR(N30=0,W30=0),"",X30/N30) | AJ30: =IF(U30=0,"",(U30-U30*P30-Q30-R30-N30)/U30) -> 0.30495333 | AL30: =IF(B30="Kept for Self","—",IF(Z30="Baseball","Apr – Oct (MLB Season)",IF(Z30="Football","Aug – Feb (NFL Season)",IF(Z30="Basketball","Oct – Jun (NBA Season)",IF(OR(Z30="Movie",Z30="TV"),IF(ISNUMBER(SEARCH("Friday the 13th",A30)),"Sep – Oct (Halloween)","Year-Round"),IF(Z30="Music","Year-Round","Year-Round")))))) -> Oct – Jun (NBA Season)
A31: Sam Hauser Signed Jersey (Beckett) | B31: Available | C31: 4837185 | D31: 15.97 | E31: =D31 -> 15.97 | F31: =SUMIF(C:C, C31, E:E) -> 49.14 | G31: =E31/F31 -> 0.32498982 | H31: 20 | I31: =H31*G31 -> 6.4997965 | J31: 11 | K31: =J31*G31 -> 3.5748881 | L31: 4.81 | M31: =L31*G31 -> 1.5632011 | N31: =E31-I31+K31+M31 -> 14.608293 | O31: eBay | P31: =IFERROR(VLOOKUP(O31,PlatformFees,2,FALSE()),0) -> 0.136 | Q31: =IFERROR(VLOOKUP(O31,PlatformFees,3,FALSE()),0) -> 0.4 | R31: 6.5 | S31: 0 | T31: =(N31+R31+Q31)/(1-(P31+S31)) -> 24.893857 | U31: =MAX(MAX(T31*1.5, T31+15), IFERROR(VLOOKUP(A31,'Pricing Intelligence'!A:J,10,FALSE),0)) -> 39.893857 | V31: 0 | W31: =IFERROR(_xlfn.XLOOKUP(A31,'Sales Log'!$C$4:$C$303,'Sales Log'!$F$4:$F$303,0),0) -> 0 | X31: =IF(W31=0,0,W31-(W31*(P31+S31))-Q31-R31-N31) -> 0 | Y31: =IFERROR(IF(ISNUMBER(SEARCH("Jersey",A31)),"Jersey",IF(ISNUMBER(SEARCH("Photo",A31)),"Photo",IF(ISNUMBER(SEARCH("Baseball Bat",A31)),"Bat",IF(ISNUMBER(SEARCH("Bat",A31)),"Bat",IF(ISNUMBER(SEARCH("Baseball",A31)),"Baseball",IF(ISNUMBER(SEARCH("Football",A31)),"Football",IF(ISNUMBER(SEARCH("Mask",A31)),"Mask",IF(ISNUMBER(SEARCH("Drum",A31)),"Drum Stick",IF(ISNUMBER(SEARCH("Card",A31)),"Card",IF(ISNUMBER(SEARCH("RC",A31)),"Card","Other")))))))))),"Other") -> Jersey | Z31: Basketball | AA31: =IFERROR(TRIM(LEFT(A31,FIND(" Signed",A31)-1)),LEFT(A31,20)) -> Sam Hauser | AB31: =IF(ISNUMBER(SEARCH("(Beckett)",A31)),"Beckett",IF(ISNUMBER(SEARCH("(JSA)",A31)),"JSA",IF(ISNUMBER(SEARCH("(PSA)",A31)),"PSA",IF(ISNUMBER(SEARCH("(ACOA)",A31)),"ACOA",IF(ISNUMBER(SEARCH("(Schwartz)",A31)),"Schwartz","Unlabeled"))))) -> Beckett | AD31: 46210 | AG31: =IF(AE31="","",IF(AF31="",TODAY()-AE31,AF31-AE31)) | AH31: =HYPERLINK("https://www.ebay.com/sch/i.html?_nkw="&SUBSTITUTE(SUBSTITUTE(A31," ","+"),"""","")&"&LH_Sold=1&LH_Complete=1","View Sold Comps") -> View Sold Comps | AI31: =IF(OR(N31=0,W31=0),"",X31/N31) | AJ31: =IF(U31=0,"",(U31-U31*P31-Q31-R31-N31)/U31) -> 0.32486204 | AL31: =IF(B31="Kept for Self","—",IF(Z31="Baseball","Apr – Oct (MLB Season)",IF(Z31="Football","Aug – Feb (NFL Season)",IF(Z31="Basketball","Oct – Jun (NBA Season)",IF(OR(Z31="Movie",Z31="TV"),IF(ISNUMBER(SEARCH("Friday the 13th",A31)),"Sep – Oct (Halloween)","Year-Round"),IF(Z31="Music","Year-Round","Year-Round")))))) -> Oct – Jun (NBA Season)
A32: Charlie Sheen, Tom Berenger & Corbin Bernsen Signed Jersey (Beckett) | B32: Listed | C32: 4837266 | D32: 65.52 | E32: =D32 -> 65.52 | F32: =SUMIF(C:C, C32, E:E) -> 155.48 | G32: =E32/F32 -> 0.42140468 | H32: 20 | I32: =H32*G32 -> 8.4280936 | J32: 22 | K32: =J32*G32 -> 9.270903 | L32: 14.2 | M32: =L32*G32 -> 5.9839465 | N32: =E32-I32+K32+M32 -> 72.346756 | O32: eBay | P32: =IFERROR(VLOOKUP(O32,PlatformFees,2,FALSE()),0) -> 0.136 | Q32: =IFERROR(VLOOKUP(O32,PlatformFees,3,FALSE()),0) -> 0.4 | R32: 6.5 | S32: 0.03 | T32: =(N32+R32+Q32)/(1-(P32+S32)) -> 95.020091 | U32: =MAX(MAX(T32*1.5, T32+15), IFERROR(VLOOKUP(A32,'Pricing Intelligence'!A:J,10,FALSE),0)) -> 152.66667 | V32: 142.49 | W32: =IFERROR(_xlfn.XLOOKUP(A32,'Sales Log'!$C$4:$C$303,'Sales Log'!$F$4:$F$303,0),0) -> 0 | X32: =IF(W32=0,0,W32-(W32*(P32+S32))-Q32-R32-N32) -> 0 | Y32: =IFERROR(IF(ISNUMBER(SEARCH("Jersey",A32)),"Jersey",IF(ISNUMBER(SEARCH("Photo",A32)),"Photo",IF(ISNUMBER(SEARCH("Baseball Bat",A32)),"Bat",IF(ISNUMBER(SEARCH("Bat",A32)),"Bat",IF(ISNUMBER(SEARCH("Baseball",A32)),"Baseball",IF(ISNUMBER(SEARCH("Football",A32)),"Football",IF(ISNUMBER(SEARCH("Mask",A32)),"Mask",IF(ISNUMBER(SEARCH("Drum",A32)),"Drum Stick",IF(ISNUMBER(SEARCH("Card",A32)),"Card",IF(ISNUMBER(SEARCH("RC",A32)),"Card","Other")))))))))),"Other") -> Jersey | Z32: Movie | AA32: =IFERROR(TRIM(LEFT(A32,FIND(" Signed",A32)-1)),LEFT(A32,20)) -> Charlie Sheen, Tom Berenger & Corbin Bernsen | AB32: =IF(ISNUMBER(SEARCH("(Beckett)",A32)),"Beckett",IF(ISNUMBER(SEARCH("(JSA)",A32)),"JSA",IF(ISNUMBER(SEARCH("(PSA)",A32)),"PSA",IF(ISNUMBER(SEARCH("(ACOA)",A32)),"ACOA",IF(ISNUMBER(SEARCH("(Schwartz)",A32)),"Schwartz","Unlabeled"))))) -> Beckett | AD32: 46210 | AE32: 46225 | AG32: =IF(AE32="","",IF(AF32="",TODAY()-AE32,AF32-AE32)) -> 7 | AH32: =HYPERLINK("https://www.ebay.com/sch/i.html?_nkw="&SUBSTITUTE(SUBSTITUTE(A32," ","+"),"""","")&"&LH_Sold=1&LH_Complete=1","View Sold Comps") -> View Sold Comps | AI32: =IF(OR(N32=0,W32=0),"",X32/N32) | AJ32: =IF(U32=0,"",(U32-U32*P32-Q32-R32-N32)/U32) -> 0.34491645 | AL32: =IF(B32="Kept for Self","—",IF(Z32="Baseball","Apr – Oct (MLB Season)",IF(Z32="Football","Aug – Feb (NFL Season)",IF(Z32="Basketball","Oct – Jun (NBA Season)",IF(OR(Z32="Movie",Z32="TV"),IF(ISNUMBER(SEARCH("Friday the 13th",A32)),"Sep – Oct (Halloween)","Year-Round"),IF(Z32="Music","Year-Round","Year-Round")))))) -> Year-Round
A33: Trey Lance Signed Jersey (Beckett) | B33: Listed | C33: 4837266 | D33: 16.25 | E33: =D33 -> 16.25 | F33: =SUMIF(C:C, C33, E:E) -> 155.48 | G33: =E33/F33 -> 0.10451505 | H33: 20 | I33: =H33*G33 -> 2.090301 | J33: 22 | K33: =J33*G33 -> 2.2993311 | L33: 14.2 | M33: =L33*G33 -> 1.4841137 | N33: =E33-I33+K33+M33 -> 17.943144 | O33: eBay | P33: =IFERROR(VLOOKUP(O33,PlatformFees,2,FALSE()),0) -> 0.136 | Q33: =IFERROR(VLOOKUP(O33,PlatformFees,3,FALSE()),0) -> 0.4 | R33: 6.5 | S33: 0.03 | T33: =(N33+R33+Q33)/(1-(P33+S33)) -> 29.787942 | U33: =MAX(MAX(T33*1.5, T33+15), IFERROR(VLOOKUP(A33,'Pricing Intelligence'!A:J,10,FALSE),0)) -> 44.787942 | V33: 36.09 | W33: =IFERROR(_xlfn.XLOOKUP(A33,'Sales Log'!$C$4:$C$303,'Sales Log'!$F$4:$F$303,0),0) -> 0 | X33: =IF(W33=0,0,W33-(W33*(P33+S33))-Q33-R33-N33) -> 0 | Y33: =IFERROR(IF(ISNUMBER(SEARCH("Jersey",A33)),"Jersey",IF(ISNUMBER(SEARCH("Photo",A33)),"Photo",IF(ISNUMBER(SEARCH("Baseball Bat",A33)),"Bat",IF(ISNUMBER(SEARCH("Bat",A33)),"Bat",IF(ISNUMBER(SEARCH("Baseball",A33)),"Baseball",IF(ISNUMBER(SEARCH("Football",A33)),"Football",IF(ISNUMBER(SEARCH("Mask",A33)),"Mask",IF(ISNUMBER(SEARCH("Drum",A33)),"Drum Stick",IF(ISNUMBER(SEARCH("Card",A33)),"Card",IF(ISNUMBER(SEARCH("RC",A33)),"Card","Other")))))))))),"Other") -> Jersey | Z33: Football | AA33: =IFERROR(TRIM(LEFT(A33,FIND(" Signed",A33)-1)),LEFT(A33,20)) -> Trey Lance | AB33: =IF(ISNUMBER(SEARCH("(Beckett)",A33)),"Beckett",IF(ISNUMBER(SEARCH("(JSA)",A33)),"JSA",IF(ISNUMBER(SEARCH("(PSA)",A33)),"PSA",IF(ISNUMBER(SEARCH("(ACOA)",A33)),"ACOA",IF(ISNUMBER(SEARCH("(Schwartz)",A33)),"Schwartz","Unlabeled"))))) -> Beckett | AD33: 46210 | AE33: 46225 | AG33: =IF(AE33="","",IF(AF33="",TODAY()-AE33,AF33-AE33)) -> 7 | AH33: =HYPERLINK("https://www.ebay.com/sch/i.html?_nkw="&SUBSTITUTE(SUBSTITUTE(A33," ","+"),"""","")&"&LH_Sold=1&LH_Complete=1","View Sold Comps") -> View Sold Comps | AI33: =IF(OR(N33=0,W33=0),"",X33/N33) | AJ33: =IF(U33=0,"",(U33-U33*P33-Q33-R33-N33)/U33) -> 0.30931625 | AL33: =IF(B33="Kept for Self","—",IF(Z33="Baseball","Apr – Oct (MLB Season)",IF(Z33="Football","Aug – Feb (NFL Season)",IF(Z33="Basketball","Oct – Jun (NBA Season)",IF(OR(Z33="Movie",Z33="TV"),IF(ISNUMBER(SEARCH("Friday the 13th",A33)),"Sep – Oct (Halloween)","Year-Round"),IF(Z33="Music","Year-Round","Year-Round")))))) -> Aug – Feb (NFL Season)
A34: Chad Smith Signed 16" Drum Stick (Beckett) | B34: Listed | C34: 4837266 | D34: 43 | E34: =D34 -> 43 | F34: =SUMIF(C:C, C34, E:E) -> 155.48 | G34: =E34/F34 -> 0.2765629 | H34: 20 | I34: =H34*G34 -> 5.531258 | J34: 22 | K34: =J34*G34 -> 6.0843838 | L34: 14.2 | M34: =L34*G34 -> 3.9271932 | N34: =E34-I34+K34+M34 -> 47.480319 | O34: eBay | P34: =IFERROR(VLOOKUP(O34,PlatformFees,2,FALSE()),0) -> 0.136 | Q34: =IFERROR(VLOOKUP(O34,PlatformFees,3,FALSE()),0) -> 0.4 | R34: 6.5 | S34: 0.03 | T34: =(N34+R34+Q34)/(1-(P34+S34)) -> 65.204219 | U34: =MAX(MAX(T34*1.5, T34+15), IFERROR(VLOOKUP(A34,'Pricing Intelligence'!A:J,10,FALSE),0)) -> 102.66333 | V34: 119.99 | W34: =IFERROR(_xlfn.XLOOKUP(A34,'Sales Log'!$C$4:$C$303,'Sales Log'!$F$4:$F$303,0),0) -> 0 | X34: =IF(W34=0,0,W34-(W34*(P34+S34))-Q34-R34-N34) -> 0 | Y34: =IFERROR(IF(ISNUMBER(SEARCH("Jersey",A34)),"Jersey",IF(ISNUMBER(SEARCH("Photo",A34)),"Photo",IF(ISNUMBER(SEARCH("Baseball Bat",A34)),"Bat",IF(ISNUMBER(SEARCH("Bat",A34)),"Bat",IF(ISNUMBER(SEARCH("Baseball",A34)),"Baseball",IF(ISNUMBER(SEARCH("Football",A34)),"Football",IF(ISNUMBER(SEARCH("Mask",A34)),"Mask",IF(ISNUMBER(SEARCH("Drum",A34)),"Drum Stick",IF(ISNUMBER(SEARCH("Card",A34)),"Card",IF(ISNUMBER(SEARCH("RC",A34)),"Card","Other")))))))))),"Other") -> Drum Stick | Z34: Music | AA34: =IFERROR(TRIM(LEFT(A34,FIND(" Signed",A34)-1)),LEFT(A34,20)) -> Chad Smith | AB34: =IF(ISNUMBER(SEARCH("(Beckett)",A34)),"Beckett",IF(ISNUMBER(SEARCH("(JSA)",A34)),"JSA",IF(ISNUMBER(SEARCH("(PSA)",A34)),"PSA",IF(ISNUMBER(SEARCH("(ACOA)",A34)),"ACOA",IF(ISNUMBER(SEARCH("(Schwartz)",A34)),"Schwartz","Unlabeled"))))) -> Beckett | AD34: 46210 | AE34: 46225 | AG34: =IF(AE34="","",IF(AF34="",TODAY()-AE34,AF34-AE34)) -> 7 | AH34: =HYPERLINK("https://www.ebay.com/sch/i.html?_nkw="&SUBSTITUTE(SUBSTITUTE(A34," ","+"),"""","")&"&LH_Sold=1&LH_Complete=1","View Sold Comps") -> View Sold Comps | AI34: =IF(OR(N34=0,W34=0),"",X34/N34) | AJ34: =IF(U34=0,"",(U34-U34*P34-Q34-R34-N34)/U34) -> 0.33430437 | AL34: =IF(B34="Kept for Self","—",IF(Z34="Baseball","Apr – Oct (MLB Season)",IF(Z34="Football","Aug – Feb (NFL Season)",IF(Z34="Basketball","Oct – Jun (NBA Season)",IF(OR(Z34="Movie",Z34="TV"),IF(ISNUMBER(SEARCH("Friday the 13th",A34)),"Sep – Oct (Halloween)","Year-Round"),IF(Z34="Music","Year-Round","Year-Round")))))) -> Year-Round
A35: Andre Rison Signed NFL Football Inscribed "Bad Moon" (Schwartz) | B35: Available | C35: 4837266 | D35: 30.71 | E35: =D35 -> 30.71 | F35: =SUMIF(C:C, C35, E:E) -> 155.48 | G35: =E35/F35 -> 0.19751737 | H35: 20 | I35: =H35*G35 -> 3.9503473 | J35: 22 | K35: =J35*G35 -> 4.345382 | L35: 14.2 | M35: =L35*G35 -> 2.8047466 | N35: =E35-I35+K35+M35 -> 33.909781 | O35: eBay | P35: =IFERROR(VLOOKUP(O35,PlatformFees,2,FALSE()),0) -> 0.136 | Q35: =IFERROR(VLOOKUP(O35,PlatformFees,3,FALSE()),0) -> 0.4 | R35: 6.5 | S35: 0 | T35: =(N35+R35+Q35)/(1-(P35+S35)) -> 47.233543 | U35: =MAX(MAX(T35*1.5, T35+15), IFERROR(VLOOKUP(A35,'Pricing Intelligence'!A:J,10,FALSE),0)) -> 70.850315 | V35: 0 | W35: =IFERROR(_xlfn.XLOOKUP(A35,'Sales Log'!$C$4:$C$303,'Sales Log'!$F$4:$F$303,0),0) -> 0 | X35: =IF(W35=0,0,W35-(W35*(P35+S35))-Q35-R35-N35) -> 0 | Y35: =IFERROR(IF(ISNUMBER(SEARCH("Jersey",A35)),"Jersey",IF(ISNUMBER(SEARCH("Photo",A35)),"Photo",IF(ISNUMBER(SEARCH("Baseball Bat",A35)),"Bat",IF(ISNUMBER(SEARCH("Bat",A35)),"Bat",IF(ISNUMBER(SEARCH("Baseball",A35)),"Baseball",IF(ISNUMBER(SEARCH("Football",A35)),"Football",IF(ISNUMBER(SEARCH("Mask",A35)),"Mask",IF(ISNUMBER(SEARCH("Drum",A35)),"Drum Stick",IF(ISNUMBER(SEARCH("Card",A35)),"Card",IF(ISNUMBER(SEARCH("RC",A35)),"Card","Other")))))))))),"Other") -> Football | Z35: Football | AA35: =IFERROR(TRIM(LEFT(A35,FIND(" Signed",A35)-1)),LEFT(A35,20)) -> Andre Rison | AB35: =IF(ISNUMBER(SEARCH("(Beckett)",A35)),"Beckett",IF(ISNUMBER(SEARCH("(JSA)",A35)),"JSA",IF(ISNUMBER(SEARCH("(PSA)",A35)),"PSA",IF(ISNUMBER(SEARCH("(ACOA)",A35)),"ACOA",IF(ISNUMBER(SEARCH("(Schwartz)",A35)),"Schwartz","Unlabeled"))))) -> Schwartz | AD35: 46210 | AG35: =IF(AE35="","",IF(AF35="",TODAY()-AE35,AF35-AE35)) | AH35: =HYPERLINK("https://www.ebay.com/sch/i.html?_nkw="&SUBSTITUTE(SUBSTITUTE(A35," ","+"),"""","")&"&LH_Sold=1&LH_Complete=1","View Sold Comps") -> View Sold Comps | AI35: =IF(OR(N35=0,W35=0),"",X35/N35) | AJ35: =IF(U35=0,"",(U35-U35*P35-Q35-R35-N35)/U35) -> 0.288 | AL35: =IF(B35="Kept for Self","—",IF(Z35="Baseball","Apr – Oct (MLB Season)",IF(Z35="Football","Aug – Feb (NFL Season)",IF(Z35="Basketball","Oct – Jun (NBA Season)",IF(OR(Z35="Movie",Z35="TV"),IF(ISNUMBER(SEARCH("Friday the 13th",A35)),"Sep – Oct (Halloween)","Year-Round"),IF(Z35="Music","Year-Round","Year-Round")))))) -> Aug – Feb (NFL Season)
C36: TOTALS | D36: =SUM(D2:D35) -> 974.59 | E36: =SUM(E2:E35) -> 974.59 | H36: =SUM(H2:H35) -> 1009 | I36: =SUM(I2:I35) -> 221 | J36: =SUM(J2:J35) -> 1777.91 | K36: =SUM(K2:K35) -> 218.78 | L36: =SUM(L2:L35) -> 736.3 | M36: =SUM(M2:M35) -> 94.77 | N36: =SUM(N2:N35) -> 1067.14 | Q36: =SUM(Q2:Q35) -> 13.6 | R36: =SUM(R2:R35) -> 221 | T36: =SUM(T2:T35) -> 1521.5269 | U36: =SUM(U2:U35) -> 2579.7325 | W36: =SUM(W2:W35) -> 0 | X36: =SUM(X2:X35) -> 0
C38: SUMMARY
C39: Total Items: | D39: =COUNTA(A2:A35) -> 34
C40: Unique Invoices: | D40: {=SUMPRODUCT(1/COUNTIF(C2:C35,C2:C35))} -> 8
C41: Total Base Cost: | D41: =N36 -> 1067.14
C42: Total Discounts Applied: | D42: =I36 -> 221
C43: Total Shipping: | D43: =K36 -> 218.78
C44: Total Tax: | D44: =M36 -> 94.77
C45: Average Item Cost: | D45: =AVERAGE(N2:N35) -> 31.386471
V46: 65

Sheet Sales Log
A1: SALES LOG
A3: Sale ID | B3: Sale Date | C3: Item Name | D3: Platform Sold | E3: Buyer / Handle | F3: Gross Sale Price | G3: Buyer Shipping Paid | H3: Actual Shipping Cost | I3: Platform Fee % | J3: Platform Flat Fee | K3: Platform Fees ($) | L3: Payment Processing ($) | M3: Promoted Listing Fee ($) | N3: Net Proceeds | O3: True Total Cost | P3: Net Profit | Q3: ROI % | R3: Days to Sell | S3: SALES SUMMARY | U3: Invoice ID (helper) | V3: Category (helper) | W3: Auth (helper)
A4: =IF(C4="","",ROW()-3) | I4: =IFERROR(VLOOKUP(D4,PlatformFees,2,FALSE()),0) -> 0 | J4: =IFERROR(VLOOKUP(D4,PlatformFees,3,FALSE()),0) -> 0 | K4: =IF(ISNUMBER(F4),F4*I4+J4,0) -> 0 | N4: =IF(ISNUMBER(F4),F4+IFERROR(G4,0)-IFERROR(H4,0)-K4-IFERROR(L4,0)-IFERROR(M4,0),0) -> 0 | O4: =IFERROR(VLOOKUP(C4,Inventory!$A$2:$N$35,13,FALSE()),0) -> 0 | P4: =IF(ISNUMBER(F4),N4-O4,0) -> 0 | Q4: =IFERROR(IF(O4=0,0,P4/O4),0) -> 0 | R4: =IFERROR(IF(AND(ISNUMBER(B4),C4<>""),B4-VLOOKUP(C4,Inventory!$A$2:$AE$35,29,FALSE()),""),"") | S4: Total Sales Count | T4: =COUNTA(C4:C303) -> 0 | U4: =IFERROR(VLOOKUP(C4,Inventory!$A$2:$C$35,2,FALSE()),"") | V4: =IFERROR(VLOOKUP(C4,Inventory!$A$2:$Y$35,22,FALSE()),"") | W4: =IFERROR(VLOOKUP(C4,Inventory!$A$2:$AB$35,25,FALSE()),"")
A5: =IF(C5="","",ROW()-3) | I5: =IFERROR(VLOOKUP(D5,PlatformFees,2,FALSE()),0) -> 0 | J5: =IFERROR(VLOOKUP(D5,PlatformFees,3,FALSE()),0) -> 0 | K5: =IF(ISNUMBER(F5),F5*I5+J5,0) -> 0 | N5: =IF(ISNUMBER(F5),F5+IFERROR(G5,0)-IFERROR(H5,0)-K5-IFERROR(L5,0)-IFERROR(M5,0),0) -> 0 | O5: =IFERROR(VLOOKUP(C5,Inventory!$A$2:$N$35,13,FALSE()),0) -> 0 | P5: =IF(ISNUMBER(F5),N5-O5,0) -> 0 | Q5: =IFERROR(IF(O5=0,0,P5/O5),0) -> 0 | R5: =IFERROR(IF(AND(ISNUMBER(B5),C5<>""),B5-VLOOKUP(C5,Inventory!$A$2:$AE$35,29,FALSE()),""),"") | S5: Gross Revenue | T5: =SUM(F4:F303) -> 0 | U5: =IFERROR(VLOOKUP(C5,Inventory!$A$2:$C$35,2,FALSE()),"") | V5: =IFERROR(VLOOKUP(C5,Inventory!$A$2:$Y$35,22,FALSE()),"") | W5: =IFERROR(VLOOKUP(C5,Inventory!$A$2:$AB$35,25,FALSE()),"")
A6: =IF(C6="","",ROW()-3) | I6: =IFERROR(VLOOKUP(D6,PlatformFees,2,FALSE()),0) -> 0 | J6: =IFERROR(VLOOKUP(D6,PlatformFees,3,FALSE()),0) -> 0 | K6: =IF(ISNUMBER(F6),F6*I6+J6,0) -> 0 | N6: =IF(ISNUMBER(F6),F6+IFERROR(G6,0)-IFERROR(H6,0)-K6-IFERROR(L6,0)-IFERROR(M6,0),0) -> 0 | O6: =IFERROR(VLOOKUP(C6,Inventory!$A$2:$N$35,13,FALSE()),0) -> 0 | P6: =IF(ISNUMBER(F6),N6-O6,0) -> 0 | Q6: =IFERROR(IF(O6=0,0,P6/O6),0) -> 0 | R6: =IFERROR(IF(AND(ISNUMBER(B6),C6<>""),B6-VLOOKUP(C6,Inventory!$A$2:$AE$35,29,FALSE()),""),"") | S6: Total Fees Paid | T6: =SUM(K4:K303)+SUM(L4:L303)+SUM(M4:M303) -> 0 | U6: =IFERROR(VLOOKUP(C6,Inventory!$A$2:$C$35,2,FALSE()),"") | V6: =IFERROR(VLOOKUP(C6,Inventory!$A$2:$Y$35,22,FALSE()),"") | W6: =IFERROR(VLOOKUP(C6,Inventory!$A$2:$AB$35,25,FALSE()),"")
A7: =IF(C7="","",ROW()-3) | I7: =IFERROR(VLOOKUP(D7,PlatformFees,2,FALSE()),0) -> 0 | J7: =IFERROR(VLOOKUP(D7,PlatformFees,3,FALSE()),0) -> 0 | K7: =IF(ISNUMBER(F7),F7*I7+J7,0) -> 0 | N7: =IF(ISNUMBER(F7),F7+IFERROR(G7,0)-IFERROR(H7,0)-K7-IFERROR(L7,0)-IFERROR(M7,0),0) -> 0 | O7: =IFERROR(VLOOKUP(C7,Inventory!$A$2:$N$35,13,FALSE()),0) -> 0 | P7: =IF(ISNUMBER(F7),N7-O7,0) -> 0 | Q7: =IFERROR(IF(O7=0,0,P7/O7),0) -> 0 | R7: =IFERROR(IF(AND(ISNUMBER(B7),C7<>""),B7-VLOOKUP(C7,Inventory!$A$2:$AE$35,29,FALSE()),""),"") | S7: Net Proceeds | T7: =SUM(N4:N303) -> 0 | U7: =IFERROR(VLOOKUP(C7,Inventory!$A$2:$C$35,2,FALSE()),"") | V7: =IFERROR(VLOOKUP(C7,Inventory!$A$2:$Y$35,22,FALSE()),"") | W7: =IFERROR(VLOOKUP(C7,Inventory!$A$2:$AB$35,25,FALSE()),"")
A8: =IF(C8="","",ROW()-3) | I8: =IFERROR(VLOOKUP(D8,PlatformFees,2,FALSE()),0) -> 0 | J8: =IFERROR(VLOOKUP(D8,PlatformFees,3,FALSE()),0) -> 0 | K8: =IF(ISNUMBER(F8),F8*I8+J8,0) -> 0 | N8: =IF(ISNUMBER(F8),F8+IFERROR(G8,0)-IFERROR(H8,0)-K8-IFERROR(L8,0)-IFERROR(M8,0),0) -> 0 | O8: =IFERROR(VLOOKUP(C8,Inventory!$A$2:$N$35,13,FALSE()),0) -> 0 | P8: =IF(ISNUMBER(F8),N8-O8,0) -> 0 | Q8: =IFERROR(IF(O8=0,0,P8/O8),0) -> 0 | R8: =IFERROR(IF(AND(ISNUMBER(B8),C8<>""),B8-VLOOKUP(C8,Inventory!$A$2:$AE$35,29,FALSE()),""),"") | S8: Total COGS (True Cost) | T8: =SUM(O4:O303) -> 0 | U8: =IFERROR(VLOOKUP(C8,Inventory!$A$2:$C$35,2,FALSE()),"") | V8: =IFERROR(VLOOKUP(C8,Inventory!$A$2:$Y$35,22,FALSE()),"") | W8: =IFERROR(VLOOKUP(C8,Inventory!$A$2:$AB$35,25,FALSE()),"")
A9: =IF(C9="","",ROW()-3) | I9: =IFERROR(VLOOKUP(D9,PlatformFees,2,FALSE()),0) -> 0 | J9: =IFERROR(VLOOKUP(D9,PlatformFees,3,FALSE()),0) -> 0 | K9: =IF(ISNUMBER(F9),F9*I9+J9,0) -> 0 | N9: =IF(ISNUMBER(F9),F9+IFERROR(G9,0)-IFERROR(H9,0)-K9-IFERROR(L9,0)-IFERROR(M9,0),0) -> 0 | O9: =IFERROR(VLOOKUP(C9,Inventory!$A$2:$N$35,13,FALSE()),0) -> 0 | P9: =IF(ISNUMBER(F9),N9-O9,0) -> 0 | Q9: =IFERROR(IF(O9=0,0,P9/O9),0) -> 0 | R9: =IFERROR(IF(AND(ISNUMBER(B9),C9<>""),B9-VLOOKUP(C9,Inventory!$A$2:$AE$35,29,FALSE()),""),"") | S9: Net Profit | T9: =SUM(P4:P303) -> 0 | U9: =IFERROR(VLOOKUP(C9,Inventory!$A$2:$C$35,2,FALSE()),"") | V9: =IFERROR(VLOOKUP(C9,Inventory!$A$2:$Y$35,22,FALSE()),"") | W9: =IFERROR(VLOOKUP(C9,Inventory!$A$2:$AB$35,25,FALSE()),"")
A10: =IF(C10="","",ROW()-3) | I10: =IFERROR(VLOOKUP(D10,PlatformFees,2,FALSE()),0) -> 0 | J10: =IFERROR(VLOOKUP(D10,PlatformFees,3,FALSE()),0) -> 0 | K10: =IF(ISNUMBER(F10),F10*I10+J10,0) -> 0 | N10: =IF(ISNUMBER(F10),F10+IFERROR(G10,0)-IFERROR(H10,0)-K10-IFERROR(L10,0)-IFERROR(M10,0),0) -> 0 | O10: =IFERROR(VLOOKUP(C10,Inventory!$A$2:$N$35,13,FALSE()),0) -> 0 | P10: =IF(ISNUMBER(F10),N10-O10,0) -> 0 | Q10: =IFERROR(IF(O10=0,0,P10/O10),0) -> 0 | R10: =IFERROR(IF(AND(ISNUMBER(B10),C10<>""),B10-VLOOKUP(C10,Inventory!$A$2:$AE$35,29,FALSE()),""),"") | S10: Avg Profit / Sale | T10: =IFERROR(SUM(P4:P303)/COUNT(P4:P303),0) -> 0 | U10: =IFERROR(VLOOKUP(C10,Inventory!$A$2:$C$35,2,FALSE()),"") | V10: =IFERROR(VLOOKUP(C10,Inventory!$A$2:$Y$35,22,FALSE()),"") | W10: =IFERROR(VLOOKUP(C10,Inventory!$A$2:$AB$35,25,FALSE()),"")
A11: =IF(C11="","",ROW()-3) | I11: =IFERROR(VLOOKUP(D11,PlatformFees,2,FALSE()),0) -> 0 | J11: =IFERROR(VLOOKUP(D11,PlatformFees,3,FALSE()),0) -> 0 | K11: =IF(ISNUMBER(F11),F11*I11+J11,0) -> 0 | N11: =IF(ISNUMBER(F11),F11+IFERROR(G11,0)-IFERROR(H11,0)-K11-IFERROR(L11,0)-IFERROR(M11,0),0) -> 0 | O11: =IFERROR(VLOOKUP(C11,Inventory!$A$2:$N$35,13,FALSE()),0) -> 0 | P11: =IF(ISNUMBER(F11),N11-O11,0) -> 0 | Q11: =IFERROR(IF(O11=0,0,P11/O11),0) -> 0 | R11: =IFERROR(IF(AND(ISNUMBER(B11),C11<>""),B11-VLOOKUP(C11,Inventory!$A$2:$AE$35,29,FALSE()),""),"") | S11: Blended ROI % | T11: =IFERROR(SUM(P4:P303)/SUM(O4:O303),0) -> 0 | U11: =IFERROR(VLOOKUP(C11,Inventory!$A$2:$C$35,2,FALSE()),"") | V11: =IFERROR(VLOOKUP(C11,Inventory!$A$2:$Y$35,22,FALSE()),"") | W11: =IFERROR(VLOOKUP(C11,Inventory!$A$2:$AB$35,25,FALSE()),"")
A12: =IF(C12="","",ROW()-3) | I12: =IFERROR(VLOOKUP(D12,PlatformFees,2,FALSE()),0) -> 0 | J12: =IFERROR(VLOOKUP(D12,PlatformFees,3,FALSE()),0) -> 0 | K12: =IF(ISNUMBER(F12),F12*I12+J12,0) -> 0 | N12: =IF(ISNUMBER(F12),F12+IFERROR(G12,0)-IFERROR(H12,0)-K12-IFERROR(L12,0)-IFERROR(M12,0),0) -> 0 | O12: =IFERROR(VLOOKUP(C12,Inventory!$A$2:$N$35,13,FALSE()),0) -> 0 | P12: =IF(ISNUMBER(F12),N12-O12,0) -> 0 | Q12: =IFERROR(IF(O12=0,0,P12/O12),0) -> 0 | R12: =IFERROR(IF(AND(ISNUMBER(B12),C12<>""),B12-VLOOKUP(C12,Inventory!$A$2:$AE$35,29,FALSE()),""),"") | S12: Avg Days to Sell | T12: =IFERROR(AVERAGE(R4:R303),0) -> 0 | U12: =IFERROR(VLOOKUP(C12,Inventory!$A$2:$C$35,2,FALSE()),"") | V12: =IFERROR(VLOOKUP(C12,Inventory!$A$2:$Y$35,22,FALSE()),"") | W12: =IFERROR(VLOOKUP(C12,Inventory!$A$2:$AB$35,25,FALSE()),"")
A13: =IF(C13="","",ROW()-3) | I13: =IFERROR(VLOOKUP(D13,PlatformFees,2,FALSE()),0) -> 0 | J13: =IFERROR(VLOOKUP(D13,PlatformFees,3,FALSE()),0) -> 0 | K13: =IF(ISNUMBER(F13),F13*I13+J13,0) -> 0 | N13: =IF(ISNUMBER(F13),F13+IFERROR(G13,0)-IFERROR(H13,0)-K13-IFERROR(L13,0)-IFERROR(M13,0),0) -> 0 | O13: =IFERROR(VLOOKUP(C13,Inventory!$A$2:$N$35,13,FALSE()),0) -> 0 | P13: =IF(ISNUMBER(F13),N13-O13,0) -> 0 | Q13: =IFERROR(IF(O13=0,0,P13/O13),0) -> 0 | R13: =IFERROR(IF(AND(ISNUMBER(B13),C13<>""),B13-VLOOKUP(C13,Inventory!$A$2:$AE$35,29,FALSE()),""),"") | U13: =IFERROR(VLOOKUP(C13,Inventory!$A$2:$C$35,2,FALSE()),"") | V13: =IFERROR(VLOOKUP(C13,Inventory!$A$2:$Y$35,22,FALSE()),"") | W13: =IFERROR(VLOOKUP(C13,Inventory!$A$2:$AB$35,25,FALSE()),"")
A14: =IF(C14="","",ROW()-3) | I14: =IFERROR(VLOOKUP(D14,PlatformFees,2,FALSE()),0) -> 0 | J14: =IFERROR(VLOOKUP(D14,PlatformFees,3,FALSE()),0) -> 0 | K14: =IF(ISNUMBER(F14),F14*I14+J14,0) -> 0 | N14: =IF(ISNUMBER(F14),F14+IFERROR(G14,0)-IFERROR(H14,0)-K14-IFERROR(L14,0)-IFERROR(M14,0),0) -> 0 | O14: =IFERROR(VLOOKUP(C14,Inventory!$A$2:$N$35,13,FALSE()),0) -> 0 | P14: =IF(ISNUMBER(F14),N14-O14,0) -> 0 | Q14: =IFERROR(IF(O14=0,0,P14/O14),0) -> 0 | R14: =IFERROR(IF(AND(ISNUMBER(B14),C14<>""),B14-VLOOKUP(C14,Inventory!$A$2:$AE$35,29,FALSE()),""),"") | U14: =IFERROR(VLOOKUP(C14,Inventory!$A$2:$C$35,2,FALSE()),"") | V14: =IFERROR(VLOOKUP(C14,Inventory!$A$2:$Y$35,22,FALSE()),"") | W14: =IFERROR(VLOOKUP(C14,Inventory!$A$2:$AB$35,25,FALSE()),"")
A15: =IF(C15="","",ROW()-3) | I15: =IFERROR(VLOOKUP(D15,PlatformFees,2,FALSE()),0) -> 0 | J15: =IFERROR(VLOOKUP(D15,PlatformFees,3,FALSE()),0) -> 0 | K15: =IF(ISNUMBER(F15),F15*I15+J15,0) -> 0 | N15: =IF(ISNUMBER(F15),F15+IFERROR(G15,0)-IFERROR(H15,0)-K15-IFERROR(L15,0)-IFERROR(M15,0),0) -> 0 | O15: =IFERROR(VLOOKUP(C15,Inventory!$A$2:$N$35,13,FALSE()),0) -> 0 | P15: =IF(ISNUMBER(F15),N15-O15,0) -> 0 | Q15: =IFERROR(IF(O15=0,0,P15/O15),0) -> 0 | R15: =IFERROR(IF(AND(ISNUMBER(B15),C15<>""),B15-VLOOKUP(C15,Inventory!$A$2:$AE$35,29,FALSE()),""),"") | U15: =IFERROR(VLOOKUP(C15,Inventory!$A$2:$C$35,2,FALSE()),"") | V15: =IFERROR(VLOOKUP(C15,Inventory!$A$2:$Y$35,22,FALSE()),"") | W15: =IFERROR(VLOOKUP(C15,Inventory!$A$2:$AB$35,25,FALSE()),"")
A16: =IF(C16="","",ROW()-3) | I16: =IFERROR(VLOOKUP(D16,PlatformFees,2,FALSE()),0) -> 0 | J16: =IFERROR(VLOOKUP(D16,PlatformFees,3,FALSE()),0) -> 0 | K16: =IF(ISNUMBER(F16),F16*I16+J16,0) -> 0 | N16: =IF(ISNUMBER(F16),F16+IFERROR(G16,0)-IFERROR(H16,0)-K16-IFERROR(L16,0)-IFERROR(M16,0),0) -> 0 | O16: =IFERROR(VLOOKUP(C16,Inventory!$A$2:$N$35,13,FALSE()),0) -> 0 | P16: =IF(ISNUMBER(F16),N16-O16,0) -> 0 | Q16: =IFERROR(IF(O16=0,0,P16/O16),0) -> 0 | R16: =IFERROR(IF(AND(ISNUMBER(B16),C16<>""),B16-VLOOKUP(C16,Inventory!$A$2:$AE$35,29,FALSE()),""),"") | U16: =IFERROR(VLOOKUP(C16,Inventory!$A$2:$C$35,2,FALSE()),"") | V16: =IFERROR(VLOOKUP(C16,Inventory!$A$2:$Y$35,22,FALSE()),"") | W16: =IFERROR(VLOOKUP(C16,Inventory!$A$2:$AB$35,25,FALSE()),"")
A17: =IF(C17="","",ROW()-3) | I17: =IFERROR(VLOOKUP(D17,PlatformFees,2,FALSE()),0) -> 0 | J17: =IFERROR(VLOOKUP(D17,PlatformFees,3,FALSE()),0) -> 0 | K17: =IF(ISNUMBER(F17),F17*I17+J17,0) -> 0 | N17: =IF(ISNUMBER(F17),F17+IFERROR(G17,0)-IFERROR(H17,0)-K17-IFERROR(L17,0)-IFERROR(M17,0),0) -> 0 | O17: =IFERROR(VLOOKUP(C17,Inventory!$A$2:$N$35,13,FALSE()),0) -> 0 | P17: =IF(ISNUMBER(F17),N17-O17,0) -> 0 | Q17: =IFERROR(IF(O17=0,0,P17/O17),0) -> 0 | R17: =IFERROR(IF(AND(ISNUMBER(B17),C17<>""),B17-VLOOKUP(C17,Inventory!$A$2:$AE$35,29,FALSE()),""),"") | U17: =IFERROR(VLOOKUP(C17,Inventory!$A$2:$C$35,2,FALSE()),"") | V17: =IFERROR(VLOOKUP(C17,Inventory!$A$2:$Y$35,22,FALSE()),"") | W17: =IFERROR(VLOOKUP(C17,Inventory!$A$2:$AB$35,25,FALSE()),"")
A18: =IF(C18="","",ROW()-3) | I18: =IFERROR(VLOOKUP(D18,PlatformFees,2,FALSE()),0) -> 0 | J18: =IFERROR(VLOOKUP(D18,PlatformFees,3,FALSE()),0) -> 0 | K18: =IF(ISNUMBER(F18),F18*I18+J18,0) -> 0 | N18: =IF(ISNUMBER(F18),F18+IFERROR(G18,0)-IFERROR(H18,0)-K18-IFERROR(L18,0)-IFERROR(M18,0),0) -> 0 | O18: =IFERROR(VLOOKUP(C18,Inventory!$A$2:$N$35,13,FALSE()),0) -> 0 | P18: =IF(ISNUMBER(F18),N18-O18,0) -> 0 | Q18: =IFERROR(IF(O18=0,0,P18/O18),0) -> 0 | R18: =IFERROR(IF(AND(ISNUMBER(B18),C18<>""),B18-VLOOKUP(C18,Inventory!$A$2:$AE$35,29,FALSE()),""),"") | U18: =IFERROR(VLOOKUP(C18,Inventory!$A$2:$C$35,2,FALSE()),"") | V18: =IFERROR(VLOOKUP(C18,Inventory!$A$2:$Y$35,22,FALSE()),"") | W18: =IFERROR(VLOOKUP(C18,Inventory!$A$2:$AB$35,25,FALSE()),"")
A19: =IF(C19="","",ROW()-3) | I19: =IFERROR(VLOOKUP(D19,PlatformFees,2,FALSE()),0) -> 0 | J19: =IFERROR(VLOOKUP(D19,PlatformFees,3,FALSE()),0) -> 0 | K19: =IF(ISNUMBER(F19),F19*I19+J19,0) -> 0 | N19: =IF(ISNUMBER(F19),F19+IFERROR(G19,0)-IFERROR(H19,0)-K19-IFERROR(L19,0)-IFERROR(M19,0),0) -> 0 | O19: =IFERROR(VLOOKUP(C19,Inventory!$A$2:$N$35,13,FALSE()),0) -> 0 | P19: =IF(ISNUMBER(F19),N19-O19,0) -> 0 | Q19: =IFERROR(IF(O19=0,0,P19/O19),0) -> 0 | R19: =IFERROR(IF(AND(ISNUMBER(B19),C19<>""),B19-VLOOKUP(C19,Inventory!$A$2:$AE$35,29,FALSE()),""),"") | U19: =IFERROR(VLOOKUP(C19,Inventory!$A$2:$C$35,2,FALSE()),"") | V19: =IFERROR(VLOOKUP(C19,Inventory!$A$2:$Y$35,22,FALSE()),"") | W19: =IFERROR(VLOOKUP(C19,Inventory!$A$2:$AB$35,25,FALSE()),"")
A20: =IF(C20="","",ROW()-3) | I20: =IFERROR(VLOOKUP(D20,PlatformFees,2,FALSE()),0) -> 0 | J20: =IFERROR(VLOOKUP(D20,PlatformFees,3,FALSE()),0) -> 0 | K20: =IF(ISNUMBER(F20),F20*I20+J20,0) -> 0 | N20: =IF(ISNUMBER(F20),F20+IFERROR(G20,0)-IFERROR(H20,0)-K20-IFERROR(L20,0)-IFERROR(M20,0),0) -> 0 | O20: =IFERROR(VLOOKUP(C20,Inventory!$A$2:$N$35,13,FALSE()),0) -> 0 | P20: =IF(ISNUMBER(F20),N20-O20,0) -> 0 | Q20: =IFERROR(IF(O20=0,0,P20/O20),0) -> 0 | R20: =IFERROR(IF(AND(ISNUMBER(B20),C20<>""),B20-VLOOKUP(C20,Inventory!$A$2:$AE$35,29,FALSE()),""),"") | U20: =IFERROR(VLOOKUP(C20,Inventory!$A$2:$C$35,2,FALSE()),"") | V20: =IFERROR(VLOOKUP(C20,Inventory!$A$2:$Y$35,22,FALSE()),"") | W20: =IFERROR(VLOOKUP(C20,Inventory!$A$2:$AB$35,25,FALSE()),"")
A21: =IF(C21="","",ROW()-3) | I21: =IFERROR(VLOOKUP(D21,PlatformFees,2,FALSE()),0) -> 0 | J21: =IFERROR(VLOOKUP(D21,PlatformFees,3,FALSE()),0) -> 0 | K21: =IF(ISNUMBER(F21),F21*I21+J21,0) -> 0 | N21: =IF(ISNUMBER(F21),F21+IFERROR(G21,0)-IFERROR(H21,0)-K21-IFERROR(L21,0)-IFERROR(M21,0),0) -> 0 | O21: =IFERROR(VLOOKUP(C21,Inventory!$A$2:$N$35,13,FALSE()),0) -> 0 | P21: =IF(ISNUMBER(F21),N21-O21,0) -> 0 | Q21: =IFERROR(IF(O21=0,0,P21/O21),0) -> 0 | R21: =IFERROR(IF(AND(ISNUMBER(B21),C21<>""),B21-VLOOKUP(C21,Inventory!$A$2:$AE$35,29,FALSE()),""),"") | U21: =IFERROR(VLOOKUP(C21,Inventory!$A$2:$C$35,2,FALSE()),"") | V21: =IFERROR(VLOOKUP(C21,Inventory!$A$2:$Y$35,22,FALSE()),"") | W21: =IFERROR(VLOOKUP(C21,Inventory!$A$2:$AB$35,25,FALSE()),"")
A22: =IF(C22="","",ROW()-3) | I22: =IFERROR(VLOOKUP(D22,PlatformFees,2,FALSE()),0) -> 0 | J22: =IFERROR(VLOOKUP(D22,PlatformFees,3,FALSE()),0) -> 0 | K22: =IF(ISNUMBER(F22),F22*I22+J22,0) -> 0 | N22: =IF(ISNUMBER(F22),F22+IFERROR(G22,0)-IFERROR(H22,0)-K22-IFERROR(L22,0)-IFERROR(M22,0),0) -> 0 | O22: =IFERROR(VLOOKUP(C22,Inventory!$A$2:$N$35,13,FALSE()),0) -> 0 | P22: =IF(ISNUMBER(F22),N22-O22,0) -> 0 | Q22: =IFERROR(IF(O22=0,0,P22/O22),0) -> 0 | R22: =IFERROR(IF(AND(ISNUMBER(B22),C22<>""),B22-VLOOKUP(C22,Inventory!$A$2:$AE$35,29,FALSE()),""),"") | U22: =IFERROR(VLOOKUP(C22,Inventory!$A$2:$C$35,2,FALSE()),"") | V22: =IFERROR(VLOOKUP(C22,Inventory!$A$2:$Y$35,22,FALSE()),"") | W22: =IFERROR(VLOOKUP(C22,Inventory!$A$2:$AB$35,25,FALSE()),"")
A23: =IF(C23="","",ROW()-3) | I23: =IFERROR(VLOOKUP(D23,PlatformFees,2,FALSE()),0) -> 0 | J23: =IFERROR(VLOOKUP(D23,PlatformFees,3,FALSE()),0) -> 0 | K23: =IF(ISNUMBER(F23),F23*I23+J23,0) -> 0 | N23: =IF(ISNUMBER(F23),F23+IFERROR(G23,0)-IFERROR(H23,0)-K23-IFERROR(L23,0)-IFERROR(M23,0),0) -> 0 | O23: =IFERROR(VLOOKUP(C23,Inventory!$A$2:$N$35,13,FALSE()),0) -> 0 | P23: =IF(ISNUMBER(F23),N23-O23,0) -> 0 | Q23: =IFERROR(IF(O23=0,0,P23/O23),0) -> 0 | R23: =IFERROR(IF(AND(ISNUMBER(B23),C23<>""),B23-VLOOKUP(C23,Inventory!$A$2:$AE$35,29,FALSE()),""),"") | U23: =IFERROR(VLOOKUP(C23,Inventory!$A$2:$C$35,2,FALSE()),"") | V23: =IFERROR(VLOOKUP(C23,Inventory!$A$2:$Y$35,22,FALSE()),"") | W23: =IFERROR(VLOOKUP(C23,Inventory!$A$2:$AB$35,25,FALSE()),"")
A24: =IF(C24="","",ROW()-3) | I24: =IFERROR(VLOOKUP(D24,PlatformFees,2,FALSE()),0) -> 0 | J24: =IFERROR(VLOOKUP(D24,PlatformFees,3,FALSE()),0) -> 0 | K24: =IF(ISNUMBER(F24),F24*I24+J24,0) -> 0 | N24: =IF(ISNUMBER(F24),F24+IFERROR(G24,0)-IFERROR(H24,0)-K24-IFERROR(L24,0)-IFERROR(M24,0),0) -> 0 | O24: =IFERROR(VLOOKUP(C24,Inventory!$A$2:$N$35,13,FALSE()),0) -> 0 | P24: =IF(ISNUMBER(F24),N24-O24,0) -> 0 | Q24: =IFERROR(IF(O24=0,0,P24/O24),0) -> 0 | R24: =IFERROR(IF(AND(ISNUMBER(B24),C24<>""),B24-VLOOKUP(C24,Inventory!$A$2:$AE$35,29,FALSE()),""),"") | U24: =IFERROR(VLOOKUP(C24,Inventory!$A$2:$C$35,2,FALSE()),"") | V24: =IFERROR(VLOOKUP(C24,Inventory!$A$2:$Y$35,22,FALSE()),"") | W24: =IFERROR(VLOOKUP(C24,Inventory!$A$2:$AB$35,25,FALSE()),"")
... A303: =IF(C303="","",ROW()-3) | I303: =IFERROR(VLOOKUP(D303,PlatformFees,2,FALSE()),0) -> 0 | J303: =IFERROR(VLOOKUP(D303,PlatformFees,3,FALSE()),0) -> 0 | K303: =IF(ISNUMBER(F303),F303*I303+J303,0) -> 0 | N303: =IF(ISNUMBER(F303),F303+IFERROR(G303,0)-IFERROR(H303,0)-K303-IFERROR(L303,0)-IFERROR(M303,0),0) -> 0 | O303: =IFERROR(VLOOKUP(C303,Inventory!$A$2:$N$35,13,FALSE()),0) -> 0 | P303: =IF(ISNUMBER(F303),N303-O303,0) -> 0 | Q303: =IFERROR(IF(O303=0,0,P303/O303),0) -> 0 | R303: =IFERROR(IF(AND(ISNUMBER(B303),C303<>""),B303-VLOOKUP(C303,Inventory!$A$2:$AE$35,29,FALSE()),""),"") | U303: =IFERROR(VLOOKUP(C303,Inventory!$A$2:$C$35,2,FALSE()),"") | V303: =IFERROR(VLOOKUP(C303,Inventory!$A$2:$Y$35,22,FALSE()),"") | W303: =IFERROR(VLOOKUP(C303,Inventory!$A$2:$AB$35,25,FALSE()),"")

Sheet Pricing Intelligence
A1: PRICING INTELLIGENCE — LIVE eBay COMPS
A2: Use the "Refresh Live Comps" instructions in the yellow box to set up Power Query. Each item has a clickable "Sold Comps" URL that opens eBay Sold Listings. Once Power Query is wired, the Live Avg / Live High / Live Low columns auto-populate on refresh.
A4: Item Name | B4: Category | C4: True Cost | D4: Min Sell Price | E4: Manual Comp #1 | F4: Manual Comp #2 | G4: Manual Comp #3 | H4: Manual Avg | I4: Live Avg (eBay) | J4: Recommended List Price | K4: Sold Comps Link
A5: =Inventory!A2 -> Shawn Kemp Signed 1990-91 Hoops #279 RC (JSA) | B5: =Inventory!Y2 -> Card | C5: =Inventory!N2 -> 16.254971 | D5: =Inventory!T2 -> 26.799735 | E5: 59 | F5: 39 | G5: 55.99 | H5: =IFERROR(AVERAGE(E5:G5),0) -> 51.33 | J5: =MAX(IF(AND(I5<>"",I5>0),I5,IF(AND(H5<>"",H5>0),H5,D5*1.2)),D5*1.2) -> 51.33 | K5: =HYPERLINK("https://www.ebay.com/sch/i.html?_nkw="&SUBSTITUTE(SUBSTITUTE(A5," ","+"),"""","")&"&LH_Sold=1&LH_Complete=1&_sop=13","🔗 View Sold Comps") -> 🔗 View Sold Comps
A6: =Inventory!A3 -> Mark Henn Signed "The Lion King" 8x10 Photo (Beckett) | B6: =Inventory!Y3 -> Photo | C6: =Inventory!N3 -> 17.029017 | D6: =Inventory!T3 -> 29.396827 | H6: =IFERROR(AVERAGE(E6:G6),0) -> 0 | J6: =MAX(IF(AND(I6<>"",I6>0),I6,IF(AND(H6<>"",H6>0),H6,D6*1.2)),D6*1.2) -> 35.276193 | K6: =HYPERLINK("https://www.ebay.com/sch/i.html?_nkw="&SUBSTITUTE(SUBSTITUTE(A6," ","+"),"""","")&"&LH_Sold=1&LH_Complete=1&_sop=13","🔗 View Sold Comps") -> 🔗 View Sold Comps
A7: =Inventory!A4 -> Ari Lehman Signed "Friday the 13th" Jason Voorhees Mask Inscribed "Jason 1" (Beckett) | B7: =Inventory!Y4 -> Mask | C7: =Inventory!N4 -> 55.90334 | D7: =Inventory!T4 -> 74.41154 | E7: 29.99 | F7: 27 | G7: 32.99 | H7: =IFERROR(AVERAGE(E7:G7),0) -> 29.993333 | J7: =MAX(IF(AND(I7<>"",I7>0),I7,IF(AND(H7<>"",H7>0),H7,D7*1.2)),D7*1.2) -> 89.293848 | K7: =HYPERLINK("https://www.ebay.com/sch/i.html?_nkw="&SUBSTITUTE(SUBSTITUTE(A7," ","+"),"""","")&"&LH_Sold=1&LH_Complete=1&_sop=13","🔗 View Sold Comps") -> 🔗 View Sold Comps
A8: =Inventory!A5 -> Shawn Kemp Signed Jersey (JSA) | B8: =Inventory!Y5 -> Jersey | C8: =Inventory!N5 -> 44.722672 | D8: =Inventory!T5 -> 59.748463 | E8: 39 | F8: 39 | G8: 39 | H8: =IFERROR(AVERAGE(E8:G8),0) -> 39 | J8: =MAX(IF(AND(I8<>"",I8>0),I8,IF(AND(H8<>"",H8>0),H8,D8*1.2)),D8*1.2) -> 71.698155 | K8: =HYPERLINK("https://www.ebay.com/sch/i.html?_nkw="&SUBSTITUTE(SUBSTITUTE(A8," ","+"),"""","")&"&LH_Sold=1&LH_Complete=1&_sop=13","🔗 View Sold Comps") -> 🔗 View Sold Comps
A9: =Inventory!A6 -> Cheech Marin & Tommy Chong Signed "The Simpsons" 8x10 Photo (JSA) | B9: =Inventory!Y6 -> Photo | C9: =Inventory!N6 -> 16.335405 | D9: =Inventory!T6 -> 26.892829 | E9: 64.95 | F9: 55 | G9: 60 | H9: =IFERROR(AVERAGE(E9:G9),0) -> 59.983333 | J9: =MAX(IF(AND(I9<>"",I9>0),I9,IF(AND(H9<>"",H9>0),H9,D9*1.2)),D9*1.2) -> 59.983333 | K9: =HYPERLINK("https://www.ebay.com/sch/i.html?_nkw="&SUBSTITUTE(SUBSTITUTE(A9," ","+"),"""","")&"&LH_Sold=1&LH_Complete=1&_sop=13","🔗 View Sold Comps") -> 🔗 View Sold Comps
A10: =Inventory!A7 -> Chris Cooper Signed "Cars 3" 8x10 Photo Inscribed "AKA 'Smokey'" & "Best Wishes" (ACOA) | B10: =Inventory!Y7 -> Photo | C10: =Inventory!N7 -> 8.3500309 | D10: =Inventory!T7 -> 18.734682 | E10: 19.95 | F10: 24.99 | H10: =IFERROR(AVERAGE(E10:G10),0) -> 22.47 | J10: =MAX(IF(AND(I10<>"",I10>0),I10,IF(AND(H10<>"",H10>0),H10,D10*1.2)),D10*1.2) -> 22.481618 | K10: =HYPERLINK("https://www.ebay.com/sch/i.html?_nkw="&SUBSTITUTE(SUBSTITUTE(A10," ","+"),"""","")&"&LH_Sold=1&LH_Complete=1&_sop=13","🔗 View Sold Comps") -> 🔗 View Sold Comps
A11: =Inventory!A8 -> Frank Thomas Signed OML Baseball (JSA) | B11: =Inventory!Y8 -> Baseball | C11: =Inventory!N8 -> 27.324564 | D11: =Inventory!T8 -> 39.611764 | E11: 37 | F11: 42 | G11: 46 | H11: =IFERROR(AVERAGE(E11:G11),0) -> 41.666667 | J11: =MAX(IF(AND(I11<>"",I11>0),I11,IF(AND(H11<>"",H11>0),H11,D11*1.2)),D11*1.2) -> 47.534117 | K11: =HYPERLINK("https://www.ebay.com/sch/i.html?_nkw="&SUBSTITUTE(SUBSTITUTE(A11," ","+"),"""","")&"&LH_Sold=1&LH_Complete=1&_sop=13","🔗 View Sold Comps") -> 🔗 View Sold Comps
A12: =Inventory!A9 -> Jimbo Covert Signed NFL Football Inscribed "SB XX Champs" (JSA) | B12: =Inventory!Y9 -> Football | C12: =Inventory!N9 -> 35.68 | D12: =Inventory!T9 -> 51.055156 | E12: 99 | F12: 109 | G12: 125 | H12: =IFERROR(AVERAGE(E12:G12),0) -> 111 | J12: =MAX(IF(AND(I12<>"",I12>0),I12,IF(AND(H12<>"",H12>0),H12,D12*1.2)),D12*1.2) -> 111 | K12: =HYPERLINK("https://www.ebay.com/sch/i.html?_nkw="&SUBSTITUTE(SUBSTITUTE(A12," ","+"),"""","")&"&LH_Sold=1&LH_Complete=1&_sop=13","🔗 View Sold Comps") -> 🔗 View Sold Comps
A13: =Inventory!A10 -> Moisés Ballesteros Signed OML Baseball (Beckett) | B13: =Inventory!Y10 -> Baseball | C13: =Inventory!N10 -> 31.389175 | D13: =Inventory!T10 -> 44.316175 | E13: 64.99 | H13: =IFERROR(AVERAGE(E13:G13),0) -> 64.99 | J13: =MAX(IF(AND(I13<>"",I13>0),I13,IF(AND(H13<>"",H13>0),H13,D13*1.2)),D13*1.2) -> 64.99 | K13: =HYPERLINK("https://www.ebay.com/sch/i.html?_nkw="&SUBSTITUTE(SUBSTITUTE(A13," ","+"),"""","")&"&LH_Sold=1&LH_Complete=1&_sop=13","🔗 View Sold Comps") -> 🔗 View Sold Comps
A14: =Inventory!A11 -> Moisés Ballesteros Signed Jersey Inscribed "Mo Baller" (Beckett) | B14: =Inventory!Y11 -> Jersey | C14: =Inventory!N11 -> 31.389175 | D14: =Inventory!T11 -> 44.316175 | E14: 129 | F14: 70 | H14: =IFERROR(AVERAGE(E14:G14),0) -> 99.5 | J14: =MAX(IF(AND(I14<>"",I14>0),I14,IF(AND(H14<>"",H14>0),H14,D14*1.2)),D14*1.2) -> 99.5 | K14: =HYPERLINK("https://www.ebay.com/sch/i.html?_nkw="&SUBSTITUTE(SUBSTITUTE(A14," ","+"),"""","")&"&LH_Sold=1&LH_Complete=1&_sop=13","🔗 View Sold Comps") -> 🔗 View Sold Comps
A15: =Inventory!A12 -> Moisés Ballesteros Signed Louisville Slugger Baseball Bat (Beckett) | B15: =Inventory!Y12 -> Bat | C15: =Inventory!N12 -> 31.389175 | D15: =Inventory!T12 -> 44.316175 | E15: 119 | F15: 129.99 | G15: 119.99 | H15: =IFERROR(AVERAGE(E15:G15),0) -> 122.99333 | J15: =MAX(IF(AND(I15<>"",I15>0),I15,IF(AND(H15<>"",H15>0),H15,D15*1.2)),D15*1.2) -> 122.99333 | K15: =HYPERLINK("https://www.ebay.com/sch/i.html?_nkw="&SUBSTITUTE(SUBSTITUTE(A15," ","+"),"""","")&"&LH_Sold=1&LH_Complete=1&_sop=13","🔗 View Sold Comps") -> 🔗 View Sold Comps
A16: =Inventory!A13 -> Moisés Ballesteros Signed Jersey (Beckett) | B16: =Inventory!Y13 -> Jersey | C16: =Inventory!N13 -> 31.389175 | D16: =Inventory!T13 -> 44.316175 | E16: 129 | F16: 70 | H16: =IFERROR(AVERAGE(E16:G16),0) -> 99.5 | J16: =MAX(IF(AND(I16<>"",I16>0),I16,IF(AND(H16<>"",H16>0),H16,D16*1.2)),D16*1.2) -> 99.5 | K16: =HYPERLINK("https://www.ebay.com/sch/i.html?_nkw="&SUBSTITUTE(SUBSTITUTE(A16," ","+"),"""","")&"&LH_Sold=1&LH_Complete=1&_sop=13","🔗 View Sold Comps") -> 🔗 View Sold Comps
A17: =Inventory!A14 -> Sammy Sosa Signed Louisville Slugger Baseball Bat (Beckett) | B17: =Inventory!Y14 -> Bat | C17: =Inventory!N14 -> 39.246051 | D17: =Inventory!T14 -> 53.409781 | E17: 109 | F17: 82 | G17: 129 | H17: =IFERROR(AVERAGE(E17:G17),0) -> 106.66667 | J17: =MAX(IF(AND(I17<>"",I17>0),I17,IF(AND(H17<>"",H17>0),H17,D17*1.2)),D17*1.2) -> 106.66667 | K17: =HYPERLINK("https://www.ebay.com/sch/i.html?_nkw="&SUBSTITUTE(SUBSTITUTE(A17," ","+"),"""","")&"&LH_Sold=1&LH_Complete=1&_sop=13","🔗 View Sold Comps") -> 🔗 View Sold Comps
A18: =Inventory!A15 -> Sammy Sosa Signed Louisville Slugger Baseball Bat (JSA) | B18: =Inventory!Y15 -> Bat | C18: =Inventory!N15 -> 39.246051 | D18: =Inventory!T15 -> 53.409781 | E18: 129 | F18: 86 | G18: 109 | H18: =IFERROR(AVERAGE(E18:G18),0) -> 108 | J18: =MAX(IF(AND(I18<>"",I18>0),I18,IF(AND(H18<>"",H18>0),H18,D18*1.2)),D18*1.2) -> 108 | K18: =HYPERLINK("https://www.ebay.com/sch/i.html?_nkw="&SUBSTITUTE(SUBSTITUTE(A18," ","+"),"""","")&"&LH_Sold=1&LH_Complete=1&_sop=13","🔗 View Sold Comps") -> 🔗 View Sold Comps
A19: =Inventory!A16 -> Sammy Sosa Signed Jersey (JSA) | B19: =Inventory!Y16 -> Jersey | C19: =Inventory!N16 -> 33.829278 | D19: =Inventory!T16 -> 47.140368 | E19: 80 | F19: 60 | G19: 63 | H19: =IFERROR(AVERAGE(E19:G19),0) -> 67.666667 | J19: =MAX(IF(AND(I19<>"",I19>0),I19,IF(AND(H19<>"",H19>0),H19,D19*1.2)),D19*1.2) -> 67.666667 | K19: =HYPERLINK("https://www.ebay.com/sch/i.html?_nkw="&SUBSTITUTE(SUBSTITUTE(A19," ","+"),"""","")&"&LH_Sold=1&LH_Complete=1&_sop=13","🔗 View Sold Comps") -> 🔗 View Sold Comps
A20: =Inventory!A17 -> Sammy Sosa Signed Jersey (JSA) | B20: =Inventory!Y17 -> Jersey | C20: =Inventory!N17 -> 43.704668 | D20: =Inventory!T17 -> 58.570218 | E20: 80 | F20: 60 | G20: 63 | H20: =IFERROR(AVERAGE(E20:G20),0) -> 67.666667 | J20: =MAX(IF(AND(I20<>"",I20>0),I20,IF(AND(H20<>"",H20>0),H20,D20*1.2)),D20*1.2) -> 70.284261 | K20: =HYPERLINK("https://www.ebay.com/sch/i.html?_nkw="&SUBSTITUTE(SUBSTITUTE(A20," ","+"),"""","")&"&LH_Sold=1&LH_Complete=1&_sop=13","🔗 View Sold Comps") -> 🔗 View Sold Comps
A21: =Inventory!A18 -> Sammy Sosa Signed Louisville Slugger Baseball Bat (Beckett) | B21: =Inventory!Y18 -> Bat | C21: =Inventory!N18 -> 43.75577 | D21: =Inventory!T18 -> 58.629363 | E21: 109 | F21: 82 | G21: 129 | H21: =IFERROR(AVERAGE(E21:G21),0) -> 106.66667 | J21: =MAX(IF(AND(I21<>"",I21>0),I21,IF(AND(H21<>"",H21>0),H21,D21*1.2)),D21*1.2) -> 106.66667 | K21: =HYPERLINK("https://www.ebay.com/sch/i.html?_nkw="&SUBSTITUTE(SUBSTITUTE(A21," ","+"),"""","")&"&LH_Sold=1&LH_Complete=1&_sop=13","🔗 View Sold Comps") -> 🔗 View Sold Comps
A22: =Inventory!A19 -> Donte DiVincenzo Signed Jersey (Beckett) | B22: =Inventory!Y19 -> Jersey | C22: =Inventory!N19 -> 23.545075 | D22: =Inventory!T19 -> 35.237356 | H22: =IFERROR(AVERAGE(E22:G22),0) -> 0 | J22: =MAX(IF(AND(I22<>"",I22>0),I22,IF(AND(H22<>"",H22>0),H22,D22*1.2)),D22*1.2) -> 42.284827 | K22: =HYPERLINK("https://www.ebay.com/sch/i.html?_nkw="&SUBSTITUTE(SUBSTITUTE(A22," ","+"),"""","")&"&LH_Sold=1&LH_Complete=1&_sop=13","🔗 View Sold Comps") -> 🔗 View Sold Comps
A23: =Inventory!A20 -> Derek Harper Signed Jersey (JSA) | B23: =Inventory!Y20 -> Jersey | C23: =Inventory!N20 -> 31.389175 | D23: =Inventory!T20 -> 44.316175 | H23: =IFERROR(AVERAGE(E23:G23),0) -> 0 | J23: =MAX(IF(AND(I23<>"",I23>0),I23,IF(AND(H23<>"",H23>0),H23,D23*1.2)),D23*1.2) -> 53.17941 | K23: =HYPERLINK("https://www.ebay.com/sch/i.html?_nkw="&SUBSTITUTE(SUBSTITUTE(A23," ","+"),"""","")&"&LH_Sold=1&LH_Complete=1&_sop=13","🔗 View Sold Comps") -> 🔗 View Sold Comps
A24: =Inventory!A21 -> Jamal Anderson Signed Jersey (JSA) | B24: =Inventory!Y21 -> Jersey | C24: =Inventory!N21 -> 24.413803 | D24: =Inventory!T21 -> 36.242828 | H24: =IFERROR(AVERAGE(E24:G24),0) -> 0 | J24: =MAX(IF(AND(I24<>"",I24>0),I24,IF(AND(H24<>"",H24>0),H24,D24*1.2)),D24*1.2) -> 43.491393 | K24: =HYPERLINK("https://www.ebay.com/sch/i.html?_nkw="&SUBSTITUTE(SUBSTITUTE(A24," ","+"),"""","")&"&LH_Sold=1&LH_Complete=1&_sop=13","🔗 View Sold Comps") -> 🔗 View Sold Comps
A25: =Inventory!A22 -> Kyle Tucker Signed Jersey (JSA) | B25: =Inventory!Y22 -> Jersey | C25: =Inventory!N22 -> 31.389175 | D25: =Inventory!T22 -> 44.316175 | H25: =IFERROR(AVERAGE(E25:G25),0) -> 0 | J25: =MAX(IF(AND(I25<>"",I25>0),I25,IF(AND(H25<>"",H25>0),H25,D25*1.2)),D25*1.2) -> 53.17941 | K25: =HYPERLINK("https://www.ebay.com/sch/i.html?_nkw="&SUBSTITUTE(SUBSTITUTE(A25," ","+"),"""","")&"&LH_Sold=1&LH_Complete=1&_sop=13","🔗 View Sold Comps") -> 🔗 View Sold Comps
A26: =Inventory!A23 -> Steve Spurrier Signed Florida Gators 8x10 Photo Inscribed "Go Gators" (ACOA) | B26: =Inventory!Y23 -> Photo | C26: =Inventory!N23 -> 54.934251 | D26: =Inventory!T23 -> 71.56742 | H26: =IFERROR(AVERAGE(E26:G26),0) -> 0 | J26: =MAX(IF(AND(I26<>"",I26>0),I26,IF(AND(H26<>"",H26>0),H26,D26*1.2)),D26*1.2) -> 85.880904 | K26: =HYPERLINK("https://www.ebay.com/sch/i.html?_nkw="&SUBSTITUTE(SUBSTITUTE(A26," ","+"),"""","")&"&LH_Sold=1&LH_Complete=1&_sop=13","🔗 View Sold Comps") -> 🔗 View Sold Comps
A27: =Inventory!A24 -> Joe Johnson Signed Jersey (Beckett) | B27: =Inventory!Y24 -> Jersey | C27: =Inventory!N24 -> 4.37 | D27: =Inventory!T24 -> 13.043981 | H27: =IFERROR(AVERAGE(E27:G27),0) -> 0 | J27: =MAX(IF(AND(I27<>"",I27>0),I27,IF(AND(H27<>"",H27>0),H27,D27*1.2)),D27*1.2) -> 15.652778 | K27: =HYPERLINK("https://www.ebay.com/sch/i.html?_nkw="&SUBSTITUTE(SUBSTITUTE(A27," ","+"),"""","")&"&LH_Sold=1&LH_Complete=1&_sop=13","🔗 View Sold Comps") -> 🔗 View Sold Comps
A28: =Inventory!A25 -> Xavier Watts Signed Jersey (JSA) | B28: =Inventory!Y25 -> Jersey | C28: =Inventory!N25 -> 37.111781 | D28: =Inventory!T25 -> 50.939562 | H28: =IFERROR(AVERAGE(E28:G28),0) -> 0 | J28: =MAX(IF(AND(I28<>"",I28>0),I28,IF(AND(H28<>"",H28>0),H28,D28*1.2)),D28*1.2) -> 61.127474 | K28: =HYPERLINK("https://www.ebay.com/sch/i.html?_nkw="&SUBSTITUTE(SUBSTITUTE(A28," ","+"),"""","")&"&LH_Sold=1&LH_Complete=1&_sop=13","🔗 View Sold Comps") -> 🔗 View Sold Comps
A29: =Inventory!A26 -> Xavier Watts Signed Jersey Inscribed "Dirty Birds!" (JSA) | B29: =Inventory!Y26 -> Jersey | C29: =Inventory!N26 -> 37.111781 | D29: =Inventory!T26 -> 50.939562 | H29: =IFERROR(AVERAGE(E29:G29),0) -> 0 | J29: =MAX(IF(AND(I29<>"",I29>0),I29,IF(AND(H29<>"",H29>0),H29,D29*1.2)),D29*1.2) -> 61.127474 | K29: =HYPERLINK("https://www.ebay.com/sch/i.html?_nkw="&SUBSTITUTE(SUBSTITUTE(A29," ","+"),"""","")&"&LH_Sold=1&LH_Complete=1&_sop=13","🔗 View Sold Comps") -> 🔗 View Sold Comps
A30: =Inventory!A27 -> Rob Gronkowski Signed Jersey | B30: =Inventory!Y27 -> Jersey | C30: =Inventory!N27 -> 29.653219 | D30: =Inventory!T27 -> 43.309501 | H30: =IFERROR(AVERAGE(E30:G30),0) -> 0 | J30: =MAX(IF(AND(I30<>"",I30>0),I30,IF(AND(H30<>"",H30>0),H30,D30*1.2)),D30*1.2) -> 51.971401 | K30: =HYPERLINK("https://www.ebay.com/sch/i.html?_nkw="&SUBSTITUTE(SUBSTITUTE(A30," ","+"),"""","")&"&LH_Sold=1&LH_Complete=1&_sop=13","🔗 View Sold Comps") -> 🔗 View Sold Comps
A31: =Inventory!A28 -> Joe Johnson Signed Jersey (PSA) | B31: =Inventory!Y28 -> Jersey | C31: =Inventory!N28 -> 29.653219 | D31: =Inventory!T28 -> 43.309501 | H31: =IFERROR(AVERAGE(E31:G31),0) -> 0 | J31: =MAX(IF(AND(I31<>"",I31>0),I31,IF(AND(H31<>"",H31>0),H31,D31*1.2)),D31*1.2) -> 51.971401 | K31: =HYPERLINK("https://www.ebay.com/sch/i.html?_nkw="&SUBSTITUTE(SUBSTITUTE(A31," ","+"),"""","")&"&LH_Sold=1&LH_Complete=1&_sop=13","🔗 View Sold Comps") -> 🔗 View Sold Comps
A32: =Inventory!A29 -> Moses Moody Signed Jersey (Beckett) | B32: =Inventory!Y29 -> Jersey | C32: =Inventory!N29 -> 13.483171 | D32: =Inventory!T29 -> 23.591633 | H32: =IFERROR(AVERAGE(E32:G32),0) -> 0 | J32: =MAX(IF(AND(I32<>"",I32>0),I32,IF(AND(H32<>"",H32>0),H32,D32*1.2)),D32*1.2) -> 28.309959 | K32: =HYPERLINK("https://www.ebay.com/sch/i.html?_nkw="&SUBSTITUTE(SUBSTITUTE(A32," ","+"),"""","")&"&LH_Sold=1&LH_Complete=1&_sop=13","🔗 View Sold Comps") -> 🔗 View Sold Comps
A33: =Inventory!A30 -> Grayson Allen Signed Jersey (Beckett) | B33: =Inventory!Y30 -> Jersey | C33: =Inventory!N30 -> 16.858537 | D33: =Inventory!T30 -> 27.498307 | H33: =IFERROR(AVERAGE(E33:G33),0) -> 0 | J33: =MAX(IF(AND(I33<>"",I33>0),I33,IF(AND(H33<>"",H33>0),H33,D33*1.2)),D33*1.2) -> 32.997968 | K33: =HYPERLINK("https://www.ebay.com/sch/i.html?_nkw="&SUBSTITUTE(SUBSTITUTE(A33," ","+"),"""","")&"&LH_Sold=1&LH_Complete=1&_sop=13","🔗 View Sold Comps") -> 🔗 View Sold Comps
A34: =Inventory!A31 -> Sam Hauser Signed Jersey (Beckett) | B34: =Inventory!Y31 -> Jersey | C34: =Inventory!N31 -> 14.608293 | D34: =Inventory!T31 -> 24.893857 | H34: =IFERROR(AVERAGE(E34:G34),0) -> 0 | J34: =MAX(IF(AND(I34<>"",I34>0),I34,IF(AND(H34<>"",H34>0),H34,D34*1.2)),D34*1.2) -> 29.872629 | K34: =HYPERLINK("https://www.ebay.com/sch/i.html?_nkw="&SUBSTITUTE(SUBSTITUTE(A34," ","+"),"""","")&"&LH_Sold=1&LH_Complete=1&_sop=13","🔗 View Sold Comps") -> 🔗 View Sold Comps
A35: =Inventory!A32 -> Charlie Sheen, Tom Berenger & Corbin Bernsen Signed Jersey (Beckett) | B35: =Inventory!Y32 -> Jersey | C35: =Inventory!N32 -> 72.346756 | D35: =Inventory!T32 -> 95.020091 | E35: 149 | F35: 160 | G35: 149 | H35: =IFERROR(AVERAGE(E35:G35),0) -> 152.66667 | J35: =MAX(IF(AND(I35<>"",I35>0),I35,IF(AND(H35<>"",H35>0),H35,D35*1.2)),D35*1.2) -> 152.66667 | K35: =HYPERLINK("https://www.ebay.com/sch/i.html?_nkw="&SUBSTITUTE(SUBSTITUTE(A35," ","+"),"""","")&"&LH_Sold=1&LH_Complete=1&_sop=13","🔗 View Sold Comps") -> 🔗 View Sold Comps
A36: =Inventory!A33 -> Trey Lance Signed Jersey (Beckett) | B36: =Inventory!Y33 -> Jersey | C36: =Inventory!N33 -> 17.943144 | D36: =Inventory!T33 -> 29.787942 | H36: =IFERROR(AVERAGE(E36:G36),0) -> 0 | J36: =MAX(IF(AND(I36<>"",I36>0),I36,IF(AND(H36<>"",H36>0),H36,D36*1.2)),D36*1.2) -> 35.745531 | K36: =HYPERLINK("https://www.ebay.com/sch/i.html?_nkw="&SUBSTITUTE(SUBSTITUTE(A36," ","+"),"""","")&"&LH_Sold=1&LH_Complete=1&_sop=13","🔗 View Sold Comps") -> 🔗 View Sold Comps
A37: =Inventory!A34 -> Chad Smith Signed 16" Drum Stick (Beckett) | B37: =Inventory!Y34 -> Drum Stick | C37: =Inventory!N34 -> 47.480319 | D37: =Inventory!T34 -> 65.204219 | E37: 119.99 | F37: 99 | G37: 89 | H37: =IFERROR(AVERAGE(E37:G37),0) -> 102.66333 | J37: =MAX(IF(AND(I37<>"",I37>0),I37,IF(AND(H37<>"",H37>0),H37,D37*1.2)),D37*1.2) -> 102.66333 | K37: =HYPERLINK("https://www.ebay.com/sch/i.html?_nkw="&SUBSTITUTE(SUBSTITUTE(A37," ","+"),"""","")&"&LH_Sold=1&LH_Complete=1&_sop=13","🔗 View Sold Comps") -> 🔗 View Sold Comps
A38: =Inventory!A35 -> Andre Rison Signed NFL Football Inscribed "Bad Moon" (Schwartz) | B38: =Inventory!Y35 -> Football | C38: =Inventory!N35 -> 33.909781 | D38: =Inventory!T35 -> 47.233543 | E38: 35 | F38: 35 | H38: =IFERROR(AVERAGE(E38:G38),0) -> 35 | J38: =MAX(IF(AND(I38<>"",I38>0),I38,IF(AND(H38<>"",H38>0),H38,D38*1.2)),D38*1.2) -> 56.680252 | K38: =HYPERLINK("https://www.ebay.com/sch/i.html?_nkw="&SUBSTITUTE(SUBSTITUTE(A38," ","+"),"""","")&"&LH_Sold=1&LH_Complete=1&_sop=13","🔗 View Sold Comps") -> 🔗 View Sold Comps
A42: HOW TO ENABLE LIVE eBay COMP PULL-IN (Power Query)
A43: 1. In Excel, go to Data → Get Data → From Other Sources → From Web.
A44: 2. Paste any URL from column K (they are pre-built eBay Sold Listings search URLs).
A45: 3. In the Power Query Navigator, choose the HTML table containing sold prices, then click "Transform Data".
A46: 4. Filter to only completed/sold rows, keep the Price column, remove nulls, and rename the query "eBay_Comps_[Item]".
A47: 5. Click Close & Load To → Only Create Connection. Then in a helper column, use =AVERAGE() over the returned range.
A48: 6. Alternative easier route: use an add-in like "Terapeak" (built into eBay Seller Hub) — export CSV, then use Data → From File → From CSV.
A49: 7. Once loaded, point cell I5 (Live Avg) to the query output cell — e.g., ="eBay_Comps_Kemp"!B2. Copy down.
A50: 8. Right-click any query → Refresh, or Data → Refresh All (Ctrl+Alt+F5) to pull fresh comps anytime.
A51: ⚠ Note: eBay rate-limits scraping. Refresh sparingly (once per session) or use Terapeak API for higher volume.

Sheet Categories
A1: CATEGORY & PERFORMANCE BREAKDOWN
A3: BY CATEGORY
A4: Category | B4: # Items | C4: Total True Cost | D4: Avg Cost | E4: Items Sold | F4: Realized Revenue | G4: Realized Profit | H4: Avg Margin %
A5: Jersey | B5: =COUNTIF(Inventory!$Y$2:$Y$35,A5) -> 19 | C5: =SUMIF(Inventory!$Y$2:$Y$35,A5,Inventory!$N$2:$N$35) -> 568.9121 | D5: =IFERROR(C5/B5,0) -> 29.942742 | E5: =COUNTIFS('Sales Log'!$V$4:$V$303,A5,'Sales Log'!$F$4:$F$303,">0") -> 0 | F5: =SUMIFS('Sales Log'!$F$4:$F$303,'Sales Log'!$V$4:$V$303,A5) -> 0 | G5: =SUMIFS('Sales Log'!$P$4:$P$303,'Sales Log'!$V$4:$V$303,A5) -> 0 | H5: =IFERROR(G5/F5,0) -> 0
A6: Photo | B6: =COUNTIF(Inventory!$Y$2:$Y$35,A6) -> 4 | C6: =SUMIF(Inventory!$Y$2:$Y$35,A6,Inventory!$N$2:$N$35) -> 96.648704 | D6: =IFERROR(C6/B6,0) -> 24.162176 | E6: =COUNTIFS('Sales Log'!$V$4:$V$303,A6,'Sales Log'!$F$4:$F$303,">0") -> 0 | F6: =SUMIFS('Sales Log'!$F$4:$F$303,'Sales Log'!$V$4:$V$303,A6) -> 0 | G6: =SUMIFS('Sales Log'!$P$4:$P$303,'Sales Log'!$V$4:$V$303,A6) -> 0 | H6: =IFERROR(G6/F6,0) -> 0
A7: Baseball | B7: =COUNTIF(Inventory!$Y$2:$Y$35,A7) -> 2 | C7: =SUMIF(Inventory!$Y$2:$Y$35,A7,Inventory!$N$2:$N$35) -> 58.71374 | D7: =IFERROR(C7/B7,0) -> 29.35687 | E7: =COUNTIFS('Sales Log'!$V$4:$V$303,A7,'Sales Log'!$F$4:$F$303,">0") -> 0 | F7: =SUMIFS('Sales Log'!$F$4:$F$303,'Sales Log'!$V$4:$V$303,A7) -> 0 | G7: =SUMIFS('Sales Log'!$P$4:$P$303,'Sales Log'!$V$4:$V$303,A7) -> 0 | H7: =IFERROR(G7/F7,0) -> 0
A8: Bat | B8: =COUNTIF(Inventory!$Y$2:$Y$35,A8) -> 4 | C8: =SUMIF(Inventory!$Y$2:$Y$35,A8,Inventory!$N$2:$N$35) -> 153.63705 | D8: =IFERROR(C8/B8,0) -> 38.409262 | E8: =COUNTIFS('Sales Log'!$V$4:$V$303,A8,'Sales Log'!$F$4:$F$303,">0") -> 0 | F8: =SUMIFS('Sales Log'!$F$4:$F$303,'Sales Log'!$V$4:$V$303,A8) -> 0 | G8: =SUMIFS('Sales Log'!$P$4:$P$303,'Sales Log'!$V$4:$V$303,A8) -> 0 | H8: =IFERROR(G8/F8,0) -> 0
A9: Football | B9: =COUNTIF(Inventory!$Y$2:$Y$35,A9) -> 2 | C9: =SUMIF(Inventory!$Y$2:$Y$35,A9,Inventory!$N$2:$N$35) -> 69.589781 | D9: =IFERROR(C9/B9,0) -> 34.794891 | E9: =COUNTIFS('Sales Log'!$V$4:$V$303,A9,'Sales Log'!$F$4:$F$303,">0") -> 0 | F9: =SUMIFS('Sales Log'!$F$4:$F$303,'Sales Log'!$V$4:$V$303,A9) -> 0 | G9: =SUMIFS('Sales Log'!$P$4:$P$303,'Sales Log'!$V$4:$V$303,A9) -> 0 | H9: =IFERROR(G9/F9,0) -> 0
A10: Mask | B10: =COUNTIF(Inventory!$Y$2:$Y$35,A10) -> 1 | C10: =SUMIF(Inventory!$Y$2:$Y$35,A10,Inventory!$N$2:$N$35) -> 55.90334 | D10: =IFERROR(C10/B10,0) -> 55.90334 | E10: =COUNTIFS('Sales Log'!$V$4:$V$303,A10,'Sales Log'!$F$4:$F$303,">0") -> 0 | F10: =SUMIFS('Sales Log'!$F$4:$F$303,'Sales Log'!$V$4:$V$303,A10) -> 0 | G10: =SUMIFS('Sales Log'!$P$4:$P$303,'Sales Log'!$V$4:$V$303,A10) -> 0 | H10: =IFERROR(G10/F10,0) -> 0
A11: Drum Stick | B11: =COUNTIF(Inventory!$Y$2:$Y$35,A11) -> 1 | C11: =SUMIF(Inventory!$Y$2:$Y$35,A11,Inventory!$N$2:$N$35) -> 47.480319 | D11: =IFERROR(C11/B11,0) -> 47.480319 | E11: =COUNTIFS('Sales Log'!$V$4:$V$303,A11,'Sales Log'!$F$4:$F$303,">0") -> 0 | F11: =SUMIFS('Sales Log'!$F$4:$F$303,'Sales Log'!$V$4:$V$303,A11) -> 0 | G11: =SUMIFS('Sales Log'!$P$4:$P$303,'Sales Log'!$V$4:$V$303,A11) -> 0 | H11: =IFERROR(G11/F11,0) -> 0
A12: Card | B12: =COUNTIF(Inventory!$Y$2:$Y$35,A12) -> 1 | C12: =SUMIF(Inventory!$Y$2:$Y$35,A12,Inventory!$N$2:$N$35) -> 16.254971 | D12: =IFERROR(C12/B12,0) -> 16.254971 | E12: =COUNTIFS('Sales Log'!$V$4:$V$303,A12,'Sales Log'!$F$4:$F$303,">0") -> 0 | F12: =SUMIFS('Sales Log'!$F$4:$F$303,'Sales Log'!$V$4:$V$303,A12) -> 0 | G12: =SUMIFS('Sales Log'!$P$4:$P$303,'Sales Log'!$V$4:$V$303,A12) -> 0 | H12: =IFERROR(G12/F12,0) -> 0
A13: Other | B13: =COUNTIF(Inventory!$Y$2:$Y$35,A13) -> 0 | C13: =SUMIF(Inventory!$Y$2:$Y$35,A13,Inventory!$N$2:$N$35) -> 0 | D13: =IFERROR(C13/B13,0) -> 0 | E13: =COUNTIFS('Sales Log'!$V$4:$V$303,A13,'Sales Log'!$F$4:$F$303,">0") -> 0 | F13: =SUMIFS('Sales Log'!$F$4:$F$303,'Sales Log'!$V$4:$V$303,A13) -> 0 | G13: =SUMIFS('Sales Log'!$P$4:$P$303,'Sales Log'!$V$4:$V$303,A13) -> 0 | H13: =IFERROR(G13/F13,0) -> 0
A16: BY AUTHENTICATOR
A17: Authenticator | B17: # Items | C17: Total True Cost | D17: Avg Cost | E17: Items Sold | F17: Realized Revenue | G17: Realized Profit | H17: Avg Margin %
A18: Beckett | B18: =COUNTIF(Inventory!$AB$2:$AB$35,A18) -> 16 | C18: =SUMIF(Inventory!$AB$2:$AB$35,A18,Inventory!$N$2:$N$35) -> 492.12617 | D18: =IFERROR(C18/B18,0) -> 30.757886 | E18: =COUNTIFS('Sales Log'!$W$4:$W$303,A18,'Sales Log'!$F$4:$F$303,">0") -> 0 | F18: =SUMIFS('Sales Log'!$F$4:$F$303,'Sales Log'!$W$4:$W$303,A18) -> 0 | G18: =SUMIFS('Sales Log'!$P$4:$P$303,'Sales Log'!$W$4:$W$303,A18) -> 0 | H18: =IFERROR(G18/F18,0) -> 0
A19: JSA | B19: =COUNTIF(Inventory!$AB$2:$AB$35,A19) -> 13 | C19: =SUMIF(Inventory!$AB$2:$AB$35,A19,Inventory!$N$2:$N$35) -> 418.51333 | D19: =IFERROR(C19/B19,0) -> 32.193333 | E19: =COUNTIFS('Sales Log'!$W$4:$W$303,A19,'Sales Log'!$F$4:$F$303,">0") -> 0 | F19: =SUMIFS('Sales Log'!$F$4:$F$303,'Sales Log'!$W$4:$W$303,A19) -> 0 | G19: =SUMIFS('Sales Log'!$P$4:$P$303,'Sales Log'!$W$4:$W$303,A19) -> 0 | H19: =IFERROR(G19/F19,0) -> 0
A20: PSA | B20: =COUNTIF(Inventory!$AB$2:$AB$35,A20) -> 1 | C20: =SUMIF(Inventory!$AB$2:$AB$35,A20,Inventory!$N$2:$N$35) -> 29.653219 | D20: =IFERROR(C20/B20,0) -> 29.653219 | E20: =COUNTIFS('Sales Log'!$W$4:$W$303,A20,'Sales Log'!$F$4:$F$303,">0") -> 0 | F20: =SUMIFS('Sales Log'!$F$4:$F$303,'Sales Log'!$W$4:$W$303,A20) -> 0 | G20: =SUMIFS('Sales Log'!$P$4:$P$303,'Sales Log'!$W$4:$W$303,A20) -> 0 | H20: =IFERROR(G20/F20,0) -> 0
A21: ACOA | B21: =COUNTIF(Inventory!$AB$2:$AB$35,A21) -> 2 | C21: =SUMIF(Inventory!$AB$2:$AB$35,A21,Inventory!$N$2:$N$35) -> 63.284282 | D21: =IFERROR(C21/B21,0) -> 31.642141 | E21: =COUNTIFS('Sales Log'!$W$4:$W$303,A21,'Sales Log'!$F$4:$F$303,">0") -> 0 | F21: =SUMIFS('Sales Log'!$F$4:$F$303,'Sales Log'!$W$4:$W$303,A21) -> 0 | G21: =SUMIFS('Sales Log'!$P$4:$P$303,'Sales Log'!$W$4:$W$303,A21) -> 0 | H21: =IFERROR(G21/F21,0) -> 0
A22: Schwartz | B22: =COUNTIF(Inventory!$AB$2:$AB$35,A22) -> 1 | C22: =SUMIF(Inventory!$AB$2:$AB$35,A22,Inventory!$N$2:$N$35) -> 33.909781 | D22: =IFERROR(C22/B22,0) -> 33.909781 | E22: =COUNTIFS('Sales Log'!$W$4:$W$303,A22,'Sales Log'!$F$4:$F$303,">0") -> 0 | F22: =SUMIFS('Sales Log'!$F$4:$F$303,'Sales Log'!$W$4:$W$303,A22) -> 0 | G22: =SUMIFS('Sales Log'!$P$4:$P$303,'Sales Log'!$W$4:$W$303,A22) -> 0 | H22: =IFERROR(G22/F22,0) -> 0
A23: Unlabeled | B23: =COUNTIF(Inventory!$AB$2:$AB$35,A23) -> 1 | C23: =SUMIF(Inventory!$AB$2:$AB$35,A23,Inventory!$N$2:$N$35) -> 29.653219 | D23: =IFERROR(C23/B23,0) -> 29.653219 | E23: =COUNTIFS('Sales Log'!$W$4:$W$303,A23,'Sales Log'!$F$4:$F$303,">0") -> 0 | F23: =SUMIFS('Sales Log'!$F$4:$F$303,'Sales Log'!$W$4:$W$303,A23) -> 0 | G23: =SUMIFS('Sales Log'!$P$4:$P$303,'Sales Log'!$W$4:$W$303,A23) -> 0 | H23: =IFERROR(G23/F23,0) -> 0

Sheet Fee Reference
A1: PLATFORM FEE REFERENCE
A3: Platform | B3: Fee % | C3: Flat Fee ($) | D3: Notes
A4: eBay | B4: 0.136 | C4: 0.4 | D4: 13.6% final value fee + $0.40 per order (avg)
A5: eBay (Promoted 2%) | B5: 0.156 | C5: 0.4 | D5: FVF + 2% promoted listing rate
A6: eBay (Promoted 5%) | B6: 0.186 | C6: 0.4 | D6: FVF + 5% promoted listing rate
A7: Facebook Marketplace (Local) | B7: 0 | C7: 0 | D7: No fees for local pickup
A8: Facebook Marketplace (Shipped) | B8: 0.05 | C8: 0 | D8: 5% seller fee on shipped orders
A9: OfferUp | B9: 0.129 | C9: 0 | D9: 12.9% on shipped orders
A10: Mercari | B10: 0.1 | C10: 0 | D10: 10% seller fee + payment processing
A11: Whatnot (Live) | B11: 0.08 | C11: 0.3 | D11: 8% + $0.30, live auction platform
A12: COMC | B12: 0.2 | C12: 0 | D12: Consignment ~20% depending on tier
A13: Craigslist | B13: 0 | C13: 0 | D13: No fees — local only
A14: PWCC | B14: 0.2 | C14: 0 | D14: Vault/consignment ~20%
A15: Other | B15: 0 | C15: 0 | D15: Custom
